Workbook

Sheet START HERE
A1: FINANCIAL CAPACITY EVALUATION WORKBOOK
A2: Calculation and screening aid for evaluation committees — simple, traceable, and consistent.
A4: USE THIS ORDER — DO NOT START WITH THE RATIOS
A5: 1 | B5: Read the financial statements. | C5: Start with the Income Statement, then the Balance Sheet, then the Cash Flow Statement.
A6: 2 | B6: Use the STATEMENT MAP. | C6: Find the correct line item before entering any number.
A7: 3 | B7: Enter figures in yellow cells only. | C7: Leave missing figures blank. Do not guess.
A8: 4 | B8: Review RATIO RESULTS and DASHBOARD. | C8: These are screening aids, not final decisions.
A9: 5 | B9: Use FINDING BUILDER. | C9: Copy wording only after checking the source figures.
A11: THE PLAIN TEST
A12: Can the bidder make money? | B12: Check Gross Profit Margin and Net Profit Margin.
A13: Can the bidder pay bills? | B13: Check Current Ratio, Quick Ratio, Cash, Current Liabilities and Working Capital.
A14: Is the bidder too dependent on debt? | B14: Check Debt-to-Equity, Equity Ratio and Interest Cover where available.
A15: Is cash tied up? | B15: Check Receivables Turnover, Collection Days, Work in Progress and related-party balances.
A17: COMMITTEE RULE
A18: Every figure must have a home: statement, year and line item. If the figure cannot be traced, do not use it. A ratio is a signal, not a verdict.

Sheet DATA ENTRY
A1: DATA ENTRY — TYPE ONLY IN YELLOW CELLS
A2: Enter one row per bidder and financial year. Use the same financial year for income statement and balance sheet figures where possible. If a figure is missing, leave it blank and record the limitation in Source Note/Page.
A5: Record No. | B5: Bidder / Company | C5: Sector | D5: Financial Year | E5: Statement Status | F5: Contract Value (TTD) | G5: Revenue | H5: Cost of Sales / Direct Costs | I5: Gross Profit (if shown) | J5: Net Profit After Tax | K5: Current Assets | L5: Cash at Bank | M5: Trade Receivables - Current Year | N5: Trade Receivables - Prior Year | O5: Inventory / Stock | P5: Work in Progress | Q5: Total Assets | R5: Current Liabilities | S5: Non-current Liabilities | T5: Total Liabilities | U5: Total Equity | V5: Operating Profit / EBIT | W5: Interest Expense | X5: Source Note / Page | Y5: Figure Check Complete?
A6: =IF($B6<>"",ROW()-5,"")
A7: =IF($B7<>"",ROW()-5,"")
A8: =IF($B8<>"",ROW()-5,"")
A9: =IF($B9<>"",ROW()-5,"")
A10: =IF($B10<>"",ROW()-5,"")
A11: =IF($B11<>"",ROW()-5,"")
A12: =IF($B12<>"",ROW()-5,"")
A13: =IF($B13<>"",ROW()-5,"")
A14: =IF($B14<>"",ROW()-5,"")
A15: =IF($B15<>"",ROW()-5,"")
A16: =IF($B16<>"",ROW()-5,"")
A17: =IF($B17<>"",ROW()-5,"")
... A35: =IF($B35<>"",ROW()-5,"")

Sheet RATIO RESULTS
A1: RATIO RESULTS — AUTOMATIC CALCULATION AND SCREENING
A2: Do not type here. This sheet calculates ratios from DATA ENTRY. Ratings are first-pass screening only and do not replace approved evaluation criteria.
A5: Record No. | B5: Bidder / Company | C5: Sector | D5: Year | E5: Statement Status | F5: Data Check | G5: Gross Profit Used | H5: Gross Profit Margin | I5: GPM Rating | J5: Net Profit Margin | K5: NPM Rating | L5: ROA | M5: ROA Rating | N5: ROE | O5: ROE Rating | P5: Current Ratio | Q5: CR Rating | R5: Quick Ratio | S5: QR Rating | T5: Debt-to-Equity | U5: D/E Rating | V5: Equity Ratio | W5: Equity Rating | X5: Receivables Turnover | Y5: Collection Days | Z5: Receivables Rating | AA5: Asset Turnover | AB5: Asset Rating | AC5: Working Capital | AD5: WC Rating | AE5: Interest Cover | AF5: ICR Rating | AG5: Overall Score | AH5: Overall Screening Rating | AI5: Main Flag
A6: =IF('DATA ENTRY'!$B6<>"",'DATA ENTRY'!$A6,"") | B6: =IF('DATA ENTRY'!$B6<>"",'DATA ENTRY'!$B6,"") | C6: =IF('DATA ENTRY'!$B6<>"",'DATA ENTRY'!$C6,"") | D6: =IF('DATA ENTRY'!$B6<>"",'DATA ENTRY'!$D6,"") | E6: =IF('DATA ENTRY'!$B6<>"",'DATA ENTRY'!$E6,"") | F6: =IF($B6="","",IF('DATA ENTRY'!$Y6="Yes","Checked",IF('DATA ENTRY'!$Y6="No","Needs check","Not marked"))) | G6: =IF($B6="","",IF('DATA ENTRY'!$I6<>"",'DATA ENTRY'!$I6,IF(AND('DATA ENTRY'!$G6<>"",'DATA ENTRY'!$H6<>""),'DATA ENTRY'!$G6-'DATA ENTRY'!$H6,""))) | H6: =IF(OR($B6="",$G6="",'DATA ENTRY'!$G6=""),"",IFERROR($G6/'DATA ENTRY'!$G6,"")) | I6: =IF($B6="","",IF($H6="","Not entered",IF($H6>=0.25,"Strong",IF($H6>=0.15,"Adequate",IF($H6>=0.05,"Caution","High-risk"))))) | J6: =IF(OR($B6="",'DATA ENTRY'!$J6="",'DATA ENTRY'!$G6=""),"",IFERROR('DATA ENTRY'!$J6/'DATA ENTRY'!$G6,"")) | K6: =IF($B6="","",IF($J6="","Not entered",IF($J6>=0.08,"Strong",IF($J6>=0.03,"Adequate",IF($J6>=0,"Caution","High-risk"))))) | L6: =IF(OR($B6="",'DATA ENTRY'!$J6="",'DATA ENTRY'!$Q6=""),"",IFERROR('DATA ENTRY'!$J6/'DATA ENTRY'!$Q6,"")) | M6: =IF($B6="","",IF($L6="","Not entered",IF($L6>=0.1,"Strong",IF($L6>=0.05,"Adequate",IF($L6>=0,"Caution","High-risk"))))) | N6: =IF(OR($B6="",'DATA ENTRY'!$J6="",'DATA ENTRY'!$U6="",'DATA ENTRY'!$U6<=0),"",IFERROR('DATA ENTRY'!$J6/'DATA ENTRY'!$U6,"")) | O6: =IF($B6="","",IF(OR('DATA ENTRY'!$J6="",'DATA ENTRY'!$U6=""),"Not entered",IF('DATA ENTRY'!$U6<=0,"High-risk",IF($N6>=0.15,"Strong",IF($N6>=0.08,"Adequate",IF($N6>=0,"Caution","High-risk")))))) | P6: =IF(OR($B6="",'DATA ENTRY'!$K6="",'DATA ENTRY'!$R6=""),"",IFERROR('DATA ENTRY'!$K6/'DATA ENTRY'!$R6,"")) | Q6: =IF($B6="","",IF($P6="","Not entered",IF($P6>=1.5,"Strong",IF($P6>=1.2,"Adequate",IF($P6>=1,"Caution","High-risk"))))) | R6: =IF(OR($B6="",'DATA ENTRY'!$K6="",'DATA ENTRY'!$R6=""),"",IFERROR(('DATA ENTRY'!$K6-IF('DATA ENTRY'!$O6="",0,'DATA ENTRY'!$O6))/'DATA ENTRY'!$R6,"")) | S6: =IF($B6="","",IF($R6="","Not entered",IF($R6>=1,"Strong",IF($R6>=0.8,"Adequate",IF($R6>=0.6,"Caution","High-risk"))))) | T6: =IF(OR($B6="",'DATA ENTRY'!$T6="",'DATA ENTRY'!$U6="",'DATA ENTRY'!$U6<=0),"",IFERROR('DATA ENTRY'!$T6/'DATA ENTRY'!$U6,"")) | U6: =IF($B6="","",IF(OR('DATA ENTRY'!$T6="",'DATA ENTRY'!$U6=""),"Not entered",IF('DATA ENTRY'!$U6<=0,"High-risk",IF($T6<=1,"Strong",IF($T6<=1.5,"Adequate",IF($T6<=2,"Caution","High-risk")))))) | V6: =IF(OR($B6="",'DATA ENTRY'!$U6="",'DATA ENTRY'!$Q6=""),"",IFERROR('DATA ENTRY'!$U6/'DATA ENTRY'!$Q6,"")) | W6: =IF($B6="","",IF($V6="","Not entered",IF($V6>=0.5,"Strong",IF($V6>=0.3,"Adequate",IF($V6>=0.2,"Caution","High-risk"))))) | X6: =IF(OR($B6="",'DATA ENTRY'!$G6="",'DATA ENTRY'!$M6=""),"",IF('DATA ENTRY'!$N6<>"",'DATA ENTRY'!$G6/AVERAGE('DATA ENTRY'!$M6,'DATA ENTRY'!$N6),IFERROR('DATA ENTRY'!$G6/'DATA ENTRY'!$M6,""))) | Y6: =IF($X6="","",IFERROR(365/$X6,"")) | Z6: =IF($B6="","",IF($X6="","Not entered",IF($Y6<=60,"Strong",IF($Y6<=90,"Adequate",IF($Y6<=120,"Caution","High-risk"))))) | AA6: =IF(OR($B6="",'DATA ENTRY'!$G6="",'DATA ENTRY'!$Q6=""),"",IFERROR('DATA ENTRY'!$G6/'DATA ENTRY'!$Q6,"")) | AB6: =IF($B6="","",IF($AA6="","Not entered",IF($AA6>=1.5,"Strong",IF($AA6>=1,"Adequate",IF($AA6>=0.5,"Caution","High-risk"))))) | AC6: =IF(OR($B6="",'DATA ENTRY'!$K6="",'DATA ENTRY'!$R6=""),"",'DATA ENTRY'!$K6-'DATA ENTRY'!$R6) | AD6: =IF($B6="","",IF($AC6="","Not entered",IF($AC6<0,"High-risk",IF($AC6=0,"Caution",IF('DATA ENTRY'!$L6="","Adequate",IFERROR(IF('DATA ENTRY'!$L6/'DATA ENTRY'!$R6>=0.25,"Strong","Adequate"),"Adequate")))))) | AE6: =IF($B6="","",IF(OR('DATA ENTRY'!$W6="",'DATA ENTRY'!$W6=0),"N/A",IF('DATA ENTRY'!$V6="","",IFERROR('DATA ENTRY'!$V6/'DATA ENTRY'!$W6,"")))) | AF6: =IF($B6="","",IF($AE6="N/A","Not applicable",IF($AE6="","Not entered",IF($AE6>=4,"Strong",IF($AE6>=2.5,"Adequate",IF($AE6>=1.5,"Caution","High-risk")))))) | AG6: =IF($B6="","",IFERROR(ROUND((COUNTIF($I6:$AF6,"Strong")*4+COUNTIF($I6:$AF6,"Adequate")*3+COUNTIF($I6:$AF6,"Caution")*2+COUNTIF($I6:$AF6,"High-risk")*1)/(COUNTIF($I6:$AF6,"Strong")+COUNTIF($I6:$AF6,"Adequate")+COUNTIF($I6:$AF6,"Caution")+COUNTIF($I6:$AF6,"High-risk")),2),"")) | AH6: =IF($B6="","",IF(AND(ISNUMBER('DATA ENTRY'!$U6),'DATA ENTRY'!$U6<=0),"Financially stretched",IF($AG6="","Insufficient data",IF(AND(ISNUMBER('DATA ENTRY'!$J6),'DATA ENTRY'!$J6<0),IF($AG6>=2,"Adequate with caution","Financially stretched"),IF($AG6>=3.5,"Financially strong",IF($AG6>=2.75,"Financially adequate",IF($AG6>=2,"Adequate with caution","Financially stretched"))))))) | AI6: =IF($B6="","",IF(AND(ISNUMBER('DATA ENTRY'!$U6),'DATA ENTRY'!$U6<=0),"Negative equity — possible insolvency",IF(AND(ISNUMBER('DATA ENTRY'!$J6),'DATA ENTRY'!$J6<0),"Loss position",IF(AND(ISNUMBER($P6),$P6<1),"Current liabilities exceed current assets",IF(AND(ISNUMBER($T6),$T6>2),"High leverage",IF(AND(ISNUMBER($Y6),$Y6>120),"Slow receivables collection",IF(AND(ISNUMBER($AC6),$AC6<0),"Negative working capital",IF(OR('DATA ENTRY'!$E6="Unaudited",'DATA ENTRY'!$E6="Banker Letter Only",'DATA ENTRY'!$E6="Management Accounts"),"Statement status limits weight on ratios","No major red flag from entered ratios"))))))))
A7: =IF('DATA ENTRY'!$B7<>"",'DATA ENTRY'!$A7,"") | B7: =IF('DATA ENTRY'!$B7<>"",'DATA ENTRY'!$B7,"") | C7: =IF('DATA ENTRY'!$B7<>"",'DATA ENTRY'!$C7,"") | D7: =IF('DATA ENTRY'!$B7<>"",'DATA ENTRY'!$D7,"") | E7: =IF('DATA ENTRY'!$B7<>"",'DATA ENTRY'!$E7,"") | F7: =IF($B7="","",IF('DATA ENTRY'!$Y7="Yes","Checked",IF('DATA ENTRY'!$Y7="No","Needs check","Not marked"))) | G7: =IF($B7="","",IF('DATA ENTRY'!$I7<>"",'DATA ENTRY'!$I7,IF(AND('DATA ENTRY'!$G7<>"",'DATA ENTRY'!$H7<>""),'DATA ENTRY'!$G7-'DATA ENTRY'!$H7,""))) | H7: =IF(OR($B7="",$G7="",'DATA ENTRY'!$G7=""),"",IFERROR($G7/'DATA ENTRY'!$G7,"")) | I7: =IF($B7="","",IF($H7="","Not entered",IF($H7>=0.25,"Strong",IF($H7>=0.15,"Adequate",IF($H7>=0.05,"Caution","High-risk"))))) | J7: =IF(OR($B7="",'DATA ENTRY'!$J7="",'DATA ENTRY'!$G7=""),"",IFERROR('DATA ENTRY'!$J7/'DATA ENTRY'!$G7,"")) | K7: =IF($B7="","",IF($J7="","Not entered",IF($J7>=0.08,"Strong",IF($J7>=0.03,"Adequate",IF($J7>=0,"Caution","High-risk"))))) | L7: =IF(OR($B7="",'DATA ENTRY'!$J7="",'DATA ENTRY'!$Q7=""),"",IFERROR('DATA ENTRY'!$J7/'DATA ENTRY'!$Q7,"")) | M7: =IF($B7="","",IF($L7="","Not entered",IF($L7>=0.1,"Strong",IF($L7>=0.05,"Adequate",IF($L7>=0,"Caution","High-risk"))))) | N7: =IF(OR($B7="",'DATA ENTRY'!$J7="",'DATA ENTRY'!$U7="",'DATA ENTRY'!$U7<=0),"",IFERROR('DATA ENTRY'!$J7/'DATA ENTRY'!$U7,"")) | O7: =IF($B7="","",IF(OR('DATA ENTRY'!$J7="",'DATA ENTRY'!$U7=""),"Not entered",IF('DATA ENTRY'!$U7<=0,"High-risk",IF($N7>=0.15,"Strong",IF($N7>=0.08,"Adequate",IF($N7>=0,"Caution","High-risk")))))) | P7: =IF(OR($B7="",'DATA ENTRY'!$K7="",'DATA ENTRY'!$R7=""),"",IFERROR('DATA ENTRY'!$K7/'DATA ENTRY'!$R7,"")) | Q7: =IF($B7="","",IF($P7="","Not entered",IF($P7>=1.5,"Strong",IF($P7>=1.2,"Adequate",IF($P7>=1,"Caution","High-risk"))))) | R7: =IF(OR($B7="",'DATA ENTRY'!$K7="",'DATA ENTRY'!$R7=""),"",IFERROR(('DATA ENTRY'!$K7-IF('DATA ENTRY'!$O7="",0,'DATA ENTRY'!$O7))/'DATA ENTRY'!$R7,"")) | S7: =IF($B7="","",IF($R7="","Not entered",IF($R7>=1,"Strong",IF($R7>=0.8,"Adequate",IF($R7>=0.6,"Caution","High-risk"))))) | T7: =IF(OR($B7="",'DATA ENTRY'!$T7="",'DATA ENTRY'!$U7="",'DATA ENTRY'!$U7<=0),"",IFERROR('DATA ENTRY'!$T7/'DATA ENTRY'!$U7,"")) | U7: =IF($B7="","",IF(OR('DATA ENTRY'!$T7="",'DATA ENTRY'!$U7=""),"Not entered",IF('DATA ENTRY'!$U7<=0,"High-risk",IF($T7<=1,"Strong",IF($T7<=1.5,"Adequate",IF($T7<=2,"Caution","High-risk")))))) | V7: =IF(OR($B7="",'DATA ENTRY'!$U7="",'DATA ENTRY'!$Q7=""),"",IFERROR('DATA ENTRY'!$U7/'DATA ENTRY'!$Q7,"")) | W7: =IF($B7="","",IF($V7="","Not entered",IF($V7>=0.5,"Strong",IF($V7>=0.3,"Adequate",IF($V7>=0.2,"Caution","High-risk"))))) | X7: =IF(OR($B7="",'DATA ENTRY'!$G7="",'DATA ENTRY'!$M7=""),"",IF('DATA ENTRY'!$N7<>"",'DATA ENTRY'!$G7/AVERAGE('DATA ENTRY'!$M7,'DATA ENTRY'!$N7),IFERROR('DATA ENTRY'!$G7/'DATA ENTRY'!$M7,""))) | Y7: =IF($X7="","",IFERROR(365/$X7,"")) | Z7: =IF($B7="","",IF($X7="","Not entered",IF($Y7<=60,"Strong",IF($Y7<=90,"Adequate",IF($Y7<=120,"Caution","High-risk"))))) | AA7: =IF(OR($B7="",'DATA ENTRY'!$G7="",'DATA ENTRY'!$Q7=""),"",IFERROR('DATA ENTRY'!$G7/'DATA ENTRY'!$Q7,"")) | AB7: =IF($B7="","",IF($AA7="","Not entered",IF($AA7>=1.5,"Strong",IF($AA7>=1,"Adequate",IF($AA7>=0.5,"Caution","High-risk"))))) | AC7: =IF(OR($B7="",'DATA ENTRY'!$K7="",'DATA ENTRY'!$R7=""),"",'DATA ENTRY'!$K7-'DATA ENTRY'!$R7) | AD7: =IF($B7="","",IF($AC7="","Not entered",IF($AC7<0,"High-risk",IF($AC7=0,"Caution",IF('DATA ENTRY'!$L7="","Adequate",IFERROR(IF('DATA ENTRY'!$L7/'DATA ENTRY'!$R7>=0.25,"Strong","Adequate"),"Adequate")))))) | AE7: =IF($B7="","",IF(OR('DATA ENTRY'!$W7="",'DATA ENTRY'!$W7=0),"N/A",IF('DATA ENTRY'!$V7="","",IFERROR('DATA ENTRY'!$V7/'DATA ENTRY'!$W7,"")))) | AF7: =IF($B7="","",IF($AE7="N/A","Not applicable",IF($AE7="","Not entered",IF($AE7>=4,"Strong",IF($AE7>=2.5,"Adequate",IF($AE7>=1.5,"Caution","High-risk")))))) | AG7: =IF($B7="","",IFERROR(ROUND((COUNTIF($I7:$AF7,"Strong")*4+COUNTIF($I7:$AF7,"Adequate")*3+COUNTIF($I7:$AF7,"Caution")*2+COUNTIF($I7:$AF7,"High-risk")*1)/(COUNTIF($I7:$AF7,"Strong")+COUNTIF($I7:$AF7,"Adequate")+COUNTIF($I7:$AF7,"Caution")+COUNTIF($I7:$AF7,"High-risk")),2),"")) | AH7: =IF($B7="","",IF(AND(ISNUMBER('DATA ENTRY'!$U7),'DATA ENTRY'!$U7<=0),"Financially stretched",IF($AG7="","Insufficient data",IF(AND(ISNUMBER('DATA ENTRY'!$J7),'DATA ENTRY'!$J7<0),IF($AG7>=2,"Adequate with caution","Financially stretched"),IF($AG7>=3.5,"Financially strong",IF($AG7>=2.75,"Financially adequate",IF($AG7>=2,"Adequate with caution","Financially stretched"))))))) | AI7: =IF($B7="","",IF(AND(ISNUMBER('DATA ENTRY'!$U7),'DATA ENTRY'!$U7<=0),"Negative equity — possible insolvency",IF(AND(ISNUMBER('DATA ENTRY'!$J7),'DATA ENTRY'!$J7<0),"Loss position",IF(AND(ISNUMBER($P7),$P7<1),"Current liabilities exceed current assets",IF(AND(ISNUMBER($T7),$T7>2),"High leverage",IF(AND(ISNUMBER($Y7),$Y7>120),"Slow receivables collection",IF(AND(ISNUMBER($AC7),$AC7<0),"Negative working capital",IF(OR('DATA ENTRY'!$E7="Unaudited",'DATA ENTRY'!$E7="Banker Letter Only",'DATA ENTRY'!$E7="Management Accounts"),"Statement status limits weight on ratios","No major red flag from entered ratios"))))))))
A8: =IF('DATA ENTRY'!$B8<>"",'DATA ENTRY'!$A8,"") | B8: =IF('DATA ENTRY'!$B8<>"",'DATA ENTRY'!$B8,"") | C8: =IF('DATA ENTRY'!$B8<>"",'DATA ENTRY'!$C8,"") | D8: =IF('DATA ENTRY'!$B8<>"",'DATA ENTRY'!$D8,"") | E8: =IF('DATA ENTRY'!$B8<>"",'DATA ENTRY'!$E8,"") | F8: =IF($B8="","",IF('DATA ENTRY'!$Y8="Yes","Checked",IF('DATA ENTRY'!$Y8="No","Needs check","Not marked"))) | G8: =IF($B8="","",IF('DATA ENTRY'!$I8<>"",'DATA ENTRY'!$I8,IF(AND('DATA ENTRY'!$G8<>"",'DATA ENTRY'!$H8<>""),'DATA ENTRY'!$G8-'DATA ENTRY'!$H8,""))) | H8: =IF(OR($B8="",$G8="",'DATA ENTRY'!$G8=""),"",IFERROR($G8/'DATA ENTRY'!$G8,"")) | I8: =IF($B8="","",IF($H8="","Not entered",IF($H8>=0.25,"Strong",IF($H8>=0.15,"Adequate",IF($H8>=0.05,"Caution","High-risk"))))) | J8: =IF(OR($B8="",'DATA ENTRY'!$J8="",'DATA ENTRY'!$G8=""),"",IFERROR('DATA ENTRY'!$J8/'DATA ENTRY'!$G8,"")) | K8: =IF($B8="","",IF($J8="","Not entered",IF($J8>=0.08,"Strong",IF($J8>=0.03,"Adequate",IF($J8>=0,"Caution","High-risk"))))) | L8: =IF(OR($B8="",'DATA ENTRY'!$J8="",'DATA ENTRY'!$Q8=""),"",IFERROR('DATA ENTRY'!$J8/'DATA ENTRY'!$Q8,"")) | M8: =IF($B8="","",IF($L8="","Not entered",IF($L8>=0.1,"Strong",IF($L8>=0.05,"Adequate",IF($L8>=0,"Caution","High-risk"))))) | N8: =IF(OR($B8="",'DATA ENTRY'!$J8="",'DATA ENTRY'!$U8="",'DATA ENTRY'!$U8<=0),"",IFERROR('DATA ENTRY'!$J8/'DATA ENTRY'!$U8,"")) | O8: =IF($B8="","",IF(OR('DATA ENTRY'!$J8="",'DATA ENTRY'!$U8=""),"Not entered",IF('DATA ENTRY'!$U8<=0,"High-risk",IF($N8>=0.15,"Strong",IF($N8>=0.08,"Adequate",IF($N8>=0,"Caution","High-risk")))))) | P8: =IF(OR($B8="",'DATA ENTRY'!$K8="",'DATA ENTRY'!$R8=""),"",IFERROR('DATA ENTRY'!$K8/'DATA ENTRY'!$R8,"")) | Q8: =IF($B8="","",IF($P8="","Not entered",IF($P8>=1.5,"Strong",IF($P8>=1.2,"Adequate",IF($P8>=1,"Caution","High-risk"))))) | R8: =IF(OR($B8="",'DATA ENTRY'!$K8="",'DATA ENTRY'!$R8=""),"",IFERROR(('DATA ENTRY'!$K8-IF('DATA ENTRY'!$O8="",0,'DATA ENTRY'!$O8))/'DATA ENTRY'!$R8,"")) | S8: =IF($B8="","",IF($R8="","Not entered",IF($R8>=1,"Strong",IF($R8>=0.8,"Adequate",IF($R8>=0.6,"Caution","High-risk"))))) | T8: =IF(OR($B8="",'DATA ENTRY'!$T8="",'DATA ENTRY'!$U8="",'DATA ENTRY'!$U8<=0),"",IFERROR('DATA ENTRY'!$T8/'DATA ENTRY'!$U8,"")) | U8: =IF($B8="","",IF(OR('DATA ENTRY'!$T8="",'DATA ENTRY'!$U8=""),"Not entered",IF('DATA ENTRY'!$U8<=0,"High-risk",IF($T8<=1,"Strong",IF($T8<=1.5,"Adequate",IF($T8<=2,"Caution","High-risk")))))) | V8: =IF(OR($B8="",'DATA ENTRY'!$U8="",'DATA ENTRY'!$Q8=""),"",IFERROR('DATA ENTRY'!$U8/'DATA ENTRY'!$Q8,"")) | W8: =IF($B8="","",IF($V8="","Not entered",IF($V8>=0.5,"Strong",IF($V8>=0.3,"Adequate",IF($V8>=0.2,"Caution","High-risk"))))) | X8: =IF(OR($B8="",'DATA ENTRY'!$G8="",'DATA ENTRY'!$M8=""),"",IF('DATA ENTRY'!$N8<>"",'DATA ENTRY'!$G8/AVERAGE('DATA ENTRY'!$M8,'DATA ENTRY'!$N8),IFERROR('DATA ENTRY'!$G8/'DATA ENTRY'!$M8,""))) | Y8: =IF($X8="","",IFERROR(365/$X8,"")) | Z8: =IF($B8="","",IF($X8="","Not entered",IF($Y8<=60,"Strong",IF($Y8<=90,"Adequate",IF($Y8<=120,"Caution","High-risk"))))) | AA8: =IF(OR($B8="",'DATA ENTRY'!$G8="",'DATA ENTRY'!$Q8=""),"",IFERROR('DATA ENTRY'!$G8/'DATA ENTRY'!$Q8,"")) | AB8: =IF($B8="","",IF($AA8="","Not entered",IF($AA8>=1.5,"Strong",IF($AA8>=1,"Adequate",IF($AA8>=0.5,"Caution","High-risk"))))) | AC8: =IF(OR($B8="",'DATA ENTRY'!$K8="",'DATA ENTRY'!$R8=""),"",'DATA ENTRY'!$K8-'DATA ENTRY'!$R8) | AD8: =IF($B8="","",IF($AC8="","Not entered",IF($AC8<0,"High-risk",IF($AC8=0,"Caution",IF('DATA ENTRY'!$L8="","Adequate",IFERROR(IF('DATA ENTRY'!$L8/'DATA ENTRY'!$R8>=0.25,"Strong","Adequate"),"Adequate")))))) | AE8: =IF($B8="","",IF(OR('DATA ENTRY'!$W8="",'DATA ENTRY'!$W8=0),"N/A",IF('DATA ENTRY'!$V8="","",IFERROR('DATA ENTRY'!$V8/'DATA ENTRY'!$W8,"")))) | AF8: =IF($B8="","",IF($AE8="N/A","Not applicable",IF($AE8="","Not entered",IF($AE8>=4,"Strong",IF($AE8>=2.5,"Adequate",IF($AE8>=1.5,"Caution","High-risk")))))) | AG8: =IF($B8="","",IFERROR(ROUND((COUNTIF($I8:$AF8,"Strong")*4+COUNTIF($I8:$AF8,"Adequate")*3+COUNTIF($I8:$AF8,"Caution")*2+COUNTIF($I8:$AF8,"High-risk")*1)/(COUNTIF($I8:$AF8,"Strong")+COUNTIF($I8:$AF8,"Adequate")+COUNTIF($I8:$AF8,"Caution")+COUNTIF($I8:$AF8,"High-risk")),2),"")) | AH8: =IF($B8="","",IF(AND(ISNUMBER('DATA ENTRY'!$U8),'DATA ENTRY'!$U8<=0),"Financially stretched",IF($AG8="","Insufficient data",IF(AND(ISNUMBER('DATA ENTRY'!$J8),'DATA ENTRY'!$J8<0),IF($AG8>=2,"Adequate with caution","Financially stretched"),IF($AG8>=3.5,"Financially strong",IF($AG8>=2.75,"Financially adequate",IF($AG8>=2,"Adequate with caution","Financially stretched"))))))) | AI8: =IF($B8="","",IF(AND(ISNUMBER('DATA ENTRY'!$U8),'DATA ENTRY'!$U8<=0),"Negative equity — possible insolvency",IF(AND(ISNUMBER('DATA ENTRY'!$J8),'DATA ENTRY'!$J8<0),"Loss position",IF(AND(ISNUMBER($P8),$P8<1),"Current liabilities exceed current assets",IF(AND(ISNUMBER($T8),$T8>2),"High leverage",IF(AND(ISNUMBER($Y8),$Y8>120),"Slow receivables collection",IF(AND(ISNUMBER($AC8),$AC8<0),"Negative working capital",IF(OR('DATA ENTRY'!$E8="Unaudited",'DATA ENTRY'!$E8="Banker Letter Only",'DATA ENTRY'!$E8="Management Accounts"),"Statement status limits weight on ratios","No major red flag from entered ratios"))))))))
A9: =IF('DATA ENTRY'!$B9<>"",'DATA ENTRY'!$A9,"") | B9: =IF('DATA ENTRY'!$B9<>"",'DATA ENTRY'!$B9,"") | C9: =IF('DATA ENTRY'!$B9<>"",'DATA ENTRY'!$C9,"") | D9: =IF('DATA ENTRY'!$B9<>"",'DATA ENTRY'!$D9,"") | E9: =IF('DATA ENTRY'!$B9<>"",'DATA ENTRY'!$E9,"") | F9: =IF($B9="","",IF('DATA ENTRY'!$Y9="Yes","Checked",IF('DATA ENTRY'!$Y9="No","Needs check","Not marked"))) | G9: =IF($B9="","",IF('DATA ENTRY'!$I9<>"",'DATA ENTRY'!$I9,IF(AND('DATA ENTRY'!$G9<>"",'DATA ENTRY'!$H9<>""),'DATA ENTRY'!$G9-'DATA ENTRY'!$H9,""))) | H9: =IF(OR($B9="",$G9="",'DATA ENTRY'!$G9=""),"",IFERROR($G9/'DATA ENTRY'!$G9,"")) | I9: =IF($B9="","",IF($H9="","Not entered",IF($H9>=0.25,"Strong",IF($H9>=0.15,"Adequate",IF($H9>=0.05,"Caution","High-risk"))))) | J9: =IF(OR($B9="",'DATA ENTRY'!$J9="",'DATA ENTRY'!$G9=""),"",IFERROR('DATA ENTRY'!$J9/'DATA ENTRY'!$G9,"")) | K9: =IF($B9="","",IF($J9="","Not entered",IF($J9>=0.08,"Strong",IF($J9>=0.03,"Adequate",IF($J9>=0,"Caution","High-risk"))))) | L9: =IF(OR($B9="",'DATA ENTRY'!$J9="",'DATA ENTRY'!$Q9=""),"",IFERROR('DATA ENTRY'!$J9/'DATA ENTRY'!$Q9,"")) | M9: =IF($B9="","",IF($L9="","Not entered",IF($L9>=0.1,"Strong",IF($L9>=0.05,"Adequate",IF($L9>=0,"Caution","High-risk"))))) | N9: =IF(OR($B9="",'DATA ENTRY'!$J9="",'DATA ENTRY'!$U9="",'DATA ENTRY'!$U9<=0),"",IFERROR('DATA ENTRY'!$J9/'DATA ENTRY'!$U9,"")) | O9: =IF($B9="","",IF(OR('DATA ENTRY'!$J9="",'DATA ENTRY'!$U9=""),"Not entered",IF('DATA ENTRY'!$U9<=0,"High-risk",IF($N9>=0.15,"Strong",IF($N9>=0.08,"Adequate",IF($N9>=0,"Caution","High-risk")))))) | P9: =IF(OR($B9="",'DATA ENTRY'!$K9="",'DATA ENTRY'!$R9=""),"",IFERROR('DATA ENTRY'!$K9/'DATA ENTRY'!$R9,"")) | Q9: =IF($B9="","",IF($P9="","Not entered",IF($P9>=1.5,"Strong",IF($P9>=1.2,"Adequate",IF($P9>=1,"Caution","High-risk"))))) | R9: =IF(OR($B9="",'DATA ENTRY'!$K9="",'DATA ENTRY'!$R9=""),"",IFERROR(('DATA ENTRY'!$K9-IF('DATA ENTRY'!$O9="",0,'DATA ENTRY'!$O9))/'DATA ENTRY'!$R9,"")) | S9: =IF($B9="","",IF($R9="","Not entered",IF($R9>=1,"Strong",IF($R9>=0.8,"Adequate",IF($R9>=0.6,"Caution","High-risk"))))) | T9: =IF(OR($B9="",'DATA ENTRY'!$T9="",'DATA ENTRY'!$U9="",'DATA ENTRY'!$U9<=0),"",IFERROR('DATA ENTRY'!$T9/'DATA ENTRY'!$U9,"")) | U9: =IF($B9="","",IF(OR('DATA ENTRY'!$T9="",'DATA ENTRY'!$U9=""),"Not entered",IF('DATA ENTRY'!$U9<=0,"High-risk",IF($T9<=1,"Strong",IF($T9<=1.5,"Adequate",IF($T9<=2,"Caution","High-risk")))))) | V9: =IF(OR($B9="",'DATA ENTRY'!$U9="",'DATA ENTRY'!$Q9=""),"",IFERROR('DATA ENTRY'!$U9/'DATA ENTRY'!$Q9,"")) | W9: =IF($B9="","",IF($V9="","Not entered",IF($V9>=0.5,"Strong",IF($V9>=0.3,"Adequate",IF($V9>=0.2,"Caution","High-risk"))))) | X9: =IF(OR($B9="",'DATA ENTRY'!$G9="",'DATA ENTRY'!$M9=""),"",IF('DATA ENTRY'!$N9<>"",'DATA ENTRY'!$G9/AVERAGE('DATA ENTRY'!$M9,'DATA ENTRY'!$N9),IFERROR('DATA ENTRY'!$G9/'DATA ENTRY'!$M9,""))) | Y9: =IF($X9="","",IFERROR(365/$X9,"")) | Z9: =IF($B9="","",IF($X9="","Not entered",IF($Y9<=60,"Strong",IF($Y9<=90,"Adequate",IF($Y9<=120,"Caution","High-risk"))))) | AA9: =IF(OR($B9="",'DATA ENTRY'!$G9="",'DATA ENTRY'!$Q9=""),"",IFERROR('DATA ENTRY'!$G9/'DATA ENTRY'!$Q9,"")) | AB9: =IF($B9="","",IF($AA9="","Not entered",IF($AA9>=1.5,"Strong",IF($AA9>=1,"Adequate",IF($AA9>=0.5,"Caution","High-risk"))))) | AC9: =IF(OR($B9="",'DATA ENTRY'!$K9="",'DATA ENTRY'!$R9=""),"",'DATA ENTRY'!$K9-'DATA ENTRY'!$R9) | AD9: =IF($B9="","",IF($AC9="","Not entered",IF($AC9<0,"High-risk",IF($AC9=0,"Caution",IF('DATA ENTRY'!$L9="","Adequate",IFERROR(IF('DATA ENTRY'!$L9/'DATA ENTRY'!$R9>=0.25,"Strong","Adequate"),"Adequate")))))) | AE9: =IF($B9="","",IF(OR('DATA ENTRY'!$W9="",'DATA ENTRY'!$W9=0),"N/A",IF('DATA ENTRY'!$V9="","",IFERROR('DATA ENTRY'!$V9/'DATA ENTRY'!$W9,"")))) | AF9: =IF($B9="","",IF($AE9="N/A","Not applicable",IF($AE9="","Not entered",IF($AE9>=4,"Strong",IF($AE9>=2.5,"Adequate",IF($AE9>=1.5,"Caution","High-risk")))))) | AG9: =IF($B9="","",IFERROR(ROUND((COUNTIF($I9:$AF9,"Strong")*4+COUNTIF($I9:$AF9,"Adequate")*3+COUNTIF($I9:$AF9,"Caution")*2+COUNTIF($I9:$AF9,"High-risk")*1)/(COUNTIF($I9:$AF9,"Strong")+COUNTIF($I9:$AF9,"Adequate")+COUNTIF($I9:$AF9,"Caution")+COUNTIF($I9:$AF9,"High-risk")),2),"")) | AH9: =IF($B9="","",IF(AND(ISNUMBER('DATA ENTRY'!$U9),'DATA ENTRY'!$U9<=0),"Financially stretched",IF($AG9="","Insufficient data",IF(AND(ISNUMBER('DATA ENTRY'!$J9),'DATA ENTRY'!$J9<0),IF($AG9>=2,"Adequate with caution","Financially stretched"),IF($AG9>=3.5,"Financially strong",IF($AG9>=2.75,"Financially adequate",IF($AG9>=2,"Adequate with caution","Financially stretched"))))))) | AI9: =IF($B9="","",IF(AND(ISNUMBER('DATA ENTRY'!$U9),'DATA ENTRY'!$U9<=0),"Negative equity — possible insolvency",IF(AND(ISNUMBER('DATA ENTRY'!$J9),'DATA ENTRY'!$J9<0),"Loss position",IF(AND(ISNUMBER($P9),$P9<1),"Current liabilities exceed current assets",IF(AND(ISNUMBER($T9),$T9>2),"High leverage",IF(AND(ISNUMBER($Y9),$Y9>120),"Slow receivables collection",IF(AND(ISNUMBER($AC9),$AC9<0),"Negative working capital",IF(OR('DATA ENTRY'!$E9="Unaudited",'DATA ENTRY'!$E9="Banker Letter Only",'DATA ENTRY'!$E9="Management Accounts"),"Statement status limits weight on ratios","No major red flag from entered ratios"))))))))
A10: =IF('DATA ENTRY'!$B10<>"",'DATA ENTRY'!$A10,"") | B10: =IF('DATA ENTRY'!$B10<>"",'DATA ENTRY'!$B10,"") | C10: =IF('DATA ENTRY'!$B10<>"",'DATA ENTRY'!$C10,"") | D10: =IF('DATA ENTRY'!$B10<>"",'DATA ENTRY'!$D10,"") | E10: =IF('DATA ENTRY'!$B10<>"",'DATA ENTRY'!$E10,"") | F10: =IF($B10="","",IF('DATA ENTRY'!$Y10="Yes","Checked",IF('DATA ENTRY'!$Y10="No","Needs check","Not marked"))) | G10: =IF($B10="","",IF('DATA ENTRY'!$I10<>"",'DATA ENTRY'!$I10,IF(AND('DATA ENTRY'!$G10<>"",'DATA ENTRY'!$H10<>""),'DATA ENTRY'!$G10-'DATA ENTRY'!$H10,""))) | H10: =IF(OR($B10="",$G10="",'DATA ENTRY'!$G10=""),"",IFERROR($G10/'DATA ENTRY'!$G10,"")) | I10: =IF($B10="","",IF($H10="","Not entered",IF($H10>=0.25,"Strong",IF($H10>=0.15,"Adequate",IF($H10>=0.05,"Caution","High-risk"))))) | J10: =IF(OR($B10="",'DATA ENTRY'!$J10="",'DATA ENTRY'!$G10=""),"",IFERROR('DATA ENTRY'!$J10/'DATA ENTRY'!$G10,"")) | K10: =IF($B10="","",IF($J10="","Not entered",IF($J10>=0.08,"Strong",IF($J10>=0.03,"Adequate",IF($J10>=0,"Caution","High-risk"))))) | L10: =IF(OR($B10="",'DATA ENTRY'!$J10="",'DATA ENTRY'!$Q10=""),"",IFERROR('DATA ENTRY'!$J10/'DATA ENTRY'!$Q10,"")) | M10: =IF($B10="","",IF($L10="","Not entered",IF($L10>=0.1,"Strong",IF($L10>=0.05,"Adequate",IF($L10>=0,"Caution","High-risk"))))) | N10: =IF(OR($B10="",'DATA ENTRY'!$J10="",'DATA ENTRY'!$U10="",'DATA ENTRY'!$U10<=0),"",IFERROR('DATA ENTRY'!$J10/'DATA ENTRY'!$U10,"")) | O10: =IF($B10="","",IF(OR('DATA ENTRY'!$J10="",'DATA ENTRY'!$U10=""),"Not entered",IF('DATA ENTRY'!$U10<=0,"High-risk",IF($N10>=0.15,"Strong",IF($N10>=0.08,"Adequate",IF($N10>=0,"Caution","High-risk")))))) | P10: =IF(OR($B10="",'DATA ENTRY'!$K10="",'DATA ENTRY'!$R10=""),"",IFERROR('DATA ENTRY'!$K10/'DATA ENTRY'!$R10,"")) | Q10: =IF($B10="","",IF($P10="","Not entered",IF($P10>=1.5,"Strong",IF($P10>=1.2,"Adequate",IF($P10>=1,"Caution","High-risk"))))) | R10: =IF(OR($B10="",'DATA ENTRY'!$K10="",'DATA ENTRY'!$R10=""),"",IFERROR(('DATA ENTRY'!$K10-IF('DATA ENTRY'!$O10="",0,'DATA ENTRY'!$O10))/'DATA ENTRY'!$R10,"")) | S10: =IF($B10="","",IF($R10="","Not entered",IF($R10>=1,"Strong",IF($R10>=0.8,"Adequate",IF($R10>=0.6,"Caution","High-risk"))))) | T10: =IF(OR($B10="",'DATA ENTRY'!$T10="",'DATA ENTRY'!$U10="",'DATA ENTRY'!$U10<=0),"",IFERROR('DATA ENTRY'!$T10/'DATA ENTRY'!$U10,"")) | U10: =IF($B10="","",IF(OR('DATA ENTRY'!$T10="",'DATA ENTRY'!$U10=""),"Not entered",IF('DATA ENTRY'!$U10<=0,"High-risk",IF($T10<=1,"Strong",IF($T10<=1.5,"Adequate",IF($T10<=2,"Caution","High-risk")))))) | V10: =IF(OR($B10="",'DATA ENTRY'!$U10="",'DATA ENTRY'!$Q10=""),"",IFERROR('DATA ENTRY'!$U10/'DATA ENTRY'!$Q10,"")) | W10: =IF($B10="","",IF($V10="","Not entered",IF($V10>=0.5,"Strong",IF($V10>=0.3,"Adequate",IF($V10>=0.2,"Caution","High-risk"))))) | X10: =IF(OR($B10="",'DATA ENTRY'!$G10="",'DATA ENTRY'!$M10=""),"",IF('DATA ENTRY'!$N10<>"",'DATA ENTRY'!$G10/AVERAGE('DATA ENTRY'!$M10,'DATA ENTRY'!$N10),IFERROR('DATA ENTRY'!$G10/'DATA ENTRY'!$M10,""))) | Y10: =IF($X10="","",IFERROR(365/$X10,"")) | Z10: =IF($B10="","",IF($X10="","Not entered",IF($Y10<=60,"Strong",IF($Y10<=90,"Adequate",IF($Y10<=120,"Caution","High-risk"))))) | AA10: =IF(OR($B10="",'DATA ENTRY'!$G10="",'DATA ENTRY'!$Q10=""),"",IFERROR('DATA ENTRY'!$G10/'DATA ENTRY'!$Q10,"")) | AB10: =IF($B10="","",IF($AA10="","Not entered",IF($AA10>=1.5,"Strong",IF($AA10>=1,"Adequate",IF($AA10>=0.5,"Caution","High-risk"))))) | AC10: =IF(OR($B10="",'DATA ENTRY'!$K10="",'DATA ENTRY'!$R10=""),"",'DATA ENTRY'!$K10-'DATA ENTRY'!$R10) | AD10: =IF($B10="","",IF($AC10="","Not entered",IF($AC10<0,"High-risk",IF($AC10=0,"Caution",IF('DATA ENTRY'!$L10="","Adequate",IFERROR(IF('DATA ENTRY'!$L10/'DATA ENTRY'!$R10>=0.25,"Strong","Adequate"),"Adequate")))))) | AE10: =IF($B10="","",IF(OR('DATA ENTRY'!$W10="",'DATA ENTRY'!$W10=0),"N/A",IF('DATA ENTRY'!$V10="","",IFERROR('DATA ENTRY'!$V10/'DATA ENTRY'!$W10,"")))) | AF10: =IF($B10="","",IF($AE10="N/A","Not applicable",IF($AE10="","Not entered",IF($AE10>=4,"Strong",IF($AE10>=2.5,"Adequate",IF($AE10>=1.5,"Caution","High-risk")))))) | AG10: =IF($B10="","",IFERROR(ROUND((COUNTIF($I10:$AF10,"Strong")*4+COUNTIF($I10:$AF10,"Adequate")*3+COUNTIF($I10:$AF10,"Caution")*2+COUNTIF($I10:$AF10,"High-risk")*1)/(COUNTIF($I10:$AF10,"Strong")+COUNTIF($I10:$AF10,"Adequate")+COUNTIF($I10:$AF10,"Caution")+COUNTIF($I10:$AF10,"High-risk")),2),"")) | AH10: =IF($B10="","",IF(AND(ISNUMBER('DATA ENTRY'!$U10),'DATA ENTRY'!$U10<=0),"Financially stretched",IF($AG10="","Insufficient data",IF(AND(ISNUMBER('DATA ENTRY'!$J10),'DATA ENTRY'!$J10<0),IF($AG10>=2,"Adequate with caution","Financially stretched"),IF($AG10>=3.5,"Financially strong",IF($AG10>=2.75,"Financially adequate",IF($AG10>=2,"Adequate with caution","Financially stretched"))))))) | AI10: =IF($B10="","",IF(AND(ISNUMBER('DATA ENTRY'!$U10),'DATA ENTRY'!$U10<=0),"Negative equity — possible insolvency",IF(AND(ISNUMBER('DATA ENTRY'!$J10),'DATA ENTRY'!$J10<0),"Loss position",IF(AND(ISNUMBER($P10),$P10<1),"Current liabilities exceed current assets",IF(AND(ISNUMBER($T10),$T10>2),"High leverage",IF(AND(ISNUMBER($Y10),$Y10>120),"Slow receivables collection",IF(AND(ISNUMBER($AC10),$AC10<0),"Negative working capital",IF(OR('DATA ENTRY'!$E10="Unaudited",'DATA ENTRY'!$E10="Banker Letter Only",'DATA ENTRY'!$E10="Management Accounts"),"Statement status limits weight on ratios","No major red flag from entered ratios"))))))))
A11: =IF('DATA ENTRY'!$B11<>"",'DATA ENTRY'!$A11,"") | B11: =IF('DATA ENTRY'!$B11<>"",'DATA ENTRY'!$B11,"") | C11: =IF('DATA ENTRY'!$B11<>"",'DATA ENTRY'!$C11,"") | D11: =IF('DATA ENTRY'!$B11<>"",'DATA ENTRY'!$D11,"") | E11: =IF('DATA ENTRY'!$B11<>"",'DATA ENTRY'!$E11,"") | F11: =IF($B11="","",IF('DATA ENTRY'!$Y11="Yes","Checked",IF('DATA ENTRY'!$Y11="No","Needs check","Not marked"))) | G11: =IF($B11="","",IF('DATA ENTRY'!$I11<>"",'DATA ENTRY'!$I11,IF(AND('DATA ENTRY'!$G11<>"",'DATA ENTRY'!$H11<>""),'DATA ENTRY'!$G11-'DATA ENTRY'!$H11,""))) | H11: =IF(OR($B11="",$G11="",'DATA ENTRY'!$G11=""),"",IFERROR($G11/'DATA ENTRY'!$G11,"")) | I11: =IF($B11="","",IF($H11="","Not entered",IF($H11>=0.25,"Strong",IF($H11>=0.15,"Adequate",IF($H11>=0.05,"Caution","High-risk"))))) | J11: =IF(OR($B11="",'DATA ENTRY'!$J11="",'DATA ENTRY'!$G11=""),"",IFERROR('DATA ENTRY'!$J11/'DATA ENTRY'!$G11,"")) | K11: =IF($B11="","",IF($J11="","Not entered",IF($J11>=0.08,"Strong",IF($J11>=0.03,"Adequate",IF($J11>=0,"Caution","High-risk"))))) | L11: =IF(OR($B11="",'DATA ENTRY'!$J11="",'DATA ENTRY'!$Q11=""),"",IFERROR('DATA ENTRY'!$J11/'DATA ENTRY'!$Q11,"")) | M11: =IF($B11="","",IF($L11="","Not entered",IF($L11>=0.1,"Strong",IF($L11>=0.05,"Adequate",IF($L11>=0,"Caution","High-risk"))))) | N11: =IF(OR($B11="",'DATA ENTRY'!$J11="",'DATA ENTRY'!$U11="",'DATA ENTRY'!$U11<=0),"",IFERROR('DATA ENTRY'!$J11/'DATA ENTRY'!$U11,"")) | O11: =IF($B11="","",IF(OR('DATA ENTRY'!$J11="",'DATA ENTRY'!$U11=""),"Not entered",IF('DATA ENTRY'!$U11<=0,"High-risk",IF($N11>=0.15,"Strong",IF($N11>=0.08,"Adequate",IF($N11>=0,"Caution","High-risk")))))) | P11: =IF(OR($B11="",'DATA ENTRY'!$K11="",'DATA ENTRY'!$R11=""),"",IFERROR('DATA ENTRY'!$K11/'DATA ENTRY'!$R11,"")) | Q11: =IF($B11="","",IF($P11="","Not entered",IF($P11>=1.5,"Strong",IF($P11>=1.2,"Adequate",IF($P11>=1,"Caution","High-risk"))))) | R11: =IF(OR($B11="",'DATA ENTRY'!$K11="",'DATA ENTRY'!$R11=""),"",IFERROR(('DATA ENTRY'!$K11-IF('DATA ENTRY'!$O11="",0,'DATA ENTRY'!$O11))/'DATA ENTRY'!$R11,"")) | S11: =IF($B11="","",IF($R11="","Not entered",IF($R11>=1,"Strong",IF($R11>=0.8,"Adequate",IF($R11>=0.6,"Caution","High-risk"))))) | T11: =IF(OR($B11="",'DATA ENTRY'!$T11="",'DATA ENTRY'!$U11="",'DATA ENTRY'!$U11<=0),"",IFERROR('DATA ENTRY'!$T11/'DATA ENTRY'!$U11,"")) | U11: =IF($B11="","",IF(OR('DATA ENTRY'!$T11="",'DATA ENTRY'!$U11=""),"Not entered",IF('DATA ENTRY'!$U11<=0,"High-risk",IF($T11<=1,"Strong",IF($T11<=1.5,"Adequate",IF($T11<=2,"Caution","High-risk")))))) | V11: =IF(OR($B11="",'DATA ENTRY'!$U11="",'DATA ENTRY'!$Q11=""),"",IFERROR('DATA ENTRY'!$U11/'DATA ENTRY'!$Q11,"")) | W11: =IF($B11="","",IF($V11="","Not entered",IF($V11>=0.5,"Strong",IF($V11>=0.3,"Adequate",IF($V11>=0.2,"Caution","High-risk"))))) | X11: =IF(OR($B11="",'DATA ENTRY'!$G11="",'DATA ENTRY'!$M11=""),"",IF('DATA ENTRY'!$N11<>"",'DATA ENTRY'!$G11/AVERAGE('DATA ENTRY'!$M11,'DATA ENTRY'!$N11),IFERROR('DATA ENTRY'!$G11/'DATA ENTRY'!$M11,""))) | Y11: =IF($X11="","",IFERROR(365/$X11,"")) | Z11: =IF($B11="","",IF($X11="","Not entered",IF($Y11<=60,"Strong",IF($Y11<=90,"Adequate",IF($Y11<=120,"Caution","High-risk"))))) | AA11: =IF(OR($B11="",'DATA ENTRY'!$G11="",'DATA ENTRY'!$Q11=""),"",IFERROR('DATA ENTRY'!$G11/'DATA ENTRY'!$Q11,"")) | AB11: =IF($B11="","",IF($AA11="","Not entered",IF($AA11>=1.5,"Strong",IF($AA11>=1,"Adequate",IF($AA11>=0.5,"Caution","High-risk"))))) | AC11: =IF(OR($B11="",'DATA ENTRY'!$K11="",'DATA ENTRY'!$R11=""),"",'DATA ENTRY'!$K11-'DATA ENTRY'!$R11) | AD11: =IF($B11="","",IF($AC11="","Not entered",IF($AC11<0,"High-risk",IF($AC11=0,"Caution",IF('DATA ENTRY'!$L11="","Adequate",IFERROR(IF('DATA ENTRY'!$L11/'DATA ENTRY'!$R11>=0.25,"Strong","Adequate"),"Adequate")))))) | AE11: =IF($B11="","",IF(OR('DATA ENTRY'!$W11="",'DATA ENTRY'!$W11=0),"N/A",IF('DATA ENTRY'!$V11="","",IFERROR('DATA ENTRY'!$V11/'DATA ENTRY'!$W11,"")))) | AF11: =IF($B11="","",IF($AE11="N/A","Not applicable",IF($AE11="","Not entered",IF($AE11>=4,"Strong",IF($AE11>=2.5,"Adequate",IF($AE11>=1.5,"Caution","High-risk")))))) | AG11: =IF($B11="","",IFERROR(ROUND((COUNTIF($I11:$AF11,"Strong")*4+COUNTIF($I11:$AF11,"Adequate")*3+COUNTIF($I11:$AF11,"Caution")*2+COUNTIF($I11:$AF11,"High-risk")*1)/(COUNTIF($I11:$AF11,"Strong")+COUNTIF($I11:$AF11,"Adequate")+COUNTIF($I11:$AF11,"Caution")+COUNTIF($I11:$AF11,"High-risk")),2),"")) | AH11: =IF($B11="","",IF(AND(ISNUMBER('DATA ENTRY'!$U11),'DATA ENTRY'!$U11<=0),"Financially stretched",IF($AG11="","Insufficient data",IF(AND(ISNUMBER('DATA ENTRY'!$J11),'DATA ENTRY'!$J11<0),IF($AG11>=2,"Adequate with caution","Financially stretched"),IF($AG11>=3.5,"Financially strong",IF($AG11>=2.75,"Financially adequate",IF($AG11>=2,"Adequate with caution","Financially stretched"))))))) | AI11: =IF($B11="","",IF(AND(ISNUMBER('DATA ENTRY'!$U11),'DATA ENTRY'!$U11<=0),"Negative equity — possible insolvency",IF(AND(ISNUMBER('DATA ENTRY'!$J11),'DATA ENTRY'!$J11<0),"Loss position",IF(AND(ISNUMBER($P11),$P11<1),"Current liabilities exceed current assets",IF(AND(ISNUMBER($T11),$T11>2),"High leverage",IF(AND(ISNUMBER($Y11),$Y11>120),"Slow receivables collection",IF(AND(ISNUMBER($AC11),$AC11<0),"Negative working capital",IF(OR('DATA ENTRY'!$E11="Unaudited",'DATA ENTRY'!$E11="Banker Letter Only",'DATA ENTRY'!$E11="Management Accounts"),"Statement status limits weight on ratios","No major red flag from entered ratios"))))))))
A12: =IF('DATA ENTRY'!$B12<>"",'DATA ENTRY'!$A12,"") | B12: =IF('DATA ENTRY'!$B12<>"",'DATA ENTRY'!$B12,"") | C12: =IF('DATA ENTRY'!$B12<>"",'DATA ENTRY'!$C12,"") | D12: =IF('DATA ENTRY'!$B12<>"",'DATA ENTRY'!$D12,"") | E12: =IF('DATA ENTRY'!$B12<>"",'DATA ENTRY'!$E12,"") | F12: =IF($B12="","",IF('DATA ENTRY'!$Y12="Yes","Checked",IF('DATA ENTRY'!$Y12="No","Needs check","Not marked"))) | G12: =IF($B12="","",IF('DATA ENTRY'!$I12<>"",'DATA ENTRY'!$I12,IF(AND('DATA ENTRY'!$G12<>"",'DATA ENTRY'!$H12<>""),'DATA ENTRY'!$G12-'DATA ENTRY'!$H12,""))) | H12: =IF(OR($B12="",$G12="",'DATA ENTRY'!$G12=""),"",IFERROR($G12/'DATA ENTRY'!$G12,"")) | I12: =IF($B12="","",IF($H12="","Not entered",IF($H12>=0.25,"Strong",IF($H12>=0.15,"Adequate",IF($H12>=0.05,"Caution","High-risk"))))) | J12: =IF(OR($B12="",'DATA ENTRY'!$J12="",'DATA ENTRY'!$G12=""),"",IFERROR('DATA ENTRY'!$J12/'DATA ENTRY'!$G12,"")) | K12: =IF($B12="","",IF($J12="","Not entered",IF($J12>=0.08,"Strong",IF($J12>=0.03,"Adequate",IF($J12>=0,"Caution","High-risk"))))) | L12: =IF(OR($B12="",'DATA ENTRY'!$J12="",'DATA ENTRY'!$Q12=""),"",IFERROR('DATA ENTRY'!$J12/'DATA ENTRY'!$Q12,"")) | M12: =IF($B12="","",IF($L12="","Not entered",IF($L12>=0.1,"Strong",IF($L12>=0.05,"Adequate",IF($L12>=0,"Caution","High-risk"))))) | N12: =IF(OR($B12="",'DATA ENTRY'!$J12="",'DATA ENTRY'!$U12="",'DATA ENTRY'!$U12<=0),"",IFERROR('DATA ENTRY'!$J12/'DATA ENTRY'!$U12,"")) | O12: =IF($B12="","",IF(OR('DATA ENTRY'!$J12="",'DATA ENTRY'!$U12=""),"Not entered",IF('DATA ENTRY'!$U12<=0,"High-risk",IF($N12>=0.15,"Strong",IF($N12>=0.08,"Adequate",IF($N12>=0,"Caution","High-risk")))))) | P12: =IF(OR($B12="",'DATA ENTRY'!$K12="",'DATA ENTRY'!$R12=""),"",IFERROR('DATA ENTRY'!$K12/'DATA ENTRY'!$R12,"")) | Q12: =IF($B12="","",IF($P12="","Not entered",IF($P12>=1.5,"Strong",IF($P12>=1.2,"Adequate",IF($P12>=1,"Caution","High-risk"))))) | R12: =IF(OR($B12="",'DATA ENTRY'!$K12="",'DATA ENTRY'!$R12=""),"",IFERROR(('DATA ENTRY'!$K12-IF('DATA ENTRY'!$O12="",0,'DATA ENTRY'!$O12))/'DATA ENTRY'!$R12,"")) | S12: =IF($B12="","",IF($R12="","Not entered",IF($R12>=1,"Strong",IF($R12>=0.8,"Adequate",IF($R12>=0.6,"Caution","High-risk"))))) | T12: =IF(OR($B12="",'DATA ENTRY'!$T12="",'DATA ENTRY'!$U12="",'DATA ENTRY'!$U12<=0),"",IFERROR('DATA ENTRY'!$T12/'DATA ENTRY'!$U12,"")) | U12: =IF($B12="","",IF(OR('DATA ENTRY'!$T12="",'DATA ENTRY'!$U12=""),"Not entered",IF('DATA ENTRY'!$U12<=0,"High-risk",IF($T12<=1,"Strong",IF($T12<=1.5,"Adequate",IF($T12<=2,"Caution","High-risk")))))) | V12: =IF(OR($B12="",'DATA ENTRY'!$U12="",'DATA ENTRY'!$Q12=""),"",IFERROR('DATA ENTRY'!$U12/'DATA ENTRY'!$Q12,"")) | W12: =IF($B12="","",IF($V12="","Not entered",IF($V12>=0.5,"Strong",IF($V12>=0.3,"Adequate",IF($V12>=0.2,"Caution","High-risk"))))) | X12: =IF(OR($B12="",'DATA ENTRY'!$G12="",'DATA ENTRY'!$M12=""),"",IF('DATA ENTRY'!$N12<>"",'DATA ENTRY'!$G12/AVERAGE('DATA ENTRY'!$M12,'DATA ENTRY'!$N12),IFERROR('DATA ENTRY'!$G12/'DATA ENTRY'!$M12,""))) | Y12: =IF($X12="","",IFERROR(365/$X12,"")) | Z12: =IF($B12="","",IF($X12="","Not entered",IF($Y12<=60,"Strong",IF($Y12<=90,"Adequate",IF($Y12<=120,"Caution","High-risk"))))) | AA12: =IF(OR($B12="",'DATA ENTRY'!$G12="",'DATA ENTRY'!$Q12=""),"",IFERROR('DATA ENTRY'!$G12/'DATA ENTRY'!$Q12,"")) | AB12: =IF($B12="","",IF($AA12="","Not entered",IF($AA12>=1.5,"Strong",IF($AA12>=1,"Adequate",IF($AA12>=0.5,"Caution","High-risk"))))) | AC12: =IF(OR($B12="",'DATA ENTRY'!$K12="",'DATA ENTRY'!$R12=""),"",'DATA ENTRY'!$K12-'DATA ENTRY'!$R12) | AD12: =IF($B12="","",IF($AC12="","Not entered",IF($AC12<0,"High-risk",IF($AC12=0,"Caution",IF('DATA ENTRY'!$L12="","Adequate",IFERROR(IF('DATA ENTRY'!$L12/'DATA ENTRY'!$R12>=0.25,"Strong","Adequate"),"Adequate")))))) | AE12: =IF($B12="","",IF(OR('DATA ENTRY'!$W12="",'DATA ENTRY'!$W12=0),"N/A",IF('DATA ENTRY'!$V12="","",IFERROR('DATA ENTRY'!$V12/'DATA ENTRY'!$W12,"")))) | AF12: =IF($B12="","",IF($AE12="N/A","Not applicable",IF($AE12="","Not entered",IF($AE12>=4,"Strong",IF($AE12>=2.5,"Adequate",IF($AE12>=1.5,"Caution","High-risk")))))) | AG12: =IF($B12="","",IFERROR(ROUND((COUNTIF($I12:$AF12,"Strong")*4+COUNTIF($I12:$AF12,"Adequate")*3+COUNTIF($I12:$AF12,"Caution")*2+COUNTIF($I12:$AF12,"High-risk")*1)/(COUNTIF($I12:$AF12,"Strong")+COUNTIF($I12:$AF12,"Adequate")+COUNTIF($I12:$AF12,"Caution")+COUNTIF($I12:$AF12,"High-risk")),2),"")) | AH12: =IF($B12="","",IF(AND(ISNUMBER('DATA ENTRY'!$U12),'DATA ENTRY'!$U12<=0),"Financially stretched",IF($AG12="","Insufficient data",IF(AND(ISNUMBER('DATA ENTRY'!$J12),'DATA ENTRY'!$J12<0),IF($AG12>=2,"Adequate with caution","Financially stretched"),IF($AG12>=3.5,"Financially strong",IF($AG12>=2.75,"Financially adequate",IF($AG12>=2,"Adequate with caution","Financially stretched"))))))) | AI12: =IF($B12="","",IF(AND(ISNUMBER('DATA ENTRY'!$U12),'DATA ENTRY'!$U12<=0),"Negative equity — possible insolvency",IF(AND(ISNUMBER('DATA ENTRY'!$J12),'DATA ENTRY'!$J12<0),"Loss position",IF(AND(ISNUMBER($P12),$P12<1),"Current liabilities exceed current assets",IF(AND(ISNUMBER($T12),$T12>2),"High leverage",IF(AND(ISNUMBER($Y12),$Y12>120),"Slow receivables collection",IF(AND(ISNUMBER($AC12),$AC12<0),"Negative working capital",IF(OR('DATA ENTRY'!$E12="Unaudited",'DATA ENTRY'!$E12="Banker Letter Only",'DATA ENTRY'!$E12="Management Accounts"),"Statement status limits weight on ratios","No major red flag from entered ratios"))))))))
A13: =IF('DATA ENTRY'!$B13<>"",'DATA ENTRY'!$A13,"") | B13: =IF('DATA ENTRY'!$B13<>"",'DATA ENTRY'!$B13,"") | C13: =IF('DATA ENTRY'!$B13<>"",'DATA ENTRY'!$C13,"") | D13: =IF('DATA ENTRY'!$B13<>"",'DATA ENTRY'!$D13,"") | E13: =IF('DATA ENTRY'!$B13<>"",'DATA ENTRY'!$E13,"") | F13: =IF($B13="","",IF('DATA ENTRY'!$Y13="Yes","Checked",IF('DATA ENTRY'!$Y13="No","Needs check","Not marked"))) | G13: =IF($B13="","",IF('DATA ENTRY'!$I13<>"",'DATA ENTRY'!$I13,IF(AND('DATA ENTRY'!$G13<>"",'DATA ENTRY'!$H13<>""),'DATA ENTRY'!$G13-'DATA ENTRY'!$H13,""))) | H13: =IF(OR($B13="",$G13="",'DATA ENTRY'!$G13=""),"",IFERROR($G13/'DATA ENTRY'!$G13,"")) | I13: =IF($B13="","",IF($H13="","Not entered",IF($H13>=0.25,"Strong",IF($H13>=0.15,"Adequate",IF($H13>=0.05,"Caution","High-risk"))))) | J13: =IF(OR($B13="",'DATA ENTRY'!$J13="",'DATA ENTRY'!$G13=""),"",IFERROR('DATA ENTRY'!$J13/'DATA ENTRY'!$G13,"")) | K13: =IF($B13="","",IF($J13="","Not entered",IF($J13>=0.08,"Strong",IF($J13>=0.03,"Adequate",IF($J13>=0,"Caution","High-risk"))))) | L13: =IF(OR($B13="",'DATA ENTRY'!$J13="",'DATA ENTRY'!$Q13=""),"",IFERROR('DATA ENTRY'!$J13/'DATA ENTRY'!$Q13,"")) | M13: =IF($B13="","",IF($L13="","Not entered",IF($L13>=0.1,"Strong",IF($L13>=0.05,"Adequate",IF($L13>=0,"Caution","High-risk"))))) | N13: =IF(OR($B13="",'DATA ENTRY'!$J13="",'DATA ENTRY'!$U13="",'DATA ENTRY'!$U13<=0),"",IFERROR('DATA ENTRY'!$J13/'DATA ENTRY'!$U13,"")) | O13: =IF($B13="","",IF(OR('DATA ENTRY'!$J13="",'DATA ENTRY'!$U13=""),"Not entered",IF('DATA ENTRY'!$U13<=0,"High-risk",IF($N13>=0.15,"Strong",IF($N13>=0.08,"Adequate",IF($N13>=0,"Caution","High-risk")))))) | P13: =IF(OR($B13="",'DATA ENTRY'!$K13="",'DATA ENTRY'!$R13=""),"",IFERROR('DATA ENTRY'!$K13/'DATA ENTRY'!$R13,"")) | Q13: =IF($B13="","",IF($P13="","Not entered",IF($P13>=1.5,"Strong",IF($P13>=1.2,"Adequate",IF($P13>=1,"Caution","High-risk"))))) | R13: =IF(OR($B13="",'DATA ENTRY'!$K13="",'DATA ENTRY'!$R13=""),"",IFERROR(('DATA ENTRY'!$K13-IF('DATA ENTRY'!$O13="",0,'DATA ENTRY'!$O13))/'DATA ENTRY'!$R13,"")) | S13: =IF($B13="","",IF($R13="","Not entered",IF($R13>=1,"Strong",IF($R13>=0.8,"Adequate",IF($R13>=0.6,"Caution","High-risk"))))) | T13: =IF(OR($B13="",'DATA ENTRY'!$T13="",'DATA ENTRY'!$U13="",'DATA ENTRY'!$U13<=0),"",IFERROR('DATA ENTRY'!$T13/'DATA ENTRY'!$U13,"")) | U13: =IF($B13="","",IF(OR('DATA ENTRY'!$T13="",'DATA ENTRY'!$U13=""),"Not entered",IF('DATA ENTRY'!$U13<=0,"High-risk",IF($T13<=1,"Strong",IF($T13<=1.5,"Adequate",IF($T13<=2,"Caution","High-risk")))))) | V13: =IF(OR($B13="",'DATA ENTRY'!$U13="",'DATA ENTRY'!$Q13=""),"",IFERROR('DATA ENTRY'!$U13/'DATA ENTRY'!$Q13,"")) | W13: =IF($B13="","",IF($V13="","Not entered",IF($V13>=0.5,"Strong",IF($V13>=0.3,"Adequate",IF($V13>=0.2,"Caution","High-risk"))))) | X13: =IF(OR($B13="",'DATA ENTRY'!$G13="",'DATA ENTRY'!$M13=""),"",IF('DATA ENTRY'!$N13<>"",'DATA ENTRY'!$G13/AVERAGE('DATA ENTRY'!$M13,'DATA ENTRY'!$N13),IFERROR('DATA ENTRY'!$G13/'DATA ENTRY'!$M13,""))) | Y13: =IF($X13="","",IFERROR(365/$X13,"")) | Z13: =IF($B13="","",IF($X13="","Not entered",IF($Y13<=60,"Strong",IF($Y13<=90,"Adequate",IF($Y13<=120,"Caution","High-risk"))))) | AA13: =IF(OR($B13="",'DATA ENTRY'!$G13="",'DATA ENTRY'!$Q13=""),"",IFERROR('DATA ENTRY'!$G13/'DATA ENTRY'!$Q13,"")) | AB13: =IF($B13="","",IF($AA13="","Not entered",IF($AA13>=1.5,"Strong",IF($AA13>=1,"Adequate",IF($AA13>=0.5,"Caution","High-risk"))))) | AC13: =IF(OR($B13="",'DATA ENTRY'!$K13="",'DATA ENTRY'!$R13=""),"",'DATA ENTRY'!$K13-'DATA ENTRY'!$R13) | AD13: =IF($B13="","",IF($AC13="","Not entered",IF($AC13<0,"High-risk",IF($AC13=0,"Caution",IF('DATA ENTRY'!$L13="","Adequate",IFERROR(IF('DATA ENTRY'!$L13/'DATA ENTRY'!$R13>=0.25,"Strong","Adequate"),"Adequate")))))) | AE13: =IF($B13="","",IF(OR('DATA ENTRY'!$W13="",'DATA ENTRY'!$W13=0),"N/A",IF('DATA ENTRY'!$V13="","",IFERROR('DATA ENTRY'!$V13/'DATA ENTRY'!$W13,"")))) | AF13: =IF($B13="","",IF($AE13="N/A","Not applicable",IF($AE13="","Not entered",IF($AE13>=4,"Strong",IF($AE13>=2.5,"Adequate",IF($AE13>=1.5,"Caution","High-risk")))))) | AG13: =IF($B13="","",IFERROR(ROUND((COUNTIF($I13:$AF13,"Strong")*4+COUNTIF($I13:$AF13,"Adequate")*3+COUNTIF($I13:$AF13,"Caution")*2+COUNTIF($I13:$AF13,"High-risk")*1)/(COUNTIF($I13:$AF13,"Strong")+COUNTIF($I13:$AF13,"Adequate")+COUNTIF($I13:$AF13,"Caution")+COUNTIF($I13:$AF13,"High-risk")),2),"")) | AH13: =IF($B13="","",IF(AND(ISNUMBER('DATA ENTRY'!$U13),'DATA ENTRY'!$U13<=0),"Financially stretched",IF($AG13="","Insufficient data",IF(AND(ISNUMBER('DATA ENTRY'!$J13),'DATA ENTRY'!$J13<0),IF($AG13>=2,"Adequate with caution","Financially stretched"),IF($AG13>=3.5,"Financially strong",IF($AG13>=2.75,"Financially adequate",IF($AG13>=2,"Adequate with caution","Financially stretched"))))))) | AI13: =IF($B13="","",IF(AND(ISNUMBER('DATA ENTRY'!$U13),'DATA ENTRY'!$U13<=0),"Negative equity — possible insolvency",IF(AND(ISNUMBER('DATA ENTRY'!$J13),'DATA ENTRY'!$J13<0),"Loss position",IF(AND(ISNUMBER($P13),$P13<1),"Current liabilities exceed current assets",IF(AND(ISNUMBER($T13),$T13>2),"High leverage",IF(AND(ISNUMBER($Y13),$Y13>120),"Slow receivables collection",IF(AND(ISNUMBER($AC13),$AC13<0),"Negative working capital",IF(OR('DATA ENTRY'!$E13="Unaudited",'DATA ENTRY'!$E13="Banker Letter Only",'DATA ENTRY'!$E13="Management Accounts"),"Statement status limits weight on ratios","No major red flag from entered ratios"))))))))
A14: =IF('DATA ENTRY'!$B14<>"",'DATA ENTRY'!$A14,"") | B14: =IF('DATA ENTRY'!$B14<>"",'DATA ENTRY'!$B14,"") | C14: =IF('DATA ENTRY'!$B14<>"",'DATA ENTRY'!$C14,"") | D14: =IF('DATA ENTRY'!$B14<>"",'DATA ENTRY'!$D14,"") | E14: =IF('DATA ENTRY'!$B14<>"",'DATA ENTRY'!$E14,"") | F14: =IF($B14="","",IF('DATA ENTRY'!$Y14="Yes","Checked",IF('DATA ENTRY'!$Y14="No","Needs check","Not marked"))) | G14: =IF($B14="","",IF('DATA ENTRY'!$I14<>"",'DATA ENTRY'!$I14,IF(AND('DATA ENTRY'!$G14<>"",'DATA ENTRY'!$H14<>""),'DATA ENTRY'!$G14-'DATA ENTRY'!$H14,""))) | H14: =IF(OR($B14="",$G14="",'DATA ENTRY'!$G14=""),"",IFERROR($G14/'DATA ENTRY'!$G14,"")) | I14: =IF($B14="","",IF($H14="","Not entered",IF($H14>=0.25,"Strong",IF($H14>=0.15,"Adequate",IF($H14>=0.05,"Caution","High-risk"))))) | J14: =IF(OR($B14="",'DATA ENTRY'!$J14="",'DATA ENTRY'!$G14=""),"",IFERROR('DATA ENTRY'!$J14/'DATA ENTRY'!$G14,"")) | K14: =IF($B14="","",IF($J14="","Not entered",IF($J14>=0.08,"Strong",IF($J14>=0.03,"Adequate",IF($J14>=0,"Caution","High-risk"))))) | L14: =IF(OR($B14="",'DATA ENTRY'!$J14="",'DATA ENTRY'!$Q14=""),"",IFERROR('DATA ENTRY'!$J14/'DATA ENTRY'!$Q14,"")) | M14: =IF($B14="","",IF($L14="","Not entered",IF($L14>=0.1,"Strong",IF($L14>=0.05,"Adequate",IF($L14>=0,"Caution","High-risk"))))) | N14: =IF(OR($B14="",'DATA ENTRY'!$J14="",'DATA ENTRY'!$U14="",'DATA ENTRY'!$U14<=0),"",IFERROR('DATA ENTRY'!$J14/'DATA ENTRY'!$U14,"")) | O14: =IF($B14="","",IF(OR('DATA ENTRY'!$J14="",'DATA ENTRY'!$U14=""),"Not entered",IF('DATA ENTRY'!$U14<=0,"High-risk",IF($N14>=0.15,"Strong",IF($N14>=0.08,"Adequate",IF($N14>=0,"Caution","High-risk")))))) | P14: =IF(OR($B14="",'DATA ENTRY'!$K14="",'DATA ENTRY'!$R14=""),"",IFERROR('DATA ENTRY'!$K14/'DATA ENTRY'!$R14,"")) | Q14: =IF($B14="","",IF($P14="","Not entered",IF($P14>=1.5,"Strong",IF($P14>=1.2,"Adequate",IF($P14>=1,"Caution","High-risk"))))) | R14: =IF(OR($B14="",'DATA ENTRY'!$K14="",'DATA ENTRY'!$R14=""),"",IFERROR(('DATA ENTRY'!$K14-IF('DATA ENTRY'!$O14="",0,'DATA ENTRY'!$O14))/'DATA ENTRY'!$R14,"")) | S14: =IF($B14="","",IF($R14="","Not entered",IF($R14>=1,"Strong",IF($R14>=0.8,"Adequate",IF($R14>=0.6,"Caution","High-risk"))))) | T14: =IF(OR($B14="",'DATA ENTRY'!$T14="",'DATA ENTRY'!$U14="",'DATA ENTRY'!$U14<=0),"",IFERROR('DATA ENTRY'!$T14/'DATA ENTRY'!$U14,"")) | U14: =IF($B14="","",IF(OR('DATA ENTRY'!$T14="",'DATA ENTRY'!$U14=""),"Not entered",IF('DATA ENTRY'!$U14<=0,"High-risk",IF($T14<=1,"Strong",IF($T14<=1.5,"Adequate",IF($T14<=2,"Caution","High-risk")))))) | V14: =IF(OR($B14="",'DATA ENTRY'!$U14="",'DATA ENTRY'!$Q14=""),"",IFERROR('DATA ENTRY'!$U14/'DATA ENTRY'!$Q14,"")) | W14: =IF($B14="","",IF($V14="","Not entered",IF($V14>=0.5,"Strong",IF($V14>=0.3,"Adequate",IF($V14>=0.2,"Caution","High-risk"))))) | X14: =IF(OR($B14="",'DATA ENTRY'!$G14="",'DATA ENTRY'!$M14=""),"",IF('DATA ENTRY'!$N14<>"",'DATA ENTRY'!$G14/AVERAGE('DATA ENTRY'!$M14,'DATA ENTRY'!$N14),IFERROR('DATA ENTRY'!$G14/'DATA ENTRY'!$M14,""))) | Y14: =IF($X14="","",IFERROR(365/$X14,"")) | Z14: =IF($B14="","",IF($X14="","Not entered",IF($Y14<=60,"Strong",IF($Y14<=90,"Adequate",IF($Y14<=120,"Caution","High-risk"))))) | AA14: =IF(OR($B14="",'DATA ENTRY'!$G14="",'DATA ENTRY'!$Q14=""),"",IFERROR('DATA ENTRY'!$G14/'DATA ENTRY'!$Q14,"")) | AB14: =IF($B14="","",IF($AA14="","Not entered",IF($AA14>=1.5,"Strong",IF($AA14>=1,"Adequate",IF($AA14>=0.5,"Caution","High-risk"))))) | AC14: =IF(OR($B14="",'DATA ENTRY'!$K14="",'DATA ENTRY'!$R14=""),"",'DATA ENTRY'!$K14-'DATA ENTRY'!$R14) | AD14: =IF($B14="","",IF($AC14="","Not entered",IF($AC14<0,"High-risk",IF($AC14=0,"Caution",IF('DATA ENTRY'!$L14="","Adequate",IFERROR(IF('DATA ENTRY'!$L14/'DATA ENTRY'!$R14>=0.25,"Strong","Adequate"),"Adequate")))))) | AE14: =IF($B14="","",IF(OR('DATA ENTRY'!$W14="",'DATA ENTRY'!$W14=0),"N/A",IF('DATA ENTRY'!$V14="","",IFERROR('DATA ENTRY'!$V14/'DATA ENTRY'!$W14,"")))) | AF14: =IF($B14="","",IF($AE14="N/A","Not applicable",IF($AE14="","Not entered",IF($AE14>=4,"Strong",IF($AE14>=2.5,"Adequate",IF($AE14>=1.5,"Caution","High-risk")))))) | AG14: =IF($B14="","",IFERROR(ROUND((COUNTIF($I14:$AF14,"Strong")*4+COUNTIF($I14:$AF14,"Adequate")*3+COUNTIF($I14:$AF14,"Caution")*2+COUNTIF($I14:$AF14,"High-risk")*1)/(COUNTIF($I14:$AF14,"Strong")+COUNTIF($I14:$AF14,"Adequate")+COUNTIF($I14:$AF14,"Caution")+COUNTIF($I14:$AF14,"High-risk")),2),"")) | AH14: =IF($B14="","",IF(AND(ISNUMBER('DATA ENTRY'!$U14),'DATA ENTRY'!$U14<=0),"Financially stretched",IF($AG14="","Insufficient data",IF(AND(ISNUMBER('DATA ENTRY'!$J14),'DATA ENTRY'!$J14<0),IF($AG14>=2,"Adequate with caution","Financially stretched"),IF($AG14>=3.5,"Financially strong",IF($AG14>=2.75,"Financially adequate",IF($AG14>=2,"Adequate with caution","Financially stretched"))))))) | AI14: =IF($B14="","",IF(AND(ISNUMBER('DATA ENTRY'!$U14),'DATA ENTRY'!$U14<=0),"Negative equity — possible insolvency",IF(AND(ISNUMBER('DATA ENTRY'!$J14),'DATA ENTRY'!$J14<0),"Loss position",IF(AND(ISNUMBER($P14),$P14<1),"Current liabilities exceed current assets",IF(AND(ISNUMBER($T14),$T14>2),"High leverage",IF(AND(ISNUMBER($Y14),$Y14>120),"Slow receivables collection",IF(AND(ISNUMBER($AC14),$AC14<0),"Negative working capital",IF(OR('DATA ENTRY'!$E14="Unaudited",'DATA ENTRY'!$E14="Banker Letter Only",'DATA ENTRY'!$E14="Management Accounts"),"Statement status limits weight on ratios","No major red flag from entered ratios"))))))))
A15: =IF('DATA ENTRY'!$B15<>"",'DATA ENTRY'!$A15,"") | B15: =IF('DATA ENTRY'!$B15<>"",'DATA ENTRY'!$B15,"") | C15: =IF('DATA ENTRY'!$B15<>"",'DATA ENTRY'!$C15,"") | D15: =IF('DATA ENTRY'!$B15<>"",'DATA ENTRY'!$D15,"") | E15: =IF('DATA ENTRY'!$B15<>"",'DATA ENTRY'!$E15,"") | F15: =IF($B15="","",IF('DATA ENTRY'!$Y15="Yes","Checked",IF('DATA ENTRY'!$Y15="No","Needs check","Not marked"))) | G15: =IF($B15="","",IF('DATA ENTRY'!$I15<>"",'DATA ENTRY'!$I15,IF(AND('DATA ENTRY'!$G15<>"",'DATA ENTRY'!$H15<>""),'DATA ENTRY'!$G15-'DATA ENTRY'!$H15,""))) | H15: =IF(OR($B15="",$G15="",'DATA ENTRY'!$G15=""),"",IFERROR($G15/'DATA ENTRY'!$G15,"")) | I15: =IF($B15="","",IF($H15="","Not entered",IF($H15>=0.25,"Strong",IF($H15>=0.15,"Adequate",IF($H15>=0.05,"Caution","High-risk"))))) | J15: =IF(OR($B15="",'DATA ENTRY'!$J15="",'DATA ENTRY'!$G15=""),"",IFERROR('DATA ENTRY'!$J15/'DATA ENTRY'!$G15,"")) | K15: =IF($B15="","",IF($J15="","Not entered",IF($J15>=0.08,"Strong",IF($J15>=0.03,"Adequate",IF($J15>=0,"Caution","High-risk"))))) | L15: =IF(OR($B15="",'DATA ENTRY'!$J15="",'DATA ENTRY'!$Q15=""),"",IFERROR('DATA ENTRY'!$J15/'DATA ENTRY'!$Q15,"")) | M15: =IF($B15="","",IF($L15="","Not entered",IF($L15>=0.1,"Strong",IF($L15>=0.05,"Adequate",IF($L15>=0,"Caution","High-risk"))))) | N15: =IF(OR($B15="",'DATA ENTRY'!$J15="",'DATA ENTRY'!$U15="",'DATA ENTRY'!$U15<=0),"",IFERROR('DATA ENTRY'!$J15/'DATA ENTRY'!$U15,"")) | O15: =IF($B15="","",IF(OR('DATA ENTRY'!$J15="",'DATA ENTRY'!$U15=""),"Not entered",IF('DATA ENTRY'!$U15<=0,"High-risk",IF($N15>=0.15,"Strong",IF($N15>=0.08,"Adequate",IF($N15>=0,"Caution","High-risk")))))) | P15: =IF(OR($B15="",'DATA ENTRY'!$K15="",'DATA ENTRY'!$R15=""),"",IFERROR('DATA ENTRY'!$K15/'DATA ENTRY'!$R15,"")) | Q15: =IF($B15="","",IF($P15="","Not entered",IF($P15>=1.5,"Strong",IF($P15>=1.2,"Adequate",IF($P15>=1,"Caution","High-risk"))))) | R15: =IF(OR($B15="",'DATA ENTRY'!$K15="",'DATA ENTRY'!$R15=""),"",IFERROR(('DATA ENTRY'!$K15-IF('DATA ENTRY'!$O15="",0,'DATA ENTRY'!$O15))/'DATA ENTRY'!$R15,"")) | S15: =IF($B15="","",IF($R15="","Not entered",IF($R15>=1,"Strong",IF($R15>=0.8,"Adequate",IF($R15>=0.6,"Caution","High-risk"))))) | T15: =IF(OR($B15="",'DATA ENTRY'!$T15="",'DATA ENTRY'!$U15="",'DATA ENTRY'!$U15<=0),"",IFERROR('DATA ENTRY'!$T15/'DATA ENTRY'!$U15,"")) | U15: =IF($B15="","",IF(OR('DATA ENTRY'!$T15="",'DATA ENTRY'!$U15=""),"Not entered",IF('DATA ENTRY'!$U15<=0,"High-risk",IF($T15<=1,"Strong",IF($T15<=1.5,"Adequate",IF($T15<=2,"Caution","High-risk")))))) | V15: =IF(OR($B15="",'DATA ENTRY'!$U15="",'DATA ENTRY'!$Q15=""),"",IFERROR('DATA ENTRY'!$U15/'DATA ENTRY'!$Q15,"")) | W15: =IF($B15="","",IF($V15="","Not entered",IF($V15>=0.5,"Strong",IF($V15>=0.3,"Adequate",IF($V15>=0.2,"Caution","High-risk"))))) | X15: =IF(OR($B15="",'DATA ENTRY'!$G15="",'DATA ENTRY'!$M15=""),"",IF('DATA ENTRY'!$N15<>"",'DATA ENTRY'!$G15/AVERAGE('DATA ENTRY'!$M15,'DATA ENTRY'!$N15),IFERROR('DATA ENTRY'!$G15/'DATA ENTRY'!$M15,""))) | Y15: =IF($X15="","",IFERROR(365/$X15,"")) | Z15: =IF($B15="","",IF($X15="","Not entered",IF($Y15<=60,"Strong",IF($Y15<=90,"Adequate",IF($Y15<=120,"Caution","High-risk"))))) | AA15: =IF(OR($B15="",'DATA ENTRY'!$G15="",'DATA ENTRY'!$Q15=""),"",IFERROR('DATA ENTRY'!$G15/'DATA ENTRY'!$Q15,"")) | AB15: =IF($B15="","",IF($AA15="","Not entered",IF($AA15>=1.5,"Strong",IF($AA15>=1,"Adequate",IF($AA15>=0.5,"Caution","High-risk"))))) | AC15: =IF(OR($B15="",'DATA ENTRY'!$K15="",'DATA ENTRY'!$R15=""),"",'DATA ENTRY'!$K15-'DATA ENTRY'!$R15) | AD15: =IF($B15="","",IF($AC15="","Not entered",IF($AC15<0,"High-risk",IF($AC15=0,"Caution",IF('DATA ENTRY'!$L15="","Adequate",IFERROR(IF('DATA ENTRY'!$L15/'DATA ENTRY'!$R15>=0.25,"Strong","Adequate"),"Adequate")))))) | AE15: =IF($B15="","",IF(OR('DATA ENTRY'!$W15="",'DATA ENTRY'!$W15=0),"N/A",IF('DATA ENTRY'!$V15="","",IFERROR('DATA ENTRY'!$V15/'DATA ENTRY'!$W15,"")))) | AF15: =IF($B15="","",IF($AE15="N/A","Not applicable",IF($AE15="","Not entered",IF($AE15>=4,"Strong",IF($AE15>=2.5,"Adequate",IF($AE15>=1.5,"Caution","High-risk")))))) | AG15: =IF($B15="","",IFERROR(ROUND((COUNTIF($I15:$AF15,"Strong")*4+COUNTIF($I15:$AF15,"Adequate")*3+COUNTIF($I15:$AF15,"Caution")*2+COUNTIF($I15:$AF15,"High-risk")*1)/(COUNTIF($I15:$AF15,"Strong")+COUNTIF($I15:$AF15,"Adequate")+COUNTIF($I15:$AF15,"Caution")+COUNTIF($I15:$AF15,"High-risk")),2),"")) | AH15: =IF($B15="","",IF(AND(ISNUMBER('DATA ENTRY'!$U15),'DATA ENTRY'!$U15<=0),"Financially stretched",IF($AG15="","Insufficient data",IF(AND(ISNUMBER('DATA ENTRY'!$J15),'DATA ENTRY'!$J15<0),IF($AG15>=2,"Adequate with caution","Financially stretched"),IF($AG15>=3.5,"Financially strong",IF($AG15>=2.75,"Financially adequate",IF($AG15>=2,"Adequate with caution","Financially stretched"))))))) | AI15: =IF($B15="","",IF(AND(ISNUMBER('DATA ENTRY'!$U15),'DATA ENTRY'!$U15<=0),"Negative equity — possible insolvency",IF(AND(ISNUMBER('DATA ENTRY'!$J15),'DATA ENTRY'!$J15<0),"Loss position",IF(AND(ISNUMBER($P15),$P15<1),"Current liabilities exceed current assets",IF(AND(ISNUMBER($T15),$T15>2),"High leverage",IF(AND(ISNUMBER($Y15),$Y15>120),"Slow receivables collection",IF(AND(ISNUMBER($AC15),$AC15<0),"Negative working capital",IF(OR('DATA ENTRY'!$E15="Unaudited",'DATA ENTRY'!$E15="Banker Letter Only",'DATA ENTRY'!$E15="Management Accounts"),"Statement status limits weight on ratios","No major red flag from entered ratios"))))))))
A16: =IF('DATA ENTRY'!$B16<>"",'DATA ENTRY'!$A16,"") | B16: =IF('DATA ENTRY'!$B16<>"",'DATA ENTRY'!$B16,"") | C16: =IF('DATA ENTRY'!$B16<>"",'DATA ENTRY'!$C16,"") | D16: =IF('DATA ENTRY'!$B16<>"",'DATA ENTRY'!$D16,"") | E16: =IF('DATA ENTRY'!$B16<>"",'DATA ENTRY'!$E16,"") | F16: =IF($B16="","",IF('DATA ENTRY'!$Y16="Yes","Checked",IF('DATA ENTRY'!$Y16="No","Needs check","Not marked"))) | G16: =IF($B16="","",IF('DATA ENTRY'!$I16<>"",'DATA ENTRY'!$I16,IF(AND('DATA ENTRY'!$G16<>"",'DATA ENTRY'!$H16<>""),'DATA ENTRY'!$G16-'DATA ENTRY'!$H16,""))) | H16: =IF(OR($B16="",$G16="",'DATA ENTRY'!$G16=""),"",IFERROR($G16/'DATA ENTRY'!$G16,"")) | I16: =IF($B16="","",IF($H16="","Not entered",IF($H16>=0.25,"Strong",IF($H16>=0.15,"Adequate",IF($H16>=0.05,"Caution","High-risk"))))) | J16: =IF(OR($B16="",'DATA ENTRY'!$J16="",'DATA ENTRY'!$G16=""),"",IFERROR('DATA ENTRY'!$J16/'DATA ENTRY'!$G16,"")) | K16: =IF($B16="","",IF($J16="","Not entered",IF($J16>=0.08,"Strong",IF($J16>=0.03,"Adequate",IF($J16>=0,"Caution","High-risk"))))) | L16: =IF(OR($B16="",'DATA ENTRY'!$J16="",'DATA ENTRY'!$Q16=""),"",IFERROR('DATA ENTRY'!$J16/'DATA ENTRY'!$Q16,"")) | M16: =IF($B16="","",IF($L16="","Not entered",IF($L16>=0.1,"Strong",IF($L16>=0.05,"Adequate",IF($L16>=0,"Caution","High-risk"))))) | N16: =IF(OR($B16="",'DATA ENTRY'!$J16="",'DATA ENTRY'!$U16="",'DATA ENTRY'!$U16<=0),"",IFERROR('DATA ENTRY'!$J16/'DATA ENTRY'!$U16,"")) | O16: =IF($B16="","",IF(OR('DATA ENTRY'!$J16="",'DATA ENTRY'!$U16=""),"Not entered",IF('DATA ENTRY'!$U16<=0,"High-risk",IF($N16>=0.15,"Strong",IF($N16>=0.08,"Adequate",IF($N16>=0,"Caution","High-risk")))))) | P16: =IF(OR($B16="",'DATA ENTRY'!$K16="",'DATA ENTRY'!$R16=""),"",IFERROR('DATA ENTRY'!$K16/'DATA ENTRY'!$R16,"")) | Q16: =IF($B16="","",IF($P16="","Not entered",IF($P16>=1.5,"Strong",IF($P16>=1.2,"Adequate",IF($P16>=1,"Caution","High-risk"))))) | R16: =IF(OR($B16="",'DATA ENTRY'!$K16="",'DATA ENTRY'!$R16=""),"",IFERROR(('DATA ENTRY'!$K16-IF('DATA ENTRY'!$O16="",0,'DATA ENTRY'!$O16))/'DATA ENTRY'!$R16,"")) | S16: =IF($B16="","",IF($R16="","Not entered",IF($R16>=1,"Strong",IF($R16>=0.8,"Adequate",IF($R16>=0.6,"Caution","High-risk"))))) | T16: =IF(OR($B16="",'DATA ENTRY'!$T16="",'DATA ENTRY'!$U16="",'DATA ENTRY'!$U16<=0),"",IFERROR('DATA ENTRY'!$T16/'DATA ENTRY'!$U16,"")) | U16: =IF($B16="","",IF(OR('DATA ENTRY'!$T16="",'DATA ENTRY'!$U16=""),"Not entered",IF('DATA ENTRY'!$U16<=0,"High-risk",IF($T16<=1,"Strong",IF($T16<=1.5,"Adequate",IF($T16<=2,"Caution","High-risk")))))) | V16: =IF(OR($B16="",'DATA ENTRY'!$U16="",'DATA ENTRY'!$Q16=""),"",IFERROR('DATA ENTRY'!$U16/'DATA ENTRY'!$Q16,"")) | W16: =IF($B16="","",IF($V16="","Not entered",IF($V16>=0.5,"Strong",IF($V16>=0.3,"Adequate",IF($V16>=0.2,"Caution","High-risk"))))) | X16: =IF(OR($B16="",'DATA ENTRY'!$G16="",'DATA ENTRY'!$M16=""),"",IF('DATA ENTRY'!$N16<>"",'DATA ENTRY'!$G16/AVERAGE('DATA ENTRY'!$M16,'DATA ENTRY'!$N16),IFERROR('DATA ENTRY'!$G16/'DATA ENTRY'!$M16,""))) | Y16: =IF($X16="","",IFERROR(365/$X16,"")) | Z16: =IF($B16="","",IF($X16="","Not entered",IF($Y16<=60,"Strong",IF($Y16<=90,"Adequate",IF($Y16<=120,"Caution","High-risk"))))) | AA16: =IF(OR($B16="",'DATA ENTRY'!$G16="",'DATA ENTRY'!$Q16=""),"",IFERROR('DATA ENTRY'!$G16/'DATA ENTRY'!$Q16,"")) | AB16: =IF($B16="","",IF($AA16="","Not entered",IF($AA16>=1.5,"Strong",IF($AA16>=1,"Adequate",IF($AA16>=0.5,"Caution","High-risk"))))) | AC16: =IF(OR($B16="",'DATA ENTRY'!$K16="",'DATA ENTRY'!$R16=""),"",'DATA ENTRY'!$K16-'DATA ENTRY'!$R16) | AD16: =IF($B16="","",IF($AC16="","Not entered",IF($AC16<0,"High-risk",IF($AC16=0,"Caution",IF('DATA ENTRY'!$L16="","Adequate",IFERROR(IF('DATA ENTRY'!$L16/'DATA ENTRY'!$R16>=0.25,"Strong","Adequate"),"Adequate")))))) | AE16: =IF($B16="","",IF(OR('DATA ENTRY'!$W16="",'DATA ENTRY'!$W16=0),"N/A",IF('DATA ENTRY'!$V16="","",IFERROR('DATA ENTRY'!$V16/'DATA ENTRY'!$W16,"")))) | AF16: =IF($B16="","",IF($AE16="N/A","Not applicable",IF($AE16="","Not entered",IF($AE16>=4,"Strong",IF($AE16>=2.5,"Adequate",IF($AE16>=1.5,"Caution","High-risk")))))) | AG16: =IF($B16="","",IFERROR(ROUND((COUNTIF($I16:$AF16,"Strong")*4+COUNTIF($I16:$AF16,"Adequate")*3+COUNTIF($I16:$AF16,"Caution")*2+COUNTIF($I16:$AF16,"High-risk")*1)/(COUNTIF($I16:$AF16,"Strong")+COUNTIF($I16:$AF16,"Adequate")+COUNTIF($I16:$AF16,"Caution")+COUNTIF($I16:$AF16,"High-risk")),2),"")) | AH16: =IF($B16="","",IF(AND(ISNUMBER('DATA ENTRY'!$U16),'DATA ENTRY'!$U16<=0),"Financially stretched",IF($AG16="","Insufficient data",IF(AND(ISNUMBER('DATA ENTRY'!$J16),'DATA ENTRY'!$J16<0),IF($AG16>=2,"Adequate with caution","Financially stretched"),IF($AG16>=3.5,"Financially strong",IF($AG16>=2.75,"Financially adequate",IF($AG16>=2,"Adequate with caution","Financially stretched"))))))) | AI16: =IF($B16="","",IF(AND(ISNUMBER('DATA ENTRY'!$U16),'DATA ENTRY'!$U16<=0),"Negative equity — possible insolvency",IF(AND(ISNUMBER('DATA ENTRY'!$J16),'DATA ENTRY'!$J16<0),"Loss position",IF(AND(ISNUMBER($P16),$P16<1),"Current liabilities exceed current assets",IF(AND(ISNUMBER($T16),$T16>2),"High leverage",IF(AND(ISNUMBER($Y16),$Y16>120),"Slow receivables collection",IF(AND(ISNUMBER($AC16),$AC16<0),"Negative working capital",IF(OR('DATA ENTRY'!$E16="Unaudited",'DATA ENTRY'!$E16="Banker Letter Only",'DATA ENTRY'!$E16="Management Accounts"),"Statement status limits weight on ratios","No major red flag from entered ratios"))))))))
A17: =IF('DATA ENTRY'!$B17<>"",'DATA ENTRY'!$A17,"") | B17: =IF('DATA ENTRY'!$B17<>"",'DATA ENTRY'!$B17,"") | C17: =IF('DATA ENTRY'!$B17<>"",'DATA ENTRY'!$C17,"") | D17: =IF('DATA ENTRY'!$B17<>"",'DATA ENTRY'!$D17,"") | E17: =IF('DATA ENTRY'!$B17<>"",'DATA ENTRY'!$E17,"") | F17: =IF($B17="","",IF('DATA ENTRY'!$Y17="Yes","Checked",IF('DATA ENTRY'!$Y17="No","Needs check","Not marked"))) | G17: =IF($B17="","",IF('DATA ENTRY'!$I17<>"",'DATA ENTRY'!$I17,IF(AND('DATA ENTRY'!$G17<>"",'DATA ENTRY'!$H17<>""),'DATA ENTRY'!$G17-'DATA ENTRY'!$H17,""))) | H17: =IF(OR($B17="",$G17="",'DATA ENTRY'!$G17=""),"",IFERROR($G17/'DATA ENTRY'!$G17,"")) | I17: =IF($B17="","",IF($H17="","Not entered",IF($H17>=0.25,"Strong",IF($H17>=0.15,"Adequate",IF($H17>=0.05,"Caution","High-risk"))))) | J17: =IF(OR($B17="",'DATA ENTRY'!$J17="",'DATA ENTRY'!$G17=""),"",IFERROR('DATA ENTRY'!$J17/'DATA ENTRY'!$G17,"")) | K17: =IF($B17="","",IF($J17="","Not entered",IF($J17>=0.08,"Strong",IF($J17>=0.03,"Adequate",IF($J17>=0,"Caution","High-risk"))))) | L17: =IF(OR($B17="",'DATA ENTRY'!$J17="",'DATA ENTRY'!$Q17=""),"",IFERROR('DATA ENTRY'!$J17/'DATA ENTRY'!$Q17,"")) | M17: =IF($B17="","",IF($L17="","Not entered",IF($L17>=0.1,"Strong",IF($L17>=0.05,"Adequate",IF($L17>=0,"Caution","High-risk"))))) | N17: =IF(OR($B17="",'DATA ENTRY'!$J17="",'DATA ENTRY'!$U17="",'DATA ENTRY'!$U17<=0),"",IFERROR('DATA ENTRY'!$J17/'DATA ENTRY'!$U17,"")) | O17: =IF($B17="","",IF(OR('DATA ENTRY'!$J17="",'DATA ENTRY'!$U17=""),"Not entered",IF('DATA ENTRY'!$U17<=0,"High-risk",IF($N17>=0.15,"Strong",IF($N17>=0.08,"Adequate",IF($N17>=0,"Caution","High-risk")))))) | P17: =IF(OR($B17="",'DATA ENTRY'!$K17="",'DATA ENTRY'!$R17=""),"",IFERROR('DATA ENTRY'!$K17/'DATA ENTRY'!$R17,"")) | Q17: =IF($B17="","",IF($P17="","Not entered",IF($P17>=1.5,"Strong",IF($P17>=1.2,"Adequate",IF($P17>=1,"Caution","High-risk"))))) | R17: =IF(OR($B17="",'DATA ENTRY'!$K17="",'DATA ENTRY'!$R17=""),"",IFERROR(('DATA ENTRY'!$K17-IF('DATA ENTRY'!$O17="",0,'DATA ENTRY'!$O17))/'DATA ENTRY'!$R17,"")) | S17: =IF($B17="","",IF($R17="","Not entered",IF($R17>=1,"Strong",IF($R17>=0.8,"Adequate",IF($R17>=0.6,"Caution","High-risk"))))) | T17: =IF(OR($B17="",'DATA ENTRY'!$T17="",'DATA ENTRY'!$U17="",'DATA ENTRY'!$U17<=0),"",IFERROR('DATA ENTRY'!$T17/'DATA ENTRY'!$U17,"")) | U17: =IF($B17="","",IF(OR('DATA ENTRY'!$T17="",'DATA ENTRY'!$U17=""),"Not entered",IF('DATA ENTRY'!$U17<=0,"High-risk",IF($T17<=1,"Strong",IF($T17<=1.5,"Adequate",IF($T17<=2,"Caution","High-risk")))))) | V17: =IF(OR($B17="",'DATA ENTRY'!$U17="",'DATA ENTRY'!$Q17=""),"",IFERROR('DATA ENTRY'!$U17/'DATA ENTRY'!$Q17,"")) | W17: =IF($B17="","",IF($V17="","Not entered",IF($V17>=0.5,"Strong",IF($V17>=0.3,"Adequate",IF($V17>=0.2,"Caution","High-risk"))))) | X17: =IF(OR($B17="",'DATA ENTRY'!$G17="",'DATA ENTRY'!$M17=""),"",IF('DATA ENTRY'!$N17<>"",'DATA ENTRY'!$G17/AVERAGE('DATA ENTRY'!$M17,'DATA ENTRY'!$N17),IFERROR('DATA ENTRY'!$G17/'DATA ENTRY'!$M17,""))) | Y17: =IF($X17="","",IFERROR(365/$X17,"")) | Z17: =IF($B17="","",IF($X17="","Not entered",IF($Y17<=60,"Strong",IF($Y17<=90,"Adequate",IF($Y17<=120,"Caution","High-risk"))))) | AA17: =IF(OR($B17="",'DATA ENTRY'!$G17="",'DATA ENTRY'!$Q17=""),"",IFERROR('DATA ENTRY'!$G17/'DATA ENTRY'!$Q17,"")) | AB17: =IF($B17="","",IF($AA17="","Not entered",IF($AA17>=1.5,"Strong",IF($AA17>=1,"Adequate",IF($AA17>=0.5,"Caution","High-risk"))))) | AC17: =IF(OR($B17="",'DATA ENTRY'!$K17="",'DATA ENTRY'!$R17=""),"",'DATA ENTRY'!$K17-'DATA ENTRY'!$R17) | AD17: =IF($B17="","",IF($AC17="","Not entered",IF($AC17<0,"High-risk",IF($AC17=0,"Caution",IF('DATA ENTRY'!$L17="","Adequate",IFERROR(IF('DATA ENTRY'!$L17/'DATA ENTRY'!$R17>=0.25,"Strong","Adequate"),"Adequate")))))) | AE17: =IF($B17="","",IF(OR('DATA ENTRY'!$W17="",'DATA ENTRY'!$W17=0),"N/A",IF('DATA ENTRY'!$V17="","",IFERROR('DATA ENTRY'!$V17/'DATA ENTRY'!$W17,"")))) | AF17: =IF($B17="","",IF($AE17="N/A","Not applicable",IF($AE17="","Not entered",IF($AE17>=4,"Strong",IF($AE17>=2.5,"Adequate",IF($AE17>=1.5,"Caution","High-risk")))))) | AG17: =IF($B17="","",IFERROR(ROUND((COUNTIF($I17:$AF17,"Strong")*4+COUNTIF($I17:$AF17,"Adequate")*3+COUNTIF($I17:$AF17,"Caution")*2+COUNTIF($I17:$AF17,"High-risk")*1)/(COUNTIF($I17:$AF17,"Strong")+COUNTIF($I17:$AF17,"Adequate")+COUNTIF($I17:$AF17,"Caution")+COUNTIF($I17:$AF17,"High-risk")),2),"")) | AH17: =IF($B17="","",IF(AND(ISNUMBER('DATA ENTRY'!$U17),'DATA ENTRY'!$U17<=0),"Financially stretched",IF($AG17="","Insufficient data",IF(AND(ISNUMBER('DATA ENTRY'!$J17),'DATA ENTRY'!$J17<0),IF($AG17>=2,"Adequate with caution","Financially stretched"),IF($AG17>=3.5,"Financially strong",IF($AG17>=2.75,"Financially adequate",IF($AG17>=2,"Adequate with caution","Financially stretched"))))))) | AI17: =IF($B17="","",IF(AND(ISNUMBER('DATA ENTRY'!$U17),'DATA ENTRY'!$U17<=0),"Negative equity — possible insolvency",IF(AND(ISNUMBER('DATA ENTRY'!$J17),'DATA ENTRY'!$J17<0),"Loss position",IF(AND(ISNUMBER($P17),$P17<1),"Current liabilities exceed current assets",IF(AND(ISNUMBER($T17),$T17>2),"High leverage",IF(AND(ISNUMBER($Y17),$Y17>120),"Slow receivables collection",IF(AND(ISNUMBER($AC17),$AC17<0),"Negative working capital",IF(OR('DATA ENTRY'!$E17="Unaudited",'DATA ENTRY'!$E17="Banker Letter Only",'DATA ENTRY'!$E17="Management Accounts"),"Statement status limits weight on ratios","No major red flag from entered ratios"))))))))
... A35: =IF('DATA ENTRY'!$B35<>"",'DATA ENTRY'!$A35,"") | B35: =IF('DATA ENTRY'!$B35<>"",'DATA ENTRY'!$B35,"") | C35: =IF('DATA ENTRY'!$B35<>"",'DATA ENTRY'!$C35,"") | D35: =IF('DATA ENTRY'!$B35<>"",'DATA ENTRY'!$D35,"") | E35: =IF('DATA ENTRY'!$B35<>"",'DATA ENTRY'!$E35,"") | F35: =IF($B35="","",IF('DATA ENTRY'!$Y35="Yes","Checked",IF('DATA ENTRY'!$Y35="No","Needs check","Not marked"))) | G35: =IF($B35="","",IF('DATA ENTRY'!$I35<>"",'DATA ENTRY'!$I35,IF(AND('DATA ENTRY'!$G35<>"",'DATA ENTRY'!$H35<>""),'DATA ENTRY'!$G35-'DATA ENTRY'!$H35,""))) | H35: =IF(OR($B35="",$G35="",'DATA ENTRY'!$G35=""),"",IFERROR($G35/'DATA ENTRY'!$G35,"")) | I35: =IF($B35="","",IF($H35="","Not entered",IF($H35>=0.25,"Strong",IF($H35>=0.15,"Adequate",IF($H35>=0.05,"Caution","High-risk"))))) | J35: =IF(OR($B35="",'DATA ENTRY'!$J35="",'DATA ENTRY'!$G35=""),"",IFERROR('DATA ENTRY'!$J35/'DATA ENTRY'!$G35,"")) | K35: =IF($B35="","",IF($J35="","Not entered",IF($J35>=0.08,"Strong",IF($J35>=0.03,"Adequate",IF($J35>=0,"Caution","High-risk"))))) | L35: =IF(OR($B35="",'DATA ENTRY'!$J35="",'DATA ENTRY'!$Q35=""),"",IFERROR('DATA ENTRY'!$J35/'DATA ENTRY'!$Q35,"")) | M35: =IF($B35="","",IF($L35="","Not entered",IF($L35>=0.1,"Strong",IF($L35>=0.05,"Adequate",IF($L35>=0,"Caution","High-risk"))))) | N35: =IF(OR($B35="",'DATA ENTRY'!$J35="",'DATA ENTRY'!$U35="",'DATA ENTRY'!$U35<=0),"",IFERROR('DATA ENTRY'!$J35/'DATA ENTRY'!$U35,"")) | O35: =IF($B35="","",IF(OR('DATA ENTRY'!$J35="",'DATA ENTRY'!$U35=""),"Not entered",IF('DATA ENTRY'!$U35<=0,"High-risk",IF($N35>=0.15,"Strong",IF($N35>=0.08,"Adequate",IF($N35>=0,"Caution","High-risk")))))) | P35: =IF(OR($B35="",'DATA ENTRY'!$K35="",'DATA ENTRY'!$R35=""),"",IFERROR('DATA ENTRY'!$K35/'DATA ENTRY'!$R35,"")) | Q35: =IF($B35="","",IF($P35="","Not entered",IF($P35>=1.5,"Strong",IF($P35>=1.2,"Adequate",IF($P35>=1,"Caution","High-risk"))))) | R35: =IF(OR($B35="",'DATA ENTRY'!$K35="",'DATA ENTRY'!$R35=""),"",IFERROR(('DATA ENTRY'!$K35-IF('DATA ENTRY'!$O35="",0,'DATA ENTRY'!$O35))/'DATA ENTRY'!$R35,"")) | S35: =IF($B35="","",IF($R35="","Not entered",IF($R35>=1,"Strong",IF($R35>=0.8,"Adequate",IF($R35>=0.6,"Caution","High-risk"))))) | T35: =IF(OR($B35="",'DATA ENTRY'!$T35="",'DATA ENTRY'!$U35="",'DATA ENTRY'!$U35<=0),"",IFERROR('DATA ENTRY'!$T35/'DATA ENTRY'!$U35,"")) | U35: =IF($B35="","",IF(OR('DATA ENTRY'!$T35="",'DATA ENTRY'!$U35=""),"Not entered",IF('DATA ENTRY'!$U35<=0,"High-risk",IF($T35<=1,"Strong",IF($T35<=1.5,"Adequate",IF($T35<=2,"Caution","High-risk")))))) | V35: =IF(OR($B35="",'DATA ENTRY'!$U35="",'DATA ENTRY'!$Q35=""),"",IFERROR('DATA ENTRY'!$U35/'DATA ENTRY'!$Q35,"")) | W35: =IF($B35="","",IF($V35="","Not entered",IF($V35>=0.5,"Strong",IF($V35>=0.3,"Adequate",IF($V35>=0.2,"Caution","High-risk"))))) | X35: =IF(OR($B35="",'DATA ENTRY'!$G35="",'DATA ENTRY'!$M35=""),"",IF('DATA ENTRY'!$N35<>"",'DATA ENTRY'!$G35/AVERAGE('DATA ENTRY'!$M35,'DATA ENTRY'!$N35),IFERROR('DATA ENTRY'!$G35/'DATA ENTRY'!$M35,""))) | Y35: =IF($X35="","",IFERROR(365/$X35,"")) | Z35: =IF($B35="","",IF($X35="","Not entered",IF($Y35<=60,"Strong",IF($Y35<=90,"Adequate",IF($Y35<=120,"Caution","High-risk"))))) | AA35: =IF(OR($B35="",'DATA ENTRY'!$G35="",'DATA ENTRY'!$Q35=""),"",IFERROR('DATA ENTRY'!$G35/'DATA ENTRY'!$Q35,"")) | AB35: =IF($B35="","",IF($AA35="","Not entered",IF($AA35>=1.5,"Strong",IF($AA35>=1,"Adequate",IF($AA35>=0.5,"Caution","High-risk"))))) | AC35: =IF(OR($B35="",'DATA ENTRY'!$K35="",'DATA ENTRY'!$R35=""),"",'DATA ENTRY'!$K35-'DATA ENTRY'!$R35) | AD35: =IF($B35="","",IF($AC35="","Not entered",IF($AC35<0,"High-risk",IF($AC35=0,"Caution",IF('DATA ENTRY'!$L35="","Adequate",IFERROR(IF('DATA ENTRY'!$L35/'DATA ENTRY'!$R35>=0.25,"Strong","Adequate"),"Adequate")))))) | AE35: =IF($B35="","",IF(OR('DATA ENTRY'!$W35="",'DATA ENTRY'!$W35=0),"N/A",IF('DATA ENTRY'!$V35="","",IFERROR('DATA ENTRY'!$V35/'DATA ENTRY'!$W35,"")))) | AF35: =IF($B35="","",IF($AE35="N/A","Not applicable",IF($AE35="","Not entered",IF($AE35>=4,"Strong",IF($AE35>=2.5,"Adequate",IF($AE35>=1.5,"Caution","High-risk")))))) | AG35: =IF($B35="","",IFERROR(ROUND((COUNTIF($I35:$AF35,"Strong")*4+COUNTIF($I35:$AF35,"Adequate")*3+COUNTIF($I35:$AF35,"Caution")*2+COUNTIF($I35:$AF35,"High-risk")*1)/(COUNTIF($I35:$AF35,"Strong")+COUNTIF($I35:$AF35,"Adequate")+COUNTIF($I35:$AF35,"Caution")+COUNTIF($I35:$AF35,"High-risk")),2),"")) | AH35: =IF($B35="","",IF(AND(ISNUMBER('DATA ENTRY'!$U35),'DATA ENTRY'!$U35<=0),"Financially stretched",IF($AG35="","Insufficient data",IF(AND(ISNUMBER('DATA ENTRY'!$J35),'DATA ENTRY'!$J35<0),IF($AG35>=2,"Adequate with caution","Financially stretched"),IF($AG35>=3.5,"Financially strong",IF($AG35>=2.75,"Financially adequate",IF($AG35>=2,"Adequate with caution","Financially stretched"))))))) | AI35: =IF($B35="","",IF(AND(ISNUMBER('DATA ENTRY'!$U35),'DATA ENTRY'!$U35<=0),"Negative equity — possible insolvency",IF(AND(ISNUMBER('DATA ENTRY'!$J35),'DATA ENTRY'!$J35<0),"Loss position",IF(AND(ISNUMBER($P35),$P35<1),"Current liabilities exceed current assets",IF(AND(ISNUMBER($T35),$T35>2),"High leverage",IF(AND(ISNUMBER($Y35),$Y35>120),"Slow receivables collection",IF(AND(ISNUMBER($AC35),$AC35<0),"Negative working capital",IF(OR('DATA ENTRY'!$E35="Unaudited",'DATA ENTRY'!$E35="Banker Letter Only",'DATA ENTRY'!$E35="Management Accounts"),"Statement status limits weight on ratios","No major red flag from entered ratios"))))))))

Sheet DASHBOARD
A1: DASHBOARD — COMMITTEE SCREENING VIEW
A2: Quick view only. Verify source figures before recording any finding.
A4: Bidder rows entered | C4: Strong | E4: Adequate | G4: With caution | I4: Stretched | K4: Need figure check
A5: =COUNTIF('DATA ENTRY'!B6:B35,"?*") -> 0 | C5: =COUNTIF('RATIO RESULTS'!AH6:AH35,"Financially strong") -> 0 | E5: =COUNTIF('RATIO RESULTS'!AH6:AH35,"Financially adequate") -> 0 | G5: =COUNTIF('RATIO RESULTS'!AH6:AH35,"Adequate with caution") -> 0 | I5: =COUNTIF('RATIO RESULTS'!AH6:AH35,"Financially stretched") -> 0 | K5: =COUNTIF('RATIO RESULTS'!F6:F35,"Needs check")+COUNTIF('RATIO RESULTS'!F6:F35,"Not marked") -> 0
A8: Record | B8: Bidder | C8: Sector | D8: Year | E8: Current Ratio | F8: Debt/Equity | G8: Net Margin | H8: Working Capital | I8: Overall Rating | J8: Main Flag | K8: Source Check | L8: Chair Note
A9: =IF('RATIO RESULTS'!$B6<>"",'RATIO RESULTS'!$A6,"") | B9: =IF('RATIO RESULTS'!$B6<>"",'RATIO RESULTS'!$B6,"") | C9: =IF('RATIO RESULTS'!$B6<>"",'RATIO RESULTS'!$C6,"") | D9: =IF('RATIO RESULTS'!$B6<>"",'RATIO RESULTS'!$D6,"") | E9: =IF('RATIO RESULTS'!$B6<>"",'RATIO RESULTS'!$P6,"") | F9: =IF('RATIO RESULTS'!$B6<>"",'RATIO RESULTS'!$T6,"") | G9: =IF('RATIO RESULTS'!$B6<>"",'RATIO RESULTS'!$J6,"") | H9: =IF('RATIO RESULTS'!$B6<>"",'RATIO RESULTS'!$AC6,"") | I9: =IF('RATIO RESULTS'!$B6<>"",'RATIO RESULTS'!$AH6,"") | J9: =IF('RATIO RESULTS'!$B6<>"",'RATIO RESULTS'!$AI6,"") | K9: =IF('RATIO RESULTS'!$B6<>"",'RATIO RESULTS'!$F6,"") | L9: =IF('RATIO RESULTS'!$B6<>"","Verify source figures before recording finding.","")
A10: =IF('RATIO RESULTS'!$B7<>"",'RATIO RESULTS'!$A7,"") | B10: =IF('RATIO RESULTS'!$B7<>"",'RATIO RESULTS'!$B7,"") | C10: =IF('RATIO RESULTS'!$B7<>"",'RATIO RESULTS'!$C7,"") | D10: =IF('RATIO RESULTS'!$B7<>"",'RATIO RESULTS'!$D7,"") | E10: =IF('RATIO RESULTS'!$B7<>"",'RATIO RESULTS'!$P7,"") | F10: =IF('RATIO RESULTS'!$B7<>"",'RATIO RESULTS'!$T7,"") | G10: =IF('RATIO RESULTS'!$B7<>"",'RATIO RESULTS'!$J7,"") | H10: =IF('RATIO RESULTS'!$B7<>"",'RATIO RESULTS'!$AC7,"") | I10: =IF('RATIO RESULTS'!$B7<>"",'RATIO RESULTS'!$AH7,"") | J10: =IF('RATIO RESULTS'!$B7<>"",'RATIO RESULTS'!$AI7,"") | K10: =IF('RATIO RESULTS'!$B7<>"",'RATIO RESULTS'!$F7,"") | L10: =IF('RATIO RESULTS'!$B7<>"","Verify source figures before recording finding.","")
A11: =IF('RATIO RESULTS'!$B8<>"",'RATIO RESULTS'!$A8,"") | B11: =IF('RATIO RESULTS'!$B8<>"",'RATIO RESULTS'!$B8,"") | C11: =IF('RATIO RESULTS'!$B8<>"",'RATIO RESULTS'!$C8,"") | D11: =IF('RATIO RESULTS'!$B8<>"",'RATIO RESULTS'!$D8,"") | E11: =IF('RATIO RESULTS'!$B8<>"",'RATIO RESULTS'!$P8,"") | F11: =IF('RATIO RESULTS'!$B8<>"",'RATIO RESULTS'!$T8,"") | G11: =IF('RATIO RESULTS'!$B8<>"",'RATIO RESULTS'!$J8,"") | H11: =IF('RATIO RESULTS'!$B8<>"",'RATIO RESULTS'!$AC8,"") | I11: =IF('RATIO RESULTS'!$B8<>"",'RATIO RESULTS'!$AH8,"") | J11: =IF('RATIO RESULTS'!$B8<>"",'RATIO RESULTS'!$AI8,"") | K11: =IF('RATIO RESULTS'!$B8<>"",'RATIO RESULTS'!$F8,"") | L11: =IF('RATIO RESULTS'!$B8<>"","Verify source figures before recording finding.","")
A12: =IF('RATIO RESULTS'!$B9<>"",'RATIO RESULTS'!$A9,"") | B12: =IF('RATIO RESULTS'!$B9<>"",'RATIO RESULTS'!$B9,"") | C12: =IF('RATIO RESULTS'!$B9<>"",'RATIO RESULTS'!$C9,"") | D12: =IF('RATIO RESULTS'!$B9<>"",'RATIO RESULTS'!$D9,"") | E12: =IF('RATIO RESULTS'!$B9<>"",'RATIO RESULTS'!$P9,"") | F12: =IF('RATIO RESULTS'!$B9<>"",'RATIO RESULTS'!$T9,"") | G12: =IF('RATIO RESULTS'!$B9<>"",'RATIO RESULTS'!$J9,"") | H12: =IF('RATIO RESULTS'!$B9<>"",'RATIO RESULTS'!$AC9,"") | I12: =IF('RATIO RESULTS'!$B9<>"",'RATIO RESULTS'!$AH9,"") | J12: =IF('RATIO RESULTS'!$B9<>"",'RATIO RESULTS'!$AI9,"") | K12: =IF('RATIO RESULTS'!$B9<>"",'RATIO RESULTS'!$F9,"") | L12: =IF('RATIO RESULTS'!$B9<>"","Verify source figures before recording finding.","")
A13: =IF('RATIO RESULTS'!$B10<>"",'RATIO RESULTS'!$A10,"") | B13: =IF('RATIO RESULTS'!$B10<>"",'RATIO RESULTS'!$B10,"") | C13: =IF('RATIO RESULTS'!$B10<>"",'RATIO RESULTS'!$C10,"") | D13: =IF('RATIO RESULTS'!$B10<>"",'RATIO RESULTS'!$D10,"") | E13: =IF('RATIO RESULTS'!$B10<>"",'RATIO RESULTS'!$P10,"") | F13: =IF('RATIO RESULTS'!$B10<>"",'RATIO RESULTS'!$T10,"") | G13: =IF('RATIO RESULTS'!$B10<>"",'RATIO RESULTS'!$J10,"") | H13: =IF('RATIO RESULTS'!$B10<>"",'RATIO RESULTS'!$AC10,"") | I13: =IF('RATIO RESULTS'!$B10<>"",'RATIO RESULTS'!$AH10,"") | J13: =IF('RATIO RESULTS'!$B10<>"",'RATIO RESULTS'!$AI10,"") | K13: =IF('RATIO RESULTS'!$B10<>"",'RATIO RESULTS'!$F10,"") | L13: =IF('RATIO RESULTS'!$B10<>"","Verify source figures before recording finding.","")
A14: =IF('RATIO RESULTS'!$B11<>"",'RATIO RESULTS'!$A11,"") | B14: =IF('RATIO RESULTS'!$B11<>"",'RATIO RESULTS'!$B11,"") | C14: =IF('RATIO RESULTS'!$B11<>"",'RATIO RESULTS'!$C11,"") | D14: =IF('RATIO RESULTS'!$B11<>"",'RATIO RESULTS'!$D11,"") | E14: =IF('RATIO RESULTS'!$B11<>"",'RATIO RESULTS'!$P11,"") | F14: =IF('RATIO RESULTS'!$B11<>"",'RATIO RESULTS'!$T11,"") | G14: =IF('RATIO RESULTS'!$B11<>"",'RATIO RESULTS'!$J11,"") | H14: =IF('RATIO RESULTS'!$B11<>"",'RATIO RESULTS'!$AC11,"") | I14: =IF('RATIO RESULTS'!$B11<>"",'RATIO RESULTS'!$AH11,"") | J14: =IF('RATIO RESULTS'!$B11<>"",'RATIO RESULTS'!$AI11,"") | K14: =IF('RATIO RESULTS'!$B11<>"",'RATIO RESULTS'!$F11,"") | L14: =IF('RATIO RESULTS'!$B11<>"","Verify source figures before recording finding.","")
A15: =IF('RATIO RESULTS'!$B12<>"",'RATIO RESULTS'!$A12,"") | B15: =IF('RATIO RESULTS'!$B12<>"",'RATIO RESULTS'!$B12,"") | C15: =IF('RATIO RESULTS'!$B12<>"",'RATIO RESULTS'!$C12,"") | D15: =IF('RATIO RESULTS'!$B12<>"",'RATIO RESULTS'!$D12,"") | E15: =IF('RATIO RESULTS'!$B12<>"",'RATIO RESULTS'!$P12,"") | F15: =IF('RATIO RESULTS'!$B12<>"",'RATIO RESULTS'!$T12,"") | G15: =IF('RATIO RESULTS'!$B12<>"",'RATIO RESULTS'!$J12,"") | H15: =IF('RATIO RESULTS'!$B12<>"",'RATIO RESULTS'!$AC12,"") | I15: =IF('RATIO RESULTS'!$B12<>"",'RATIO RESULTS'!$AH12,"") | J15: =IF('RATIO RESULTS'!$B12<>"",'RATIO RESULTS'!$AI12,"") | K15: =IF('RATIO RESULTS'!$B12<>"",'RATIO RESULTS'!$F12,"") | L15: =IF('RATIO RESULTS'!$B12<>"","Verify source figures before recording finding.","")
A16: =IF('RATIO RESULTS'!$B13<>"",'RATIO RESULTS'!$A13,"") | B16: =IF('RATIO RESULTS'!$B13<>"",'RATIO RESULTS'!$B13,"") | C16: =IF('RATIO RESULTS'!$B13<>"",'RATIO RESULTS'!$C13,"") | D16: =IF('RATIO RESULTS'!$B13<>"",'RATIO RESULTS'!$D13,"") | E16: =IF('RATIO RESULTS'!$B13<>"",'RATIO RESULTS'!$P13,"") | F16: =IF('RATIO RESULTS'!$B13<>"",'RATIO RESULTS'!$T13,"") | G16: =IF('RATIO RESULTS'!$B13<>"",'RATIO RESULTS'!$J13,"") | H16: =IF('RATIO RESULTS'!$B13<>"",'RATIO RESULTS'!$AC13,"") | I16: =IF('RATIO RESULTS'!$B13<>"",'RATIO RESULTS'!$AH13,"") | J16: =IF('RATIO RESULTS'!$B13<>"",'RATIO RESULTS'!$AI13,"") | K16: =IF('RATIO RESULTS'!$B13<>"",'RATIO RESULTS'!$F13,"") | L16: =IF('RATIO RESULTS'!$B13<>"","Verify source figures before recording finding.","")
A17: =IF('RATIO RESULTS'!$B14<>"",'RATIO RESULTS'!$A14,"") | B17: =IF('RATIO RESULTS'!$B14<>"",'RATIO RESULTS'!$B14,"") | C17: =IF('RATIO RESULTS'!$B14<>"",'RATIO RESULTS'!$C14,"") | D17: =IF('RATIO RESULTS'!$B14<>"",'RATIO RESULTS'!$D14,"") | E17: =IF('RATIO RESULTS'!$B14<>"",'RATIO RESULTS'!$P14,"") | F17: =IF('RATIO RESULTS'!$B14<>"",'RATIO RESULTS'!$T14,"") | G17: =IF('RATIO RESULTS'!$B14<>"",'RATIO RESULTS'!$J14,"") | H17: =IF('RATIO RESULTS'!$B14<>"",'RATIO RESULTS'!$AC14,"") | I17: =IF('RATIO RESULTS'!$B14<>"",'RATIO RESULTS'!$AH14,"") | J17: =IF('RATIO RESULTS'!$B14<>"",'RATIO RESULTS'!$AI14,"") | K17: =IF('RATIO RESULTS'!$B14<>"",'RATIO RESULTS'!$F14,"") | L17: =IF('RATIO RESULTS'!$B14<>"","Verify source figures before recording finding.","")
A18: =IF('RATIO RESULTS'!$B15<>"",'RATIO RESULTS'!$A15,"") | B18: =IF('RATIO RESULTS'!$B15<>"",'RATIO RESULTS'!$B15,"") | C18: =IF('RATIO RESULTS'!$B15<>"",'RATIO RESULTS'!$C15,"") | D18: =IF('RATIO RESULTS'!$B15<>"",'RATIO RESULTS'!$D15,"") | E18: =IF('RATIO RESULTS'!$B15<>"",'RATIO RESULTS'!$P15,"") | F18: =IF('RATIO RESULTS'!$B15<>"",'RATIO RESULTS'!$T15,"") | G18: =IF('RATIO RESULTS'!$B15<>"",'RATIO RESULTS'!$J15,"") | H18: =IF('RATIO RESULTS'!$B15<>"",'RATIO RESULTS'!$AC15,"") | I18: =IF('RATIO RESULTS'!$B15<>"",'RATIO RESULTS'!$AH15,"") | J18: =IF('RATIO RESULTS'!$B15<>"",'RATIO RESULTS'!$AI15,"") | K18: =IF('RATIO RESULTS'!$B15<>"",'RATIO RESULTS'!$F15,"") | L18: =IF('RATIO RESULTS'!$B15<>"","Verify source figures before recording finding.","")
A19: =IF('RATIO RESULTS'!$B16<>"",'RATIO RESULTS'!$A16,"") | B19: =IF('RATIO RESULTS'!$B16<>"",'RATIO RESULTS'!$B16,"") | C19: =IF('RATIO RESULTS'!$B16<>"",'RATIO RESULTS'!$C16,"") | D19: =IF('RATIO RESULTS'!$B16<>"",'RATIO RESULTS'!$D16,"") | E19: =IF('RATIO RESULTS'!$B16<>"",'RATIO RESULTS'!$P16,"") | F19: =IF('RATIO RESULTS'!$B16<>"",'RATIO RESULTS'!$T16,"") | G19: =IF('RATIO RESULTS'!$B16<>"",'RATIO RESULTS'!$J16,"") | H19: =IF('RATIO RESULTS'!$B16<>"",'RATIO RESULTS'!$AC16,"") | I19: =IF('RATIO RESULTS'!$B16<>"",'RATIO RESULTS'!$AH16,"") | J19: =IF('RATIO RESULTS'!$B16<>"",'RATIO RESULTS'!$AI16,"") | K19: =IF('RATIO RESULTS'!$B16<>"",'RATIO RESULTS'!$F16,"") | L19: =IF('RATIO RESULTS'!$B16<>"","Verify source figures before recording finding.","")
A20: =IF('RATIO RESULTS'!$B17<>"",'RATIO RESULTS'!$A17,"") | B20: =IF('RATIO RESULTS'!$B17<>"",'RATIO RESULTS'!$B17,"") | C20: =IF('RATIO RESULTS'!$B17<>"",'RATIO RESULTS'!$C17,"") | D20: =IF('RATIO RESULTS'!$B17<>"",'RATIO RESULTS'!$D17,"") | E20: =IF('RATIO RESULTS'!$B17<>"",'RATIO RESULTS'!$P17,"") | F20: =IF('RATIO RESULTS'!$B17<>"",'RATIO RESULTS'!$T17,"") | G20: =IF('RATIO RESULTS'!$B17<>"",'RATIO RESULTS'!$J17,"") | H20: =IF('RATIO RESULTS'!$B17<>"",'RATIO RESULTS'!$AC17,"") | I20: =IF('RATIO RESULTS'!$B17<>"",'RATIO RESULTS'!$AH17,"") | J20: =IF('RATIO RESULTS'!$B17<>"",'RATIO RESULTS'!$AI17,"") | K20: =IF('RATIO RESULTS'!$B17<>"",'RATIO RESULTS'!$F17,"") | L20: =IF('RATIO RESULTS'!$B17<>"","Verify source figures before recording finding.","")
... A38: =IF('RATIO RESULTS'!$B35<>"",'RATIO RESULTS'!$A35,"") | B38: =IF('RATIO RESULTS'!$B35<>"",'RATIO RESULTS'!$B35,"") | C38: =IF('RATIO RESULTS'!$B35<>"",'RATIO RESULTS'!$C35,"") | D38: =IF('RATIO RESULTS'!$B35<>"",'RATIO RESULTS'!$D35,"") | E38: =IF('RATIO RESULTS'!$B35<>"",'RATIO RESULTS'!$P35,"") | F38: =IF('RATIO RESULTS'!$B35<>"",'RATIO RESULTS'!$T35,"") | G38: =IF('RATIO RESULTS'!$B35<>"",'RATIO RESULTS'!$J35,"") | H38: =IF('RATIO RESULTS'!$B35<>"",'RATIO RESULTS'!$AC35,"") | I38: =IF('RATIO RESULTS'!$B35<>"",'RATIO RESULTS'!$AH35,"") | J38: =IF('RATIO RESULTS'!$B35<>"",'RATIO RESULTS'!$AI35,"") | K38: =IF('RATIO RESULTS'!$B35<>"",'RATIO RESULTS'!$F35,"") | L38: =IF('RATIO RESULTS'!$B35<>"","Verify source figures before recording finding.","")

Sheet FINDING BUILDER
A1: FINDING BUILDER — DEFENSIBLE COMMITTEE WORDING
A2: Generated wording must still be checked by the Committee. Do not use any sentence unless the source figures and approved criteria support it.
A5: Record | B5: Bidder | C5: Year | D5: Overall Rating | E5: Main Flag | F5: Model Finding | G5: Clarification Question | H5: Chair Check
A6: =IF('RATIO RESULTS'!$B6<>"",'RATIO RESULTS'!$A6,"") | B6: =IF('RATIO RESULTS'!$B6<>"",'RATIO RESULTS'!$B6,"") | C6: =IF('RATIO RESULTS'!$B6<>"",'RATIO RESULTS'!$D6,"") | D6: =IF('RATIO RESULTS'!$B6<>"",'RATIO RESULTS'!$AH6,"") | E6: =IF('RATIO RESULTS'!$B6<>"",'RATIO RESULTS'!$AI6,"") | F6: =IF('RATIO RESULTS'!$B6="","","The Committee reviewed "&'RATIO RESULTS'!$B6&" for financial year "&'RATIO RESULTS'!$D6&" using the submitted financial statement figures entered in the workbook. On a first-pass screening basis, the bidder is assessed as "&LOWER('RATIO RESULTS'!$AH6)&". Key indicators include Current Ratio "&IF(ISNUMBER('RATIO RESULTS'!$P6),TEXT('RATIO RESULTS'!$P6,"0.00"),"not available")&", Debt-to-Equity "&IF(ISNUMBER('RATIO RESULTS'!$T6),TEXT('RATIO RESULTS'!$T6,"0.00"),"not available")&", Net Profit Margin "&IF(ISNUMBER('RATIO RESULTS'!$J6),TEXT('RATIO RESULTS'!$J6,"0.00%"),"not available")&", and Working Capital of "&IF(ISNUMBER('RATIO RESULTS'!$AC6),"TTD "&TEXT('RATIO RESULTS'!$AC6,"#,##0"),"not available")&". The main flag noted is: "&'RATIO RESULTS'!$AI6&". This is a screening finding only and must be read with the approved prequalification criteria and the source documents.") | G6: =IF('RATIO RESULTS'!$B6="","",IF('RATIO RESULTS'!$F6<>"Checked","Confirm source figures and financial year used.",IF('RATIO RESULTS'!$AI6="Negative equity — possible insolvency","Request clarification on negative equity, accumulated losses, and any restructuring or capital injection plans.",IF('RATIO RESULTS'!$AI6="Loss position","Request explanation for loss position and evidence of capacity to perform.",IF('RATIO RESULTS'!$AI6="Current liabilities exceed current assets","Seek clarification on short-term liquidity and ability to fund mobilisation.",IF('RATIO RESULTS'!$AI6="High leverage","Seek clarification on debt service and financing support.",IF('RATIO RESULTS'!$AI6="Slow receivables collection","Seek receivables ageing and collection status.",IF('RATIO RESULTS'!$AI6="Negative working capital","Seek clarification on working-capital support.",IF('RATIO RESULTS'!$AI6="Statement status limits weight on ratios","Request audited statements before relying on these ratios.","No automatic clarification from ratio screen. Verify against criteria."))))))))) | H6: =IF('RATIO RESULTS'!$B6<>"","Chair to confirm source statement, year, line item, formula and approved criteria before use.","")
A7: =IF('RATIO RESULTS'!$B7<>"",'RATIO RESULTS'!$A7,"") | B7: =IF('RATIO RESULTS'!$B7<>"",'RATIO RESULTS'!$B7,"") | C7: =IF('RATIO RESULTS'!$B7<>"",'RATIO RESULTS'!$D7,"") | D7: =IF('RATIO RESULTS'!$B7<>"",'RATIO RESULTS'!$AH7,"") | E7: =IF('RATIO RESULTS'!$B7<>"",'RATIO RESULTS'!$AI7,"") | F7: =IF('RATIO RESULTS'!$B7="","","The Committee reviewed "&'RATIO RESULTS'!$B7&" for financial year "&'RATIO RESULTS'!$D7&" using the submitted financial statement figures entered in the workbook. On a first-pass screening basis, the bidder is assessed as "&LOWER('RATIO RESULTS'!$AH7)&". Key indicators include Current Ratio "&IF(ISNUMBER('RATIO RESULTS'!$P7),TEXT('RATIO RESULTS'!$P7,"0.00"),"not available")&", Debt-to-Equity "&IF(ISNUMBER('RATIO RESULTS'!$T7),TEXT('RATIO RESULTS'!$T7,"0.00"),"not available")&", Net Profit Margin "&IF(ISNUMBER('RATIO RESULTS'!$J7),TEXT('RATIO RESULTS'!$J7,"0.00%"),"not available")&", and Working Capital of "&IF(ISNUMBER('RATIO RESULTS'!$AC7),"TTD "&TEXT('RATIO RESULTS'!$AC7,"#,##0"),"not available")&". The main flag noted is: "&'RATIO RESULTS'!$AI7&". This is a screening finding only and must be read with the approved prequalification criteria and the source documents.") | G7: =IF('RATIO RESULTS'!$B7="","",IF('RATIO RESULTS'!$F7<>"Checked","Confirm source figures and financial year used.",IF('RATIO RESULTS'!$AI7="Negative equity — possible insolvency","Request clarification on negative equity, accumulated losses, and any restructuring or capital injection plans.",IF('RATIO RESULTS'!$AI7="Loss position","Request explanation for loss position and evidence of capacity to perform.",IF('RATIO RESULTS'!$AI7="Current liabilities exceed current assets","Seek clarification on short-term liquidity and ability to fund mobilisation.",IF('RATIO RESULTS'!$AI7="High leverage","Seek clarification on debt service and financing support.",IF('RATIO RESULTS'!$AI7="Slow receivables collection","Seek receivables ageing and collection status.",IF('RATIO RESULTS'!$AI7="Negative working capital","Seek clarification on working-capital support.",IF('RATIO RESULTS'!$AI7="Statement status limits weight on ratios","Request audited statements before relying on these ratios.","No automatic clarification from ratio screen. Verify against criteria."))))))))) | H7: =IF('RATIO RESULTS'!$B7<>"","Chair to confirm source statement, year, line item, formula and approved criteria before use.","")
A8: =IF('RATIO RESULTS'!$B8<>"",'RATIO RESULTS'!$A8,"") | B8: =IF('RATIO RESULTS'!$B8<>"",'RATIO RESULTS'!$B8,"") | C8: =IF('RATIO RESULTS'!$B8<>"",'RATIO RESULTS'!$D8,"") | D8: =IF('RATIO RESULTS'!$B8<>"",'RATIO RESULTS'!$AH8,"") | E8: =IF('RATIO RESULTS'!$B8<>"",'RATIO RESULTS'!$AI8,"") | F8: =IF('RATIO RESULTS'!$B8="","","The Committee reviewed "&'RATIO RESULTS'!$B8&" for financial year "&'RATIO RESULTS'!$D8&" using the submitted financial statement figures entered in the workbook. On a first-pass screening basis, the bidder is assessed as "&LOWER('RATIO RESULTS'!$AH8)&". Key indicators include Current Ratio "&IF(ISNUMBER('RATIO RESULTS'!$P8),TEXT('RATIO RESULTS'!$P8,"0.00"),"not available")&", Debt-to-Equity "&IF(ISNUMBER('RATIO RESULTS'!$T8),TEXT('RATIO RESULTS'!$T8,"0.00"),"not available")&", Net Profit Margin "&IF(ISNUMBER('RATIO RESULTS'!$J8),TEXT('RATIO RESULTS'!$J8,"0.00%"),"not available")&", and Working Capital of "&IF(ISNUMBER('RATIO RESULTS'!$AC8),"TTD "&TEXT('RATIO RESULTS'!$AC8,"#,##0"),"not available")&". The main flag noted is: "&'RATIO RESULTS'!$AI8&". This is a screening finding only and must be read with the approved prequalification criteria and the source documents.") | G8: =IF('RATIO RESULTS'!$B8="","",IF('RATIO RESULTS'!$F8<>"Checked","Confirm source figures and financial year used.",IF('RATIO RESULTS'!$AI8="Negative equity — possible insolvency","Request clarification on negative equity, accumulated losses, and any restructuring or capital injection plans.",IF('RATIO RESULTS'!$AI8="Loss position","Request explanation for loss position and evidence of capacity to perform.",IF('RATIO RESULTS'!$AI8="Current liabilities exceed current assets","Seek clarification on short-term liquidity and ability to fund mobilisation.",IF('RATIO RESULTS'!$AI8="High leverage","Seek clarification on debt service and financing support.",IF('RATIO RESULTS'!$AI8="Slow receivables collection","Seek receivables ageing and collection status.",IF('RATIO RESULTS'!$AI8="Negative working capital","Seek clarification on working-capital support.",IF('RATIO RESULTS'!$AI8="Statement status limits weight on ratios","Request audited statements before relying on these ratios.","No automatic clarification from ratio screen. Verify against criteria."))))))))) | H8: =IF('RATIO RESULTS'!$B8<>"","Chair to confirm source statement, year, line item, formula and approved criteria before use.","")
A9: =IF('RATIO RESULTS'!$B9<>"",'RATIO RESULTS'!$A9,"") | B9: =IF('RATIO RESULTS'!$B9<>"",'RATIO RESULTS'!$B9,"") | C9: =IF('RATIO RESULTS'!$B9<>"",'RATIO RESULTS'!$D9,"") | D9: =IF('RATIO RESULTS'!$B9<>"",'RATIO RESULTS'!$AH9,"") | E9: =IF('RATIO RESULTS'!$B9<>"",'RATIO RESULTS'!$AI9,"") | F9: =IF('RATIO RESULTS'!$B9="","","The Committee reviewed "&'RATIO RESULTS'!$B9&" for financial year "&'RATIO RESULTS'!$D9&" using the submitted financial statement figures entered in the workbook. On a first-pass screening basis, the bidder is assessed as "&LOWER('RATIO RESULTS'!$AH9)&". Key indicators include Current Ratio "&IF(ISNUMBER('RATIO RESULTS'!$P9),TEXT('RATIO RESULTS'!$P9,"0.00"),"not available")&", Debt-to-Equity "&IF(ISNUMBER('RATIO RESULTS'!$T9),TEXT('RATIO RESULTS'!$T9,"0.00"),"not available")&", Net Profit Margin "&IF(ISNUMBER('RATIO RESULTS'!$J9),TEXT('RATIO RESULTS'!$J9,"0.00%"),"not available")&", and Working Capital of "&IF(ISNUMBER('RATIO RESULTS'!$AC9),"TTD "&TEXT('RATIO RESULTS'!$AC9,"#,##0"),"not available")&". The main flag noted is: "&'RATIO RESULTS'!$AI9&". This is a screening finding only and must be read with the approved prequalification criteria and the source documents.") | G9: =IF('RATIO RESULTS'!$B9="","",IF('RATIO RESULTS'!$F9<>"Checked","Confirm source figures and financial year used.",IF('RATIO RESULTS'!$AI9="Negative equity — possible insolvency","Request clarification on negative equity, accumulated losses, and any restructuring or capital injection plans.",IF('RATIO RESULTS'!$AI9="Loss position","Request explanation for loss position and evidence of capacity to perform.",IF('RATIO RESULTS'!$AI9="Current liabilities exceed current assets","Seek clarification on short-term liquidity and ability to fund mobilisation.",IF('RATIO RESULTS'!$AI9="High leverage","Seek clarification on debt service and financing support.",IF('RATIO RESULTS'!$AI9="Slow receivables collection","Seek receivables ageing and collection status.",IF('RATIO RESULTS'!$AI9="Negative working capital","Seek clarification on working-capital support.",IF('RATIO RESULTS'!$AI9="Statement status limits weight on ratios","Request audited statements before relying on these ratios.","No automatic clarification from ratio screen. Verify against criteria."))))))))) | H9: =IF('RATIO RESULTS'!$B9<>"","Chair to confirm source statement, year, line item, formula and approved criteria before use.","")
A10: =IF('RATIO RESULTS'!$B10<>"",'RATIO RESULTS'!$A10,"") | B10: =IF('RATIO RESULTS'!$B10<>"",'RATIO RESULTS'!$B10,"") | C10: =IF('RATIO RESULTS'!$B10<>"",'RATIO RESULTS'!$D10,"") | D10: =IF('RATIO RESULTS'!$B10<>"",'RATIO RESULTS'!$AH10,"") | E10: =IF('RATIO RESULTS'!$B10<>"",'RATIO RESULTS'!$AI10,"") | F10: =IF('RATIO RESULTS'!$B10="","","The Committee reviewed "&'RATIO RESULTS'!$B10&" for financial year "&'RATIO RESULTS'!$D10&" using the submitted financial statement figures entered in the workbook. On a first-pass screening basis, the bidder is assessed as "&LOWER('RATIO RESULTS'!$AH10)&". Key indicators include Current Ratio "&IF(ISNUMBER('RATIO RESULTS'!$P10),TEXT('RATIO RESULTS'!$P10,"0.00"),"not available")&", Debt-to-Equity "&IF(ISNUMBER('RATIO RESULTS'!$T10),TEXT('RATIO RESULTS'!$T10,"0.00"),"not available")&", Net Profit Margin "&IF(ISNUMBER('RATIO RESULTS'!$J10),TEXT('RATIO RESULTS'!$J10,"0.00%"),"not available")&", and Working Capital of "&IF(ISNUMBER('RATIO RESULTS'!$AC10),"TTD "&TEXT('RATIO RESULTS'!$AC10,"#,##0"),"not available")&". The main flag noted is: "&'RATIO RESULTS'!$AI10&". This is a screening finding only and must be read with the approved prequalification criteria and the source documents.") | G10: =IF('RATIO RESULTS'!$B10="","",IF('RATIO RESULTS'!$F10<>"Checked","Confirm source figures and financial year used.",IF('RATIO RESULTS'!$AI10="Negative equity — possible insolvency","Request clarification on negative equity, accumulated losses, and any restructuring or capital injection plans.",IF('RATIO RESULTS'!$AI10="Loss position","Request explanation for loss position and evidence of capacity to perform.",IF('RATIO RESULTS'!$AI10="Current liabilities exceed current assets","Seek clarification on short-term liquidity and ability to fund mobilisation.",IF('RATIO RESULTS'!$AI10="High leverage","Seek clarification on debt service and financing support.",IF('RATIO RESULTS'!$AI10="Slow receivables collection","Seek receivables ageing and collection status.",IF('RATIO RESULTS'!$AI10="Negative working capital","Seek clarification on working-capital support.",IF('RATIO RESULTS'!$AI10="Statement status limits weight on ratios","Request audited statements before relying on these ratios.","No automatic clarification from ratio screen. Verify against criteria."))))))))) | H10: =IF('RATIO RESULTS'!$B10<>"","Chair to confirm source statement, year, line item, formula and approved criteria before use.","")
A11: =IF('RATIO RESULTS'!$B11<>"",'RATIO RESULTS'!$A11,"") | B11: =IF('RATIO RESULTS'!$B11<>"",'RATIO RESULTS'!$B11,"") | C11: =IF('RATIO RESULTS'!$B11<>"",'RATIO RESULTS'!$D11,"") | D11: =IF('RATIO RESULTS'!$B11<>"",'RATIO RESULTS'!$AH11,"") | E11: =IF('RATIO RESULTS'!$B11<>"",'RATIO RESULTS'!$AI11,"") | F11: =IF('RATIO RESULTS'!$B11="","","The Committee reviewed "&'RATIO RESULTS'!$B11&" for financial year "&'RATIO RESULTS'!$D11&" using the submitted financial statement figures entered in the workbook. On a first-pass screening basis, the bidder is assessed as "&LOWER('RATIO RESULTS'!$AH11)&". Key indicators include Current Ratio "&IF(ISNUMBER('RATIO RESULTS'!$P11),TEXT('RATIO RESULTS'!$P11,"0.00"),"not available")&", Debt-to-Equity "&IF(ISNUMBER('RATIO RESULTS'!$T11),TEXT('RATIO RESULTS'!$T11,"0.00"),"not available")&", Net Profit Margin "&IF(ISNUMBER('RATIO RESULTS'!$J11),TEXT('RATIO RESULTS'!$J11,"0.00%"),"not available")&", and Working Capital of "&IF(ISNUMBER('RATIO RESULTS'!$AC11),"TTD "&TEXT('RATIO RESULTS'!$AC11,"#,##0"),"not available")&". The main flag noted is: "&'RATIO RESULTS'!$AI11&". This is a screening finding only and must be read with the approved prequalification criteria and the source documents.") | G11: =IF('RATIO RESULTS'!$B11="","",IF('RATIO RESULTS'!$F11<>"Checked","Confirm source figures and financial year used.",IF('RATIO RESULTS'!$AI11="Negative equity — possible insolvency","Request clarification on negative equity, accumulated losses, and any restructuring or capital injection plans.",IF('RATIO RESULTS'!$AI11="Loss position","Request explanation for loss position and evidence of capacity to perform.",IF('RATIO RESULTS'!$AI11="Current liabilities exceed current assets","Seek clarification on short-term liquidity and ability to fund mobilisation.",IF('RATIO RESULTS'!$AI11="High leverage","Seek clarification on debt service and financing support.",IF('RATIO RESULTS'!$AI11="Slow receivables collection","Seek receivables ageing and collection status.",IF('RATIO RESULTS'!$AI11="Negative working capital","Seek clarification on working-capital support.",IF('RATIO RESULTS'!$AI11="Statement status limits weight on ratios","Request audited statements before relying on these ratios.","No automatic clarification from ratio screen. Verify against criteria."))))))))) | H11: =IF('RATIO RESULTS'!$B11<>"","Chair to confirm source statement, year, line item, formula and approved criteria before use.","")
A12: =IF('RATIO RESULTS'!$B12<>"",'RATIO RESULTS'!$A12,"") | B12: =IF('RATIO RESULTS'!$B12<>"",'RATIO RESULTS'!$B12,"") | C12: =IF('RATIO RESULTS'!$B12<>"",'RATIO RESULTS'!$D12,"") | D12: =IF('RATIO RESULTS'!$B12<>"",'RATIO RESULTS'!$AH12,"") | E12: =IF('RATIO RESULTS'!$B12<>"",'RATIO RESULTS'!$AI12,"") | F12: =IF('RATIO RESULTS'!$B12="","","The Committee reviewed "&'RATIO RESULTS'!$B12&" for financial year "&'RATIO RESULTS'!$D12&" using the submitted financial statement figures entered in the workbook. On a first-pass screening basis, the bidder is assessed as "&LOWER('RATIO RESULTS'!$AH12)&". Key indicators include Current Ratio "&IF(ISNUMBER('RATIO RESULTS'!$P12),TEXT('RATIO RESULTS'!$P12,"0.00"),"not available")&", Debt-to-Equity "&IF(ISNUMBER('RATIO RESULTS'!$T12),TEXT('RATIO RESULTS'!$T12,"0.00"),"not available")&", Net Profit Margin "&IF(ISNUMBER('RATIO RESULTS'!$J12),TEXT('RATIO RESULTS'!$J12,"0.00%"),"not available")&", and Working Capital of "&IF(ISNUMBER('RATIO RESULTS'!$AC12),"TTD "&TEXT('RATIO RESULTS'!$AC12,"#,##0"),"not available")&". The main flag noted is: "&'RATIO RESULTS'!$AI12&". This is a screening finding only and must be read with the approved prequalification criteria and the source documents.") | G12: =IF('RATIO RESULTS'!$B12="","",IF('RATIO RESULTS'!$F12<>"Checked","Confirm source figures and financial year used.",IF('RATIO RESULTS'!$AI12="Negative equity — possible insolvency","Request clarification on negative equity, accumulated losses, and any restructuring or capital injection plans.",IF('RATIO RESULTS'!$AI12="Loss position","Request explanation for loss position and evidence of capacity to perform.",IF('RATIO RESULTS'!$AI12="Current liabilities exceed current assets","Seek clarification on short-term liquidity and ability to fund mobilisation.",IF('RATIO RESULTS'!$AI12="High leverage","Seek clarification on debt service and financing support.",IF('RATIO RESULTS'!$AI12="Slow receivables collection","Seek receivables ageing and collection status.",IF('RATIO RESULTS'!$AI12="Negative working capital","Seek clarification on working-capital support.",IF('RATIO RESULTS'!$AI12="Statement status limits weight on ratios","Request audited statements before relying on these ratios.","No automatic clarification from ratio screen. Verify against criteria."))))))))) | H12: =IF('RATIO RESULTS'!$B12<>"","Chair to confirm source statement, year, line item, formula and approved criteria before use.","")
A13: =IF('RATIO RESULTS'!$B13<>"",'RATIO RESULTS'!$A13,"") | B13: =IF('RATIO RESULTS'!$B13<>"",'RATIO RESULTS'!$B13,"") | C13: =IF('RATIO RESULTS'!$B13<>"",'RATIO RESULTS'!$D13,"") | D13: =IF('RATIO RESULTS'!$B13<>"",'RATIO RESULTS'!$AH13,"") | E13: =IF('RATIO RESULTS'!$B13<>"",'RATIO RESULTS'!$AI13,"") | F13: =IF('RATIO RESULTS'!$B13="","","The Committee reviewed "&'RATIO RESULTS'!$B13&" for financial year "&'RATIO RESULTS'!$D13&" using the submitted financial statement figures entered in the workbook. On a first-pass screening basis, the bidder is assessed as "&LOWER('RATIO RESULTS'!$AH13)&". Key indicators include Current Ratio "&IF(ISNUMBER('RATIO RESULTS'!$P13),TEXT('RATIO RESULTS'!$P13,"0.00"),"not available")&", Debt-to-Equity "&IF(ISNUMBER('RATIO RESULTS'!$T13),TEXT('RATIO RESULTS'!$T13,"0.00"),"not available")&", Net Profit Margin "&IF(ISNUMBER('RATIO RESULTS'!$J13),TEXT('RATIO RESULTS'!$J13,"0.00%"),"not available")&", and Working Capital of "&IF(ISNUMBER('RATIO RESULTS'!$AC13),"TTD "&TEXT('RATIO RESULTS'!$AC13,"#,##0"),"not available")&". The main flag noted is: "&'RATIO RESULTS'!$AI13&". This is a screening finding only and must be read with the approved prequalification criteria and the source documents.") | G13: =IF('RATIO RESULTS'!$B13="","",IF('RATIO RESULTS'!$F13<>"Checked","Confirm source figures and financial year used.",IF('RATIO RESULTS'!$AI13="Negative equity — possible insolvency","Request clarification on negative equity, accumulated losses, and any restructuring or capital injection plans.",IF('RATIO RESULTS'!$AI13="Loss position","Request explanation for loss position and evidence of capacity to perform.",IF('RATIO RESULTS'!$AI13="Current liabilities exceed current assets","Seek clarification on short-term liquidity and ability to fund mobilisation.",IF('RATIO RESULTS'!$AI13="High leverage","Seek clarification on debt service and financing support.",IF('RATIO RESULTS'!$AI13="Slow receivables collection","Seek receivables ageing and collection status.",IF('RATIO RESULTS'!$AI13="Negative working capital","Seek clarification on working-capital support.",IF('RATIO RESULTS'!$AI13="Statement status limits weight on ratios","Request audited statements before relying on these ratios.","No automatic clarification from ratio screen. Verify against criteria."))))))))) | H13: =IF('RATIO RESULTS'!$B13<>"","Chair to confirm source statement, year, line item, formula and approved criteria before use.","")
A14: =IF('RATIO RESULTS'!$B14<>"",'RATIO RESULTS'!$A14,"") | B14: =IF('RATIO RESULTS'!$B14<>"",'RATIO RESULTS'!$B14,"") | C14: =IF('RATIO RESULTS'!$B14<>"",'RATIO RESULTS'!$D14,"") | D14: =IF('RATIO RESULTS'!$B14<>"",'RATIO RESULTS'!$AH14,"") | E14: =IF('RATIO RESULTS'!$B14<>"",'RATIO RESULTS'!$AI14,"") | F14: =IF('RATIO RESULTS'!$B14="","","The Committee reviewed "&'RATIO RESULTS'!$B14&" for financial year "&'RATIO RESULTS'!$D14&" using the submitted financial statement figures entered in the workbook. On a first-pass screening basis, the bidder is assessed as "&LOWER('RATIO RESULTS'!$AH14)&". Key indicators include Current Ratio "&IF(ISNUMBER('RATIO RESULTS'!$P14),TEXT('RATIO RESULTS'!$P14,"0.00"),"not available")&", Debt-to-Equity "&IF(ISNUMBER('RATIO RESULTS'!$T14),TEXT('RATIO RESULTS'!$T14,"0.00"),"not available")&", Net Profit Margin "&IF(ISNUMBER('RATIO RESULTS'!$J14),TEXT('RATIO RESULTS'!$J14,"0.00%"),"not available")&", and Working Capital of "&IF(ISNUMBER('RATIO RESULTS'!$AC14),"TTD "&TEXT('RATIO RESULTS'!$AC14,"#,##0"),"not available")&". The main flag noted is: "&'RATIO RESULTS'!$AI14&". This is a screening finding only and must be read with the approved prequalification criteria and the source documents.") | G14: =IF('RATIO RESULTS'!$B14="","",IF('RATIO RESULTS'!$F14<>"Checked","Confirm source figures and financial year used.",IF('RATIO RESULTS'!$AI14="Negative equity — possible insolvency","Request clarification on negative equity, accumulated losses, and any restructuring or capital injection plans.",IF('RATIO RESULTS'!$AI14="Loss position","Request explanation for loss position and evidence of capacity to perform.",IF('RATIO RESULTS'!$AI14="Current liabilities exceed current assets","Seek clarification on short-term liquidity and ability to fund mobilisation.",IF('RATIO RESULTS'!$AI14="High leverage","Seek clarification on debt service and financing support.",IF('RATIO RESULTS'!$AI14="Slow receivables collection","Seek receivables ageing and collection status.",IF('RATIO RESULTS'!$AI14="Negative working capital","Seek clarification on working-capital support.",IF('RATIO RESULTS'!$AI14="Statement status limits weight on ratios","Request audited statements before relying on these ratios.","No automatic clarification from ratio screen. Verify against criteria."))))))))) | H14: =IF('RATIO RESULTS'!$B14<>"","Chair to confirm source statement, year, line item, formula and approved criteria before use.","")
A15: =IF('RATIO RESULTS'!$B15<>"",'RATIO RESULTS'!$A15,"") | B15: =IF('RATIO RESULTS'!$B15<>"",'RATIO RESULTS'!$B15,"") | C15: =IF('RATIO RESULTS'!$B15<>"",'RATIO RESULTS'!$D15,"") | D15: =IF('RATIO RESULTS'!$B15<>"",'RATIO RESULTS'!$AH15,"") | E15: =IF('RATIO RESULTS'!$B15<>"",'RATIO RESULTS'!$AI15,"") | F15: =IF('RATIO RESULTS'!$B15="","","The Committee reviewed "&'RATIO RESULTS'!$B15&" for financial year "&'RATIO RESULTS'!$D15&" using the submitted financial statement figures entered in the workbook. On a first-pass screening basis, the bidder is assessed as "&LOWER('RATIO RESULTS'!$AH15)&". Key indicators include Current Ratio "&IF(ISNUMBER('RATIO RESULTS'!$P15),TEXT('RATIO RESULTS'!$P15,"0.00"),"not available")&", Debt-to-Equity "&IF(ISNUMBER('RATIO RESULTS'!$T15),TEXT('RATIO RESULTS'!$T15,"0.00"),"not available")&", Net Profit Margin "&IF(ISNUMBER('RATIO RESULTS'!$J15),TEXT('RATIO RESULTS'!$J15,"0.00%"),"not available")&", and Working Capital of "&IF(ISNUMBER('RATIO RESULTS'!$AC15),"TTD "&TEXT('RATIO RESULTS'!$AC15,"#,##0"),"not available")&". The main flag noted is: "&'RATIO RESULTS'!$AI15&". This is a screening finding only and must be read with the approved prequalification criteria and the source documents.") | G15: =IF('RATIO RESULTS'!$B15="","",IF('RATIO RESULTS'!$F15<>"Checked","Confirm source figures and financial year used.",IF('RATIO RESULTS'!$AI15="Negative equity — possible insolvency","Request clarification on negative equity, accumulated losses, and any restructuring or capital injection plans.",IF('RATIO RESULTS'!$AI15="Loss position","Request explanation for loss position and evidence of capacity to perform.",IF('RATIO RESULTS'!$AI15="Current liabilities exceed current assets","Seek clarification on short-term liquidity and ability to fund mobilisation.",IF('RATIO RESULTS'!$AI15="High leverage","Seek clarification on debt service and financing support.",IF('RATIO RESULTS'!$AI15="Slow receivables collection","Seek receivables ageing and collection status.",IF('RATIO RESULTS'!$AI15="Negative working capital","Seek clarification on working-capital support.",IF('RATIO RESULTS'!$AI15="Statement status limits weight on ratios","Request audited statements before relying on these ratios.","No automatic clarification from ratio screen. Verify against criteria."))))))))) | H15: =IF('RATIO RESULTS'!$B15<>"","Chair to confirm source statement, year, line item, formula and approved criteria before use.","")
A16: =IF('RATIO RESULTS'!$B16<>"",'RATIO RESULTS'!$A16,"") | B16: =IF('RATIO RESULTS'!$B16<>"",'RATIO RESULTS'!$B16,"") | C16: =IF('RATIO RESULTS'!$B16<>"",'RATIO RESULTS'!$D16,"") | D16: =IF('RATIO RESULTS'!$B16<>"",'RATIO RESULTS'!$AH16,"") | E16: =IF('RATIO RESULTS'!$B16<>"",'RATIO RESULTS'!$AI16,"") | F16: =IF('RATIO RESULTS'!$B16="","","The Committee reviewed "&'RATIO RESULTS'!$B16&" for financial year "&'RATIO RESULTS'!$D16&" using the submitted financial statement figures entered in the workbook. On a first-pass screening basis, the bidder is assessed as "&LOWER('RATIO RESULTS'!$AH16)&". Key indicators include Current Ratio "&IF(ISNUMBER('RATIO RESULTS'!$P16),TEXT('RATIO RESULTS'!$P16,"0.00"),"not available")&", Debt-to-Equity "&IF(ISNUMBER('RATIO RESULTS'!$T16),TEXT('RATIO RESULTS'!$T16,"0.00"),"not available")&", Net Profit Margin "&IF(ISNUMBER('RATIO RESULTS'!$J16),TEXT('RATIO RESULTS'!$J16,"0.00%"),"not available")&", and Working Capital of "&IF(ISNUMBER('RATIO RESULTS'!$AC16),"TTD "&TEXT('RATIO RESULTS'!$AC16,"#,##0"),"not available")&". The main flag noted is: "&'RATIO RESULTS'!$AI16&". This is a screening finding only and must be read with the approved prequalification criteria and the source documents.") | G16: =IF('RATIO RESULTS'!$B16="","",IF('RATIO RESULTS'!$F16<>"Checked","Confirm source figures and financial year used.",IF('RATIO RESULTS'!$AI16="Negative equity — possible insolvency","Request clarification on negative equity, accumulated losses, and any restructuring or capital injection plans.",IF('RATIO RESULTS'!$AI16="Loss position","Request explanation for loss position and evidence of capacity to perform.",IF('RATIO RESULTS'!$AI16="Current liabilities exceed current assets","Seek clarification on short-term liquidity and ability to fund mobilisation.",IF('RATIO RESULTS'!$AI16="High leverage","Seek clarification on debt service and financing support.",IF('RATIO RESULTS'!$AI16="Slow receivables collection","Seek receivables ageing and collection status.",IF('RATIO RESULTS'!$AI16="Negative working capital","Seek clarification on working-capital support.",IF('RATIO RESULTS'!$AI16="Statement status limits weight on ratios","Request audited statements before relying on these ratios.","No automatic clarification from ratio screen. Verify against criteria."))))))))) | H16: =IF('RATIO RESULTS'!$B16<>"","Chair to confirm source statement, year, line item, formula and approved criteria before use.","")
A17: =IF('RATIO RESULTS'!$B17<>"",'RATIO RESULTS'!$A17,"") | B17: =IF('RATIO RESULTS'!$B17<>"",'RATIO RESULTS'!$B17,"") | C17: =IF('RATIO RESULTS'!$B17<>"",'RATIO RESULTS'!$D17,"") | D17: =IF('RATIO RESULTS'!$B17<>"",'RATIO RESULTS'!$AH17,"") | E17: =IF('RATIO RESULTS'!$B17<>"",'RATIO RESULTS'!$AI17,"") | F17: =IF('RATIO RESULTS'!$B17="","","The Committee reviewed "&'RATIO RESULTS'!$B17&" for financial year "&'RATIO RESULTS'!$D17&" using the submitted financial statement figures entered in the workbook. On a first-pass screening basis, the bidder is assessed as "&LOWER('RATIO RESULTS'!$AH17)&". Key indicators include Current Ratio "&IF(ISNUMBER('RATIO RESULTS'!$P17),TEXT('RATIO RESULTS'!$P17,"0.00"),"not available")&", Debt-to-Equity "&IF(ISNUMBER('RATIO RESULTS'!$T17),TEXT('RATIO RESULTS'!$T17,"0.00"),"not available")&", Net Profit Margin "&IF(ISNUMBER('RATIO RESULTS'!$J17),TEXT('RATIO RESULTS'!$J17,"0.00%"),"not available")&", and Working Capital of "&IF(ISNUMBER('RATIO RESULTS'!$AC17),"TTD "&TEXT('RATIO RESULTS'!$AC17,"#,##0"),"not available")&". The main flag noted is: "&'RATIO RESULTS'!$AI17&". This is a screening finding only and must be read with the approved prequalification criteria and the source documents.") | G17: =IF('RATIO RESULTS'!$B17="","",IF('RATIO RESULTS'!$F17<>"Checked","Confirm source figures and financial year used.",IF('RATIO RESULTS'!$AI17="Negative equity — possible insolvency","Request clarification on negative equity, accumulated losses, and any restructuring or capital injection plans.",IF('RATIO RESULTS'!$AI17="Loss position","Request explanation for loss position and evidence of capacity to perform.",IF('RATIO RESULTS'!$AI17="Current liabilities exceed current assets","Seek clarification on short-term liquidity and ability to fund mobilisation.",IF('RATIO RESULTS'!$AI17="High leverage","Seek clarification on debt service and financing support.",IF('RATIO RESULTS'!$AI17="Slow receivables collection","Seek receivables ageing and collection status.",IF('RATIO RESULTS'!$AI17="Negative working capital","Seek clarification on working-capital support.",IF('RATIO RESULTS'!$AI17="Statement status limits weight on ratios","Request audited statements before relying on these ratios.","No automatic clarification from ratio screen. Verify against criteria."))))))))) | H17: =IF('RATIO RESULTS'!$B17<>"","Chair to confirm source statement, year, line item, formula and approved criteria before use.","")
... A35: =IF('RATIO RESULTS'!$B35<>"",'RATIO RESULTS'!$A35,"") | B35: =IF('RATIO RESULTS'!$B35<>"",'RATIO RESULTS'!$B35,"") | C35: =IF('RATIO RESULTS'!$B35<>"",'RATIO RESULTS'!$D35,"") | D35: =IF('RATIO RESULTS'!$B35<>"",'RATIO RESULTS'!$AH35,"") | E35: =IF('RATIO RESULTS'!$B35<>"",'RATIO RESULTS'!$AI35,"") | F35: =IF('RATIO RESULTS'!$B35="","","The Committee reviewed "&'RATIO RESULTS'!$B35&" for financial year "&'RATIO RESULTS'!$D35&" using the submitted financial statement figures entered in the workbook. On a first-pass screening basis, the bidder is assessed as "&LOWER('RATIO RESULTS'!$AH35)&". Key indicators include Current Ratio "&IF(ISNUMBER('RATIO RESULTS'!$P35),TEXT('RATIO RESULTS'!$P35,"0.00"),"not available")&", Debt-to-Equity "&IF(ISNUMBER('RATIO RESULTS'!$T35),TEXT('RATIO RESULTS'!$T35,"0.00"),"not available")&", Net Profit Margin "&IF(ISNUMBER('RATIO RESULTS'!$J35),TEXT('RATIO RESULTS'!$J35,"0.00%"),"not available")&", and Working Capital of "&IF(ISNUMBER('RATIO RESULTS'!$AC35),"TTD "&TEXT('RATIO RESULTS'!$AC35,"#,##0"),"not available")&". The main flag noted is: "&'RATIO RESULTS'!$AI35&". This is a screening finding only and must be read with the approved prequalification criteria and the source documents.") | G35: =IF('RATIO RESULTS'!$B35="","",IF('RATIO RESULTS'!$F35<>"Checked","Confirm source figures and financial year used.",IF('RATIO RESULTS'!$AI35="Negative equity — possible insolvency","Request clarification on negative equity, accumulated losses, and any restructuring or capital injection plans.",IF('RATIO RESULTS'!$AI35="Loss position","Request explanation for loss position and evidence of capacity to perform.",IF('RATIO RESULTS'!$AI35="Current liabilities exceed current assets","Seek clarification on short-term liquidity and ability to fund mobilisation.",IF('RATIO RESULTS'!$AI35="High leverage","Seek clarification on debt service and financing support.",IF('RATIO RESULTS'!$AI35="Slow receivables collection","Seek receivables ageing and collection status.",IF('RATIO RESULTS'!$AI35="Negative working capital","Seek clarification on working-capital support.",IF('RATIO RESULTS'!$AI35="Statement status limits weight on ratios","Request audited statements before relying on these ratios.","No automatic clarification from ratio screen. Verify against criteria."))))))))) | H35: =IF('RATIO RESULTS'!$B35<>"","Chair to confirm source statement, year, line item, formula and approved criteria before use.","")

Sheet STATEMENT MAP
A1: STATEMENT MAP — WHERE TO FIND THE NUMBERS
A2: Use this sheet before touching the calculator. Names may differ by company, so read the line item carefully.
A5: Figure needed | B5: Plain meaning | C5: Statement | D5: Common line item names | E5: Used in | F5: Committee caution
A6: Revenue | B6: Money earned from sales or work done. | C6: Income Statement | D6: Revenue; Sales; Income; Gross Revenue | E6: Gross Margin, Net Margin, Receivables Turnover, Asset Turnover | F6: Use the same year as the profit figure.
A7: Cost of Sales / Direct Costs | B7: Direct cost of delivering the job. | C7: Income Statement | D7: Cost of Sales; Direct Costs; Project Costs | E7: Gross Profit if Gross Profit not shown | F7: Do not mix with general office expenses.
A8: Gross Profit | B8: Revenue left after direct job costs. | C8: Income Statement | D8: Gross Profit | E8: Gross Profit Margin | F8: If not shown, calculate Revenue minus Cost of Sales.
A9: Net Profit After Tax | B9: What remains after all expenses and tax. | C9: Income Statement | D9: Profit for the Year; Net Profit; Total Comprehensive Income | E9: Net Margin, ROA, ROE | F9: Losses must be recorded calmly, not exaggerated.
A10: Operating Profit / EBIT | B10: Profit before interest and tax. | C10: Income Statement | D10: Operating Profit; EBIT; Profit before finance costs | E10: Interest Cover | F10: If absent, record that Interest Cover cannot be used.
A11: Interest Expense | B11: Cost of borrowing. | C11: Income Statement / Notes | D11: Finance Cost; Interest Expense; Bank Interest | E11: Interest Cover | F11: If zero or absent, do not force the ratio.
A12: Current Assets | B12: Assets expected to turn into cash within one year. | C12: Balance Sheet | D12: Current Assets | E12: Current Ratio, Quick Ratio, Working Capital | F12: Read what is inside: cash, receivables, stock, WIP, related-party balances.
A13: Cash at Bank | B13: Actual cash in bank or hand. | C13: Balance Sheet | D13: Cash at Bank; Bank; Cash and Cash Equivalents | E13: Working Capital quality | F13: Cash is stronger than receivables or related-party loans.
A14: Trade Receivables | B14: Money customers owe the company. | C14: Balance Sheet | D14: Trade Receivables; Accounts Receivable; Debtors | E14: Receivables Turnover | F14: Old receivables can behave like cash pressure.
A15: Inventory / Stock | B15: Items held for use or sale. | C15: Balance Sheet | D15: Inventory; Stock; Materials | E15: Quick Ratio | F15: Inventory is removed for Quick Ratio because it may not sell quickly.
A16: Work in Progress | B16: Work started but not fully billed or collected. | C16: Balance Sheet | D16: Work in Progress; Contract WIP | E16: Current Asset quality | F16: May depend on certification and payment timing.
... A21: Operating Cash Flow | B21: Cash from normal business activity. | C21: Cash Flow Statement | D21: Net cash from operating activities | E21: Cash-flow sense check | F21: Profit is not cash; check whether cash actually came in.

Sheet SECTOR GUIDE
A1: SECTOR GUIDE — HOW TO READ RATIOS BY TYPE OF BUSINESS
A2: Use as a screening lens only. Do not compare a contractor, supermarket, quarry, bank and consultancy as if they are the same kind of business.
A5: CORE SCREENING BANDS — START HERE, THEN ADJUST BY SECTOR
A6: Ratio | B6: Plain question | C6: Strong | D6: Adequate | E6: Caution | F6: High-risk | G6: Main caution | H6: Sheet source
A7: Current Ratio | B7: Can short-term assets cover short-term bills? | C7: 1.50+ | D7: 1.20–1.49 | E7: 1.00–1.19 | F7: Below 1.00 | G7: Read what is inside current assets. | H7: Balance Sheet
A8: Quick Ratio | B8: Can bills be paid without relying on stock? | C8: 1.00+ | D8: 0.80–0.99 | E8: 0.60–0.79 | F8: Below 0.60 | G8: Cash is stronger than receivables. | H8: Balance Sheet
A9: Debt-to-Equity | B9: Is the company leaning too much on debt? | C9: ≤ 1.00 | D9: 1.01–1.50 | E9: 1.51–2.00 | F9: Above 2.00 | G9: Debt can be normal in asset-heavy sectors. | H9: Balance Sheet
A10: Interest Cover | B10: Can profit pay interest? | C10: 4.0+ | D10: 2.5–3.99 | E10: 1.5–2.49 | F10: Below 1.5 | G10: If interest is missing, record limitation. | H10: Income Statement
A11: Profit / Margin Trend | B11: Is the business earning for its sector? | C11: Positive and steady | D11: Positive but thin | E11: Falling or one weak year | F11: Losses, no clear fix | G11: Compare to sector, not a random company. | H11: Income Statement
A12: Working Capital | B12: Does it have room to carry the job? | C12: Positive, cash-backed | D12: Positive, some slow debtors | E12: Tight or debtor-heavy | F12: Negative or cash-starved | G12: Quality of assets matters. | H12: Balance Sheet
A14: SECTOR NOTES — SIMPLE COMMITTEE READING
A15: Sector | B15: What matters most | C15: Usually strong when | D15: Committee caution
A16: Agriculture, forestry and fishing | B16: Seasonal cash, debt service | C16: Liquidity survives more than one season. | D16: Use more than one year where possible.
A17: Mining and quarrying | B17: Debt service, equipment, cash generation | C17: Interest cover is strong and cash flow is steady. | D17: High assets and lower turnover can be normal.
A18: Manufacturing | B18: Margins, stock, working capital | C18: Margins positive and working capital steady. | D18: Read stock, receivables and capacity together.
A19: Electricity, gas and air conditioning | B19: Stable cash flow, debt service | C19: Debt is supported by predictable cash. | D19: Capital-heavy sector; ordinary liquidity bands need care.
A20: Water, sewerage, waste and remediation | B20: Contract base, cash flow | C20: Recurring work supports debt and operations. | D20: Contract quality may matter more than one ratio.
A21: Construction | B21: Working capital, receivables, quick liquidity | C21: Can fund materials, labour and subcontractors before payment. | D21: Profit on paper does not pay suppliers next week.
A22: Wholesale and retail trade | B22: Stock turn, thin margins, cash | C22: Stock moves, cash cycles quickly, debt manageable. | D22: Thin margins can be normal; dead stock is the danger.
A23: Transportation and storage | B23: Fleet use, fuel, maintenance, debt | C23: Debt service is covered by real operations. | D23: Fuel and maintenance can squeeze cash quickly.
A24: Accommodation and food service | B24: Cash sales, rent/lease, operating cash | C24: Cash moves regularly and debt/rent is manageable. | D24: One bad period is not enough; repeated cash weakness matters.
A25: Information and communication | B25: Quick liquidity, receivables, recurring income | C25: Low debt and strong quick assets. | D25: Check unbilled work and slow receivables.
A26: Financial and insurance activities | B26: Regulatory capital and good standing | C26: Regulatory requirements are met. | D26: Ordinary current/quick ratios are not the main test.
... A36: Extraterritorial organizations | B36: Legal status, funding certainty | C36: Authority and funding are clear. | D36: Ratios are secondary to institutional status.

Sheet SOURCE REGISTER
A1: SOURCE REGISTER — BASIS, LIMITS AND CONTROL NOTES
A2: This workbook supports the Committee. It does not replace approved criteria, legal advice, audit assurance, or Committee judgement.
A5: Area | B5: Basis / source | C5: How it is used | D5: Committee control
A6: Financial statements | B6: Submitted bidder financial statements | C6: Source of all entered figures. | D6: Record statement name, year and line item.
A7: Ratio formulas | B7: Financial Calculations Guide prepared for committee support | C7: Core ratios and formula logic. | D7: Formula used must match the working paper.
A8: Prequalification framework | B8: Approved prequalification criteria and OPR framework | C8: Keeps financial evaluation inside the exercise rules. | D8: Do not introduce new pass/fail tests unless criteria allow.
A9: Sector screening | B9: Sector-adjusted screening guide | C9: Helps read ratios by business type. | D9: Use as screening guidance, not statutory threshold.
A10: Rating language | B10: Committee wording discipline | C10: Avoids overclaiming and reckless wording. | D10: Use 'indicates', 'raises concern', 'requires clarification'.
A11: Workbook limitation | B11: Formula outputs depend on user-entered figures | C11: If inputs are wrong, results are wrong. | D11: Second member checks figures before interpretation.
A12: Interest Cover | B12: Additional screening ratio where interest exists | C12: Tests whether operating profit can pay interest. | D12: If interest is blank/zero/not meaningful, record limitation.
A14: CHAIRPERSON RELEASE CHECK
A15: 1 | B15: All bidders entered using the same financial year rule or differences recorded.
A16: 2 | B16: Each figure traced to statement, year and line item.
A17: 3 | B17: Yellow input cells only used by committee members.
A18: 4 | B18: RATIO RESULTS reviewed for blank or Not entered items.
A19: 5 | B19: DASHBOARD used only after source checking.
A20: 6 | B20: FINDING BUILDER wording checked against approved criteria before use.
A21: 7 | B21: Workbook retained with working papers for audit trail.

Sheet VALIDATION LISTS
A1: INTERNAL DROPDOWN LISTS — DO NOT EDIT
A2: Sector List | C2: Statement Status | E2: Yes / No / NA
A3: Agriculture, forestry and fishing | C3: Audited | E3: Yes
A4: Mining and quarrying | C4: Unaudited | E4: No
A5: Manufacturing | C5: Management Accounts | E5: Not applicable
A6: Electricity, gas, steam and air conditioning | C6: Banker Letter Only
A7: Water supply, sewerage, waste and remediation | C7: Not Provided
A8: Construction | C8: Other
A9: Wholesale and retail trade
A10: Transportation and storage
A11: Accommodation and food service
A12: Information and communication
A13: Financial and insurance activities
A14: Real estate activities
A15: Professional, scientific and technical activities
A16: Administrative and support service activities
A17: Public administration and defence
A18: Education
A19: Human health and social work
A20: Arts, entertainment and recreation
... A23: Activities of extraterritorial organizations and bodies
