Workbook
Name ProcurementMethodList: LISTS!$D$5:$D$24
Name TenderTypeList: LISTS!$C$5:$C$24

Sheet START HERE
A1: MINISTRY OF DEFENCE — TENDER EVALUATION WORKBOOK
A2: Committee working tool for mandatory responsiveness, technical scoring, financial capacity, commercial evaluation and report drafting.
A4: Use this workbook in order. Yellow cells are for input. Grey and blue cells are formulas or guidance. Do not treat the workbook as the decision-maker; it is an audit-traceable working aid.
A6: STEP | B6: SHEET | C6: WHAT TO DO | D6: PLAIN ENGLISH | F6: CHAIRPERSON RULE: Agree the criteria and weights before scoring any bidder. Do not add, remove or change criteria after tenders are opened. Every finding must be traceable to a source document and a written reason.
A7: 1 | B7: TENDER SETUP | C7: Enter tender title, method, line of business, estimated value and pass marks. | D7: Set the job before scoring anyone.
A8: 2 | B8: BIDDER REGISTER | C8: Enter each bidder once. | D8: One bidder per row.
A9: 3 | B9: CRITERIA BUILDER | C9: Confirm weights before evaluation begins. | D9: No new criteria after tenders are opened.
A10: 4 | B10: RESPONSIVENESS | C10: Mark mandatory items Pass / Fail / N/A. | D10: Mandatory means pass/fail, not points.
A11: 5 | B11: TECHNICAL SCORING | C11: Score only responsive bidders against stated criteria. | D11: Score what the tender said you would score.
A12: 6 | B12: FINANCIAL CAPACITY | C12: Enter financial statement figures; ratios and rating calculate automatically. | D12: Use financial statements. Do not guess figures. | F12: SAFE METHOD: Open the source document. Find the line item. Enter the figure exactly as shown. Let the workbook calculate. If a figure cannot be traced, do not use it.
A13: 7 | B13: COMMERCIAL EVAL | C13: Enter evaluated price, VAT and payment terms. | D13: Price is scored after eligibility checks.
A14: 8 | B14: DASHBOARD | C14: Review rankings, exclusions and recommendation flag. | D14: Quick view, not the final report.
A15: 9 | B15: REPORT BUILDER | C15: Copy and clean the report text for the final evaluation report. | D15: This builds the skeleton report.
A17: Plain explanation for non-accounting users
A18: Income Statement | B18: Did the company make or lose money for the year? | C18: Use it for Revenue, Gross Profit and Net Profit.
A19: Balance Sheet | B19: What does the company own and owe on one date? | C19: Use it for Cash, Assets, Liabilities, Equity, Receivables and Working Capital.
A20: Cash Flow Statement | B20: Did real money actually move? | C20: Use it to check whether profit turned into cash.
A21: Committee test | B21: Can the bidder do the job, carry the cost, and survive the contract? | C21: Use the evidence; no guessing, no drama.
A22: Workbook rule | B22: Every figure must have a home: statement, year, line item. | C22: If it cannot be traced, do not use it.

Sheet TENDER SETUP
A1: TENDER SETUP
A2: Enter the tender details once. These fields feed the report builder and dashboard.
A4: Field | B4: Input | C4: Simple instruction | E4: FIRST PRINCIPLE: Decide the criteria before the tender goes out. The evaluation report must follow the criteria already stated in the tender documents.
A5: Ministry / Public Body | B5: Ministry of Defence | C5: Enter the full Ministry/Public Body name.
A6: Division / Unit | C6: Example: Procurement Unit / TTDF / Air Guard.
A7: Tender Title | C7: Use the exact title from the RFP/ITT.
A8: Procurement Reference | C8: Enter the file or RFP/ITT reference.
A9: Procurement Method | B9: Open Tender | C9: Example: Open Tender, Selective Tender, RFP, RFQ.
A10: Tender Type | B10: Works / Refurbishment / Construction | C10: Select the closest tender type. | E10: TRINIDAD AND TOBAGO REALITY CHECK: A low price is not value for money if the bidder cannot deliver, support the item, pay workers/suppliers, or survive delayed payment cycles.
A11: Line of Business | C11: Use the OPR/depository line of business if known.
A12: Estimated Value (TTD) | C12: Enter estimate if available.
A13: Closing Date | C13: Use the official closing date.
A14: Evaluation Report Date | C14: Enter the date the evaluation report is prepared.
A15: Overall Pass Score | B15: 70 | C15: Usually 70 unless the tender states otherwise.
A16: Minimum Technical Score | B16: 42 | C16: Default 42 (60% of 70 scored technical points). Adjust to match RFP if different.
A17: Price Scoring Formula | B17: Lowest evaluated responsive price / bidder price × price points | C17: Default formula used in Commercial Evaluation.
A18: Committee Chairperson | C18: Enter chairperson name.
A19: Prepared By | B19: Lt. Christopher Joseph, MBA-Finance, CMA | C19: Enter preparer/facilitator if applicable.

Sheet BIDDER REGISTER
A1: BIDDER REGISTER
A2: Enter each bidder once. All scoring sheets pull the names from here.
A6: No. | B6: Bidder Name | C6: Company Type | D6: Line of Business | E6: Value Category | F6: Years Experience | G6: Submitted On Time? | H6: Notes
A7: 1
A8: 2
A9: 3
A10: 4
A11: 5
A12: 6
A13: 7
A14: 8
A15: 9
A16: 10
A17: 11
A18: 12
... A26: 20

Sheet CRITERIA BUILDER
A1: CRITERIA BUILDER
A2: Confirm the evaluation structure before scoring. Adjust weights only if this matches the issued tender.
A6: Code | B6: Evaluation Area | C6: Max Points | D6: Type | E6: Minimum / Gate | F6: What it tests | G6: Committee note
A7: G1 | B7: Mandatory Responsiveness | C7: 0 | D7: Gate | E7: Pass/Fail | F7: Was the submission eligible to be evaluated? | G7: Do not score mandatory items.
A8: G2 | B8: Minimum Technical Requirement | C8: 0 | D8: Gate | E8: Pass/Fail or threshold | F8: Does the offer meet the minimum operational requirement? | G8: A cheap non-compliant bid is not value.
A9: C1 | B9: Organizational Capability / Experience | C9: 10 | D9: Manual Score | F9: Can the bidder organize and manage the job?
A10: C2 | B10: Technical Compliance / Solution | C10: 30 | D10: Manual Score | F10: Does the offer meet the technical need?
A11: C3 | B11: Methodology / Implementation Plan | C11: 15 | D11: Manual Score | F11: Does the bidder understand how to execute?
A12: C4 | B12: Warranty / Support / Training | C12: 10 | D12: Manual Score | F12: Will support exist after award?
A13: C5 | B13: Delivery / Lead Time | C13: 5 | D13: Manual Score | F13: Can the bidder deliver within the required time?
A14: C6 | B14: Financial Capacity | C14: 10 | D14: Calculated Score | F14: Can the bidder carry the contract financially? | G14: Feeds from Financial Capacity sheet.
A15: C7 | B15: Price / Commercial Offer | C15: 15 | D15: Calculated Score | F15: Is the evaluated price competitive? | G15: Feeds from Commercial Evaluation sheet.
A16: C8 | B16: Payment Terms | C16: 5 | D16: Manual Score | F16: Are payment terms acceptable to Government?
A18: Total Scored Points | B18: =SUM(C9:C16) -> 100
A19: Status | B19: =IF(B18=100,"READY: total points equal 100","CHECK: scored points must equal 100") -> READY: total points equal 100
A20: Rule | B20: Do not change criteria after tenders are opened.

Sheet RESPONSIVENESS
A1: MANDATORY RESPONSIVENESS
A2: Mark mandatory items as Pass, Fail or N/A. A failed mandatory item should be recorded clearly.
A6: Bidder | B6: Deadline | C6: Signed / Authorized | D6: Correct Envelope / Format | E6: Statutory Docs | F6: OPR / Line of Business | G6: Bid Validity | H6: Site Visit / NDA | I6: Required Forms | J6: Overall | K6: Reason / Note
A7: =IF(LEN('BIDDER REGISTER'!B7)=0,"",'BIDDER REGISTER'!B7) | J7: =IF(LEN(A7)=0,"",IF(COUNTIF(B7:I7,"Fail")>0,"Non-responsive",IF(COUNTBLANK(B7:I7)>0,"Incomplete","Responsive")))
A8: =IF(LEN('BIDDER REGISTER'!B8)=0,"",'BIDDER REGISTER'!B8) | J8: =IF(LEN(A8)=0,"",IF(COUNTIF(B8:I8,"Fail")>0,"Non-responsive",IF(COUNTBLANK(B8:I8)>0,"Incomplete","Responsive")))
A9: =IF(LEN('BIDDER REGISTER'!B9)=0,"",'BIDDER REGISTER'!B9) | J9: =IF(LEN(A9)=0,"",IF(COUNTIF(B9:I9,"Fail")>0,"Non-responsive",IF(COUNTBLANK(B9:I9)>0,"Incomplete","Responsive")))
A10: =IF(LEN('BIDDER REGISTER'!B10)=0,"",'BIDDER REGISTER'!B10) | J10: =IF(LEN(A10)=0,"",IF(COUNTIF(B10:I10,"Fail")>0,"Non-responsive",IF(COUNTBLANK(B10:I10)>0,"Incomplete","Responsive")))
A11: =IF(LEN('BIDDER REGISTER'!B11)=0,"",'BIDDER REGISTER'!B11) | J11: =IF(LEN(A11)=0,"",IF(COUNTIF(B11:I11,"Fail")>0,"Non-responsive",IF(COUNTBLANK(B11:I11)>0,"Incomplete","Responsive")))
A12: =IF(LEN('BIDDER REGISTER'!B12)=0,"",'BIDDER REGISTER'!B12) | J12: =IF(LEN(A12)=0,"",IF(COUNTIF(B12:I12,"Fail")>0,"Non-responsive",IF(COUNTBLANK(B12:I12)>0,"Incomplete","Responsive")))
A13: =IF(LEN('BIDDER REGISTER'!B13)=0,"",'BIDDER REGISTER'!B13) | J13: =IF(LEN(A13)=0,"",IF(COUNTIF(B13:I13,"Fail")>0,"Non-responsive",IF(COUNTBLANK(B13:I13)>0,"Incomplete","Responsive")))
A14: =IF(LEN('BIDDER REGISTER'!B14)=0,"",'BIDDER REGISTER'!B14) | J14: =IF(LEN(A14)=0,"",IF(COUNTIF(B14:I14,"Fail")>0,"Non-responsive",IF(COUNTBLANK(B14:I14)>0,"Incomplete","Responsive")))
A15: =IF(LEN('BIDDER REGISTER'!B15)=0,"",'BIDDER REGISTER'!B15) | J15: =IF(LEN(A15)=0,"",IF(COUNTIF(B15:I15,"Fail")>0,"Non-responsive",IF(COUNTBLANK(B15:I15)>0,"Incomplete","Responsive")))
A16: =IF(LEN('BIDDER REGISTER'!B16)=0,"",'BIDDER REGISTER'!B16) | J16: =IF(LEN(A16)=0,"",IF(COUNTIF(B16:I16,"Fail")>0,"Non-responsive",IF(COUNTBLANK(B16:I16)>0,"Incomplete","Responsive")))
A17: =IF(LEN('BIDDER REGISTER'!B17)=0,"",'BIDDER REGISTER'!B17) | J17: =IF(LEN(A17)=0,"",IF(COUNTIF(B17:I17,"Fail")>0,"Non-responsive",IF(COUNTBLANK(B17:I17)>0,"Incomplete","Responsive")))
A18: =IF(LEN('BIDDER REGISTER'!B18)=0,"",'BIDDER REGISTER'!B18) | J18: =IF(LEN(A18)=0,"",IF(COUNTIF(B18:I18,"Fail")>0,"Non-responsive",IF(COUNTBLANK(B18:I18)>0,"Incomplete","Responsive")))
... A26: =IF(LEN('BIDDER REGISTER'!B26)=0,"",'BIDDER REGISTER'!B26) | J26: =IF(LEN(A26)=0,"",IF(COUNTIF(B26:I26,"Fail")>0,"Non-responsive",IF(COUNTBLANK(B26:I26)>0,"Incomplete","Responsive")))

Sheet TECHNICAL SCORING
A1: TECHNICAL AND CAPABILITY SCORING
A2: Enter scores only within the stated maximum points. Use comments for any score that may be challenged.
A5: Max Points | C5: ='CRITERIA BUILDER'!C9 -> 10 | D5: ='CRITERIA BUILDER'!C10 -> 30 | E5: ='CRITERIA BUILDER'!C11 -> 15 | F5: ='CRITERIA BUILDER'!C12 -> 10 | G5: ='CRITERIA BUILDER'!C13 -> 5 | H5: ='CRITERIA BUILDER'!C16 -> 5
A6: Bidder | B6: Responsive? | C6: Org / Experience | D6: Technical Compliance | E6: Methodology / Plan | F6: Support / Training | G6: Delivery | H6: Payment Terms | I6: Manual Score | J6: Min Tech Pass? | K6: Evaluator Note
A7: =IF(LEN('BIDDER REGISTER'!B7)=0,"",'BIDDER REGISTER'!B7) | B7: =IF(LEN(A7)=0,"",RESPONSIVENESS!J7) | I7: =IF(LEN(A7)=0,"",IF(C7="",0,MIN(C7,C$5))+IF(D7="",0,MIN(D7,D$5))+IF(E7="",0,MIN(E7,E$5))+IF(F7="",0,MIN(F7,F$5))+IF(G7="",0,MIN(G7,G$5))+IF(H7="",0,MIN(H7,H$5))) | J7: =IF(LEN(A7)=0,"",IF(I7>='TENDER SETUP'!$B$16,"Yes","No"))
A8: =IF(LEN('BIDDER REGISTER'!B8)=0,"",'BIDDER REGISTER'!B8) | B8: =IF(LEN(A8)=0,"",RESPONSIVENESS!J8) | I8: =IF(LEN(A8)=0,"",IF(C8="",0,MIN(C8,C$5))+IF(D8="",0,MIN(D8,D$5))+IF(E8="",0,MIN(E8,E$5))+IF(F8="",0,MIN(F8,F$5))+IF(G8="",0,MIN(G8,G$5))+IF(H8="",0,MIN(H8,H$5))) | J8: =IF(LEN(A8)=0,"",IF(I8>='TENDER SETUP'!$B$16,"Yes","No"))
A9: =IF(LEN('BIDDER REGISTER'!B9)=0,"",'BIDDER REGISTER'!B9) | B9: =IF(LEN(A9)=0,"",RESPONSIVENESS!J9) | I9: =IF(LEN(A9)=0,"",IF(C9="",0,MIN(C9,C$5))+IF(D9="",0,MIN(D9,D$5))+IF(E9="",0,MIN(E9,E$5))+IF(F9="",0,MIN(F9,F$5))+IF(G9="",0,MIN(G9,G$5))+IF(H9="",0,MIN(H9,H$5))) | J9: =IF(LEN(A9)=0,"",IF(I9>='TENDER SETUP'!$B$16,"Yes","No"))
A10: =IF(LEN('BIDDER REGISTER'!B10)=0,"",'BIDDER REGISTER'!B10) | B10: =IF(LEN(A10)=0,"",RESPONSIVENESS!J10) | I10: =IF(LEN(A10)=0,"",IF(C10="",0,MIN(C10,C$5))+IF(D10="",0,MIN(D10,D$5))+IF(E10="",0,MIN(E10,E$5))+IF(F10="",0,MIN(F10,F$5))+IF(G10="",0,MIN(G10,G$5))+IF(H10="",0,MIN(H10,H$5))) | J10: =IF(LEN(A10)=0,"",IF(I10>='TENDER SETUP'!$B$16,"Yes","No"))
A11: =IF(LEN('BIDDER REGISTER'!B11)=0,"",'BIDDER REGISTER'!B11) | B11: =IF(LEN(A11)=0,"",RESPONSIVENESS!J11) | I11: =IF(LEN(A11)=0,"",IF(C11="",0,MIN(C11,C$5))+IF(D11="",0,MIN(D11,D$5))+IF(E11="",0,MIN(E11,E$5))+IF(F11="",0,MIN(F11,F$5))+IF(G11="",0,MIN(G11,G$5))+IF(H11="",0,MIN(H11,H$5))) | J11: =IF(LEN(A11)=0,"",IF(I11>='TENDER SETUP'!$B$16,"Yes","No"))
A12: =IF(LEN('BIDDER REGISTER'!B12)=0,"",'BIDDER REGISTER'!B12) | B12: =IF(LEN(A12)=0,"",RESPONSIVENESS!J12) | I12: =IF(LEN(A12)=0,"",IF(C12="",0,MIN(C12,C$5))+IF(D12="",0,MIN(D12,D$5))+IF(E12="",0,MIN(E12,E$5))+IF(F12="",0,MIN(F12,F$5))+IF(G12="",0,MIN(G12,G$5))+IF(H12="",0,MIN(H12,H$5))) | J12: =IF(LEN(A12)=0,"",IF(I12>='TENDER SETUP'!$B$16,"Yes","No"))
A13: =IF(LEN('BIDDER REGISTER'!B13)=0,"",'BIDDER REGISTER'!B13) | B13: =IF(LEN(A13)=0,"",RESPONSIVENESS!J13) | I13: =IF(LEN(A13)=0,"",IF(C13="",0,MIN(C13,C$5))+IF(D13="",0,MIN(D13,D$5))+IF(E13="",0,MIN(E13,E$5))+IF(F13="",0,MIN(F13,F$5))+IF(G13="",0,MIN(G13,G$5))+IF(H13="",0,MIN(H13,H$5))) | J13: =IF(LEN(A13)=0,"",IF(I13>='TENDER SETUP'!$B$16,"Yes","No"))
A14: =IF(LEN('BIDDER REGISTER'!B14)=0,"",'BIDDER REGISTER'!B14) | B14: =IF(LEN(A14)=0,"",RESPONSIVENESS!J14) | I14: =IF(LEN(A14)=0,"",IF(C14="",0,MIN(C14,C$5))+IF(D14="",0,MIN(D14,D$5))+IF(E14="",0,MIN(E14,E$5))+IF(F14="",0,MIN(F14,F$5))+IF(G14="",0,MIN(G14,G$5))+IF(H14="",0,MIN(H14,H$5))) | J14: =IF(LEN(A14)=0,"",IF(I14>='TENDER SETUP'!$B$16,"Yes","No"))
A15: =IF(LEN('BIDDER REGISTER'!B15)=0,"",'BIDDER REGISTER'!B15) | B15: =IF(LEN(A15)=0,"",RESPONSIVENESS!J15) | I15: =IF(LEN(A15)=0,"",IF(C15="",0,MIN(C15,C$5))+IF(D15="",0,MIN(D15,D$5))+IF(E15="",0,MIN(E15,E$5))+IF(F15="",0,MIN(F15,F$5))+IF(G15="",0,MIN(G15,G$5))+IF(H15="",0,MIN(H15,H$5))) | J15: =IF(LEN(A15)=0,"",IF(I15>='TENDER SETUP'!$B$16,"Yes","No"))
A16: =IF(LEN('BIDDER REGISTER'!B16)=0,"",'BIDDER REGISTER'!B16) | B16: =IF(LEN(A16)=0,"",RESPONSIVENESS!J16) | I16: =IF(LEN(A16)=0,"",IF(C16="",0,MIN(C16,C$5))+IF(D16="",0,MIN(D16,D$5))+IF(E16="",0,MIN(E16,E$5))+IF(F16="",0,MIN(F16,F$5))+IF(G16="",0,MIN(G16,G$5))+IF(H16="",0,MIN(H16,H$5))) | J16: =IF(LEN(A16)=0,"",IF(I16>='TENDER SETUP'!$B$16,"Yes","No"))
A17: =IF(LEN('BIDDER REGISTER'!B17)=0,"",'BIDDER REGISTER'!B17) | B17: =IF(LEN(A17)=0,"",RESPONSIVENESS!J17) | I17: =IF(LEN(A17)=0,"",IF(C17="",0,MIN(C17,C$5))+IF(D17="",0,MIN(D17,D$5))+IF(E17="",0,MIN(E17,E$5))+IF(F17="",0,MIN(F17,F$5))+IF(G17="",0,MIN(G17,G$5))+IF(H17="",0,MIN(H17,H$5))) | J17: =IF(LEN(A17)=0,"",IF(I17>='TENDER SETUP'!$B$16,"Yes","No"))
A18: =IF(LEN('BIDDER REGISTER'!B18)=0,"",'BIDDER REGISTER'!B18) | B18: =IF(LEN(A18)=0,"",RESPONSIVENESS!J18) | I18: =IF(LEN(A18)=0,"",IF(C18="",0,MIN(C18,C$5))+IF(D18="",0,MIN(D18,D$5))+IF(E18="",0,MIN(E18,E$5))+IF(F18="",0,MIN(F18,F$5))+IF(G18="",0,MIN(G18,G$5))+IF(H18="",0,MIN(H18,H$5))) | J18: =IF(LEN(A18)=0,"",IF(I18>='TENDER SETUP'!$B$16,"Yes","No"))
... A26: =IF(LEN('BIDDER REGISTER'!B26)=0,"",'BIDDER REGISTER'!B26) | B26: =IF(LEN(A26)=0,"",RESPONSIVENESS!J26) | I26: =IF(LEN(A26)=0,"",IF(C26="",0,MIN(C26,C$5))+IF(D26="",0,MIN(D26,D$5))+IF(E26="",0,MIN(E26,E$5))+IF(F26="",0,MIN(F26,F$5))+IF(G26="",0,MIN(G26,G$5))+IF(H26="",0,MIN(H26,H$5))) | J26: =IF(LEN(A26)=0,"",IF(I26>='TENDER SETUP'!$B$16,"Yes","No"))

Sheet FINANCIAL CAPACITY
A1: FINANCIAL CAPACITY
A2: Enter financial statement figures. Ratios, screening rating and committee wording calculate automatically.
A6: Bidder | B6: FY | C6: Sector | D6: Revenue | E6: Gross Profit | F6: Net Profit | G6: Current Assets | H6: Inventory | I6: Current Liabilities | J6: Total Assets | K6: Total Liabilities | L6: Total Equity | M6: Trade Receivables CY | N6: Trade Receivables PY | O6: Operating Profit | P6: Interest Expense | Q6: Gross Margin | R6: Net Margin | S6: Current Ratio | T6: Quick Ratio | U6: Debt/Equity | V6: ROA | W6: ROE | X6: Receivables Turnover | Y6: Asset Turnover | Z6: Working Capital | AA6: Interest Cover | AB6: Screening Rating | AC6: Financial Score | AD6: Committee Note
A7: =IF(LEN('BIDDER REGISTER'!B7)=0,"",'BIDDER REGISTER'!B7) | Q7: =IF(OR(LEN(A7)=0,D7="",E7=""),"",IFERROR(E7/D7,"")) | R7: =IF(OR(LEN(A7)=0,D7="",F7=""),"",IFERROR(F7/D7,"")) | S7: =IF(OR(LEN(A7)=0,G7="",I7=""),"",IFERROR(G7/I7,"")) | T7: =IF(OR(LEN(A7)=0,G7="",I7=""),"",IFERROR((G7-IF(H7="",0,H7))/I7,"")) | U7: =IF(OR(LEN(A7)=0,K7="",L7="",L7<=0),"",IFERROR(K7/L7,"")) | V7: =IF(OR(LEN(A7)=0,F7="",J7=""),"",IFERROR(F7/J7,"")) | W7: =IF(OR(LEN(A7)=0,F7="",L7="",L7<=0),"",IFERROR(F7/L7,"")) | X7: =IF(OR(LEN(A7)=0,D7="",M7=""),"",IF(N7<>"",IFERROR(D7/AVERAGE(M7,N7),""),IFERROR(D7/M7,""))) | Y7: =IF(OR(LEN(A7)=0,D7="",J7=""),"",IFERROR(D7/J7,"")) | Z7: =IF(OR(LEN(A7)=0,G7="",I7=""),"",G7-I7) | AA7: =IF(OR(LEN(A7)=0,O7="",P7="",P7<=0),"",IFERROR(O7/P7,"")) | AB7: =IF(LEN(A7)=0,"",IF(AND(ISNUMBER(L7),L7<=0),"High Risk",IF(COUNT(D7:L7)=0,"No Data",IF(COUNTBLANK(D7:L7)>0,"Incomplete",CHOOSE(1+IF(AND(ISNUMBER(S7),S7>=1.2),1,0)+IF(AND(ISNUMBER(T7),T7>=0.8),1,0)+IF(AND(ISNUMBER(U7),U7>0,U7<=1.5),1,0)+IF(AND(ISNUMBER(R7),R7>=0),1,0)+IF(AND(ISNUMBER(Z7),Z7>0),1,0),"High Risk","High Risk","Stretched","Adequate with Caution","Adequate","Strong"))))) | AC7: =IF(LEN(A7)=0,"",IF(AB7="Strong",'CRITERIA BUILDER'!$C$14,IF(AB7="Adequate",'CRITERIA BUILDER'!$C$14*0.8,IF(AB7="Adequate with Caution",'CRITERIA BUILDER'!$C$14*0.6,IF(AB7="Stretched",'CRITERIA BUILDER'!$C$14*0.3,0))))) | AD7: =IF(LEN(A7)=0,"",IF(AND(ISNUMBER(L7),L7<=0),A7&" shows negative equity. Screened as High Risk. The Committee should request clarification on accumulated losses, capital position, and any restructuring or capital injection before relying on this bidder.",A7&" is screened as "&AB7&" on financial capacity. The Committee should record the statement year, line items used, and any limitation or clarification required."))
A8: =IF(LEN('BIDDER REGISTER'!B8)=0,"",'BIDDER REGISTER'!B8) | Q8: =IF(OR(LEN(A8)=0,D8="",E8=""),"",IFERROR(E8/D8,"")) | R8: =IF(OR(LEN(A8)=0,D8="",F8=""),"",IFERROR(F8/D8,"")) | S8: =IF(OR(LEN(A8)=0,G8="",I8=""),"",IFERROR(G8/I8,"")) | T8: =IF(OR(LEN(A8)=0,G8="",I8=""),"",IFERROR((G8-IF(H8="",0,H8))/I8,"")) | U8: =IF(OR(LEN(A8)=0,K8="",L8="",L8<=0),"",IFERROR(K8/L8,"")) | V8: =IF(OR(LEN(A8)=0,F8="",J8=""),"",IFERROR(F8/J8,"")) | W8: =IF(OR(LEN(A8)=0,F8="",L8="",L8<=0),"",IFERROR(F8/L8,"")) | X8: =IF(OR(LEN(A8)=0,D8="",M8=""),"",IF(N8<>"",IFERROR(D8/AVERAGE(M8,N8),""),IFERROR(D8/M8,""))) | Y8: =IF(OR(LEN(A8)=0,D8="",J8=""),"",IFERROR(D8/J8,"")) | Z8: =IF(OR(LEN(A8)=0,G8="",I8=""),"",G8-I8) | AA8: =IF(OR(LEN(A8)=0,O8="",P8="",P8<=0),"",IFERROR(O8/P8,"")) | AB8: =IF(LEN(A8)=0,"",IF(AND(ISNUMBER(L8),L8<=0),"High Risk",IF(COUNT(D8:L8)=0,"No Data",IF(COUNTBLANK(D8:L8)>0,"Incomplete",CHOOSE(1+IF(AND(ISNUMBER(S8),S8>=1.2),1,0)+IF(AND(ISNUMBER(T8),T8>=0.8),1,0)+IF(AND(ISNUMBER(U8),U8>0,U8<=1.5),1,0)+IF(AND(ISNUMBER(R8),R8>=0),1,0)+IF(AND(ISNUMBER(Z8),Z8>0),1,0),"High Risk","High Risk","Stretched","Adequate with Caution","Adequate","Strong"))))) | AC8: =IF(LEN(A8)=0,"",IF(AB8="Strong",'CRITERIA BUILDER'!$C$14,IF(AB8="Adequate",'CRITERIA BUILDER'!$C$14*0.8,IF(AB8="Adequate with Caution",'CRITERIA BUILDER'!$C$14*0.6,IF(AB8="Stretched",'CRITERIA BUILDER'!$C$14*0.3,0))))) | AD8: =IF(LEN(A8)=0,"",IF(AND(ISNUMBER(L8),L8<=0),A8&" shows negative equity. Screened as High Risk. The Committee should request clarification on accumulated losses, capital position, and any restructuring or capital injection before relying on this bidder.",A8&" is screened as "&AB8&" on financial capacity. The Committee should record the statement year, line items used, and any limitation or clarification required."))
A9: =IF(LEN('BIDDER REGISTER'!B9)=0,"",'BIDDER REGISTER'!B9) | Q9: =IF(OR(LEN(A9)=0,D9="",E9=""),"",IFERROR(E9/D9,"")) | R9: =IF(OR(LEN(A9)=0,D9="",F9=""),"",IFERROR(F9/D9,"")) | S9: =IF(OR(LEN(A9)=0,G9="",I9=""),"",IFERROR(G9/I9,"")) | T9: =IF(OR(LEN(A9)=0,G9="",I9=""),"",IFERROR((G9-IF(H9="",0,H9))/I9,"")) | U9: =IF(OR(LEN(A9)=0,K9="",L9="",L9<=0),"",IFERROR(K9/L9,"")) | V9: =IF(OR(LEN(A9)=0,F9="",J9=""),"",IFERROR(F9/J9,"")) | W9: =IF(OR(LEN(A9)=0,F9="",L9="",L9<=0),"",IFERROR(F9/L9,"")) | X9: =IF(OR(LEN(A9)=0,D9="",M9=""),"",IF(N9<>"",IFERROR(D9/AVERAGE(M9,N9),""),IFERROR(D9/M9,""))) | Y9: =IF(OR(LEN(A9)=0,D9="",J9=""),"",IFERROR(D9/J9,"")) | Z9: =IF(OR(LEN(A9)=0,G9="",I9=""),"",G9-I9) | AA9: =IF(OR(LEN(A9)=0,O9="",P9="",P9<=0),"",IFERROR(O9/P9,"")) | AB9: =IF(LEN(A9)=0,"",IF(AND(ISNUMBER(L9),L9<=0),"High Risk",IF(COUNT(D9:L9)=0,"No Data",IF(COUNTBLANK(D9:L9)>0,"Incomplete",CHOOSE(1+IF(AND(ISNUMBER(S9),S9>=1.2),1,0)+IF(AND(ISNUMBER(T9),T9>=0.8),1,0)+IF(AND(ISNUMBER(U9),U9>0,U9<=1.5),1,0)+IF(AND(ISNUMBER(R9),R9>=0),1,0)+IF(AND(ISNUMBER(Z9),Z9>0),1,0),"High Risk","High Risk","Stretched","Adequate with Caution","Adequate","Strong"))))) | AC9: =IF(LEN(A9)=0,"",IF(AB9="Strong",'CRITERIA BUILDER'!$C$14,IF(AB9="Adequate",'CRITERIA BUILDER'!$C$14*0.8,IF(AB9="Adequate with Caution",'CRITERIA BUILDER'!$C$14*0.6,IF(AB9="Stretched",'CRITERIA BUILDER'!$C$14*0.3,0))))) | AD9: =IF(LEN(A9)=0,"",IF(AND(ISNUMBER(L9),L9<=0),A9&" shows negative equity. Screened as High Risk. The Committee should request clarification on accumulated losses, capital position, and any restructuring or capital injection before relying on this bidder.",A9&" is screened as "&AB9&" on financial capacity. The Committee should record the statement year, line items used, and any limitation or clarification required."))
A10: =IF(LEN('BIDDER REGISTER'!B10)=0,"",'BIDDER REGISTER'!B10) | Q10: =IF(OR(LEN(A10)=0,D10="",E10=""),"",IFERROR(E10/D10,"")) | R10: =IF(OR(LEN(A10)=0,D10="",F10=""),"",IFERROR(F10/D10,"")) | S10: =IF(OR(LEN(A10)=0,G10="",I10=""),"",IFERROR(G10/I10,"")) | T10: =IF(OR(LEN(A10)=0,G10="",I10=""),"",IFERROR((G10-IF(H10="",0,H10))/I10,"")) | U10: =IF(OR(LEN(A10)=0,K10="",L10="",L10<=0),"",IFERROR(K10/L10,"")) | V10: =IF(OR(LEN(A10)=0,F10="",J10=""),"",IFERROR(F10/J10,"")) | W10: =IF(OR(LEN(A10)=0,F10="",L10="",L10<=0),"",IFERROR(F10/L10,"")) | X10: =IF(OR(LEN(A10)=0,D10="",M10=""),"",IF(N10<>"",IFERROR(D10/AVERAGE(M10,N10),""),IFERROR(D10/M10,""))) | Y10: =IF(OR(LEN(A10)=0,D10="",J10=""),"",IFERROR(D10/J10,"")) | Z10: =IF(OR(LEN(A10)=0,G10="",I10=""),"",G10-I10) | AA10: =IF(OR(LEN(A10)=0,O10="",P10="",P10<=0),"",IFERROR(O10/P10,"")) | AB10: =IF(LEN(A10)=0,"",IF(AND(ISNUMBER(L10),L10<=0),"High Risk",IF(COUNT(D10:L10)=0,"No Data",IF(COUNTBLANK(D10:L10)>0,"Incomplete",CHOOSE(1+IF(AND(ISNUMBER(S10),S10>=1.2),1,0)+IF(AND(ISNUMBER(T10),T10>=0.8),1,0)+IF(AND(ISNUMBER(U10),U10>0,U10<=1.5),1,0)+IF(AND(ISNUMBER(R10),R10>=0),1,0)+IF(AND(ISNUMBER(Z10),Z10>0),1,0),"High Risk","High Risk","Stretched","Adequate with Caution","Adequate","Strong"))))) | AC10: =IF(LEN(A10)=0,"",IF(AB10="Strong",'CRITERIA BUILDER'!$C$14,IF(AB10="Adequate",'CRITERIA BUILDER'!$C$14*0.8,IF(AB10="Adequate with Caution",'CRITERIA BUILDER'!$C$14*0.6,IF(AB10="Stretched",'CRITERIA BUILDER'!$C$14*0.3,0))))) | AD10: =IF(LEN(A10)=0,"",IF(AND(ISNUMBER(L10),L10<=0),A10&" shows negative equity. Screened as High Risk. The Committee should request clarification on accumulated losses, capital position, and any restructuring or capital injection before relying on this bidder.",A10&" is screened as "&AB10&" on financial capacity. The Committee should record the statement year, line items used, and any limitation or clarification required."))
A11: =IF(LEN('BIDDER REGISTER'!B11)=0,"",'BIDDER REGISTER'!B11) | Q11: =IF(OR(LEN(A11)=0,D11="",E11=""),"",IFERROR(E11/D11,"")) | R11: =IF(OR(LEN(A11)=0,D11="",F11=""),"",IFERROR(F11/D11,"")) | S11: =IF(OR(LEN(A11)=0,G11="",I11=""),"",IFERROR(G11/I11,"")) | T11: =IF(OR(LEN(A11)=0,G11="",I11=""),"",IFERROR((G11-IF(H11="",0,H11))/I11,"")) | U11: =IF(OR(LEN(A11)=0,K11="",L11="",L11<=0),"",IFERROR(K11/L11,"")) | V11: =IF(OR(LEN(A11)=0,F11="",J11=""),"",IFERROR(F11/J11,"")) | W11: =IF(OR(LEN(A11)=0,F11="",L11="",L11<=0),"",IFERROR(F11/L11,"")) | X11: =IF(OR(LEN(A11)=0,D11="",M11=""),"",IF(N11<>"",IFERROR(D11/AVERAGE(M11,N11),""),IFERROR(D11/M11,""))) | Y11: =IF(OR(LEN(A11)=0,D11="",J11=""),"",IFERROR(D11/J11,"")) | Z11: =IF(OR(LEN(A11)=0,G11="",I11=""),"",G11-I11) | AA11: =IF(OR(LEN(A11)=0,O11="",P11="",P11<=0),"",IFERROR(O11/P11,"")) | AB11: =IF(LEN(A11)=0,"",IF(AND(ISNUMBER(L11),L11<=0),"High Risk",IF(COUNT(D11:L11)=0,"No Data",IF(COUNTBLANK(D11:L11)>0,"Incomplete",CHOOSE(1+IF(AND(ISNUMBER(S11),S11>=1.2),1,0)+IF(AND(ISNUMBER(T11),T11>=0.8),1,0)+IF(AND(ISNUMBER(U11),U11>0,U11<=1.5),1,0)+IF(AND(ISNUMBER(R11),R11>=0),1,0)+IF(AND(ISNUMBER(Z11),Z11>0),1,0),"High Risk","High Risk","Stretched","Adequate with Caution","Adequate","Strong"))))) | AC11: =IF(LEN(A11)=0,"",IF(AB11="Strong",'CRITERIA BUILDER'!$C$14,IF(AB11="Adequate",'CRITERIA BUILDER'!$C$14*0.8,IF(AB11="Adequate with Caution",'CRITERIA BUILDER'!$C$14*0.6,IF(AB11="Stretched",'CRITERIA BUILDER'!$C$14*0.3,0))))) | AD11: =IF(LEN(A11)=0,"",IF(AND(ISNUMBER(L11),L11<=0),A11&" shows negative equity. Screened as High Risk. The Committee should request clarification on accumulated losses, capital position, and any restructuring or capital injection before relying on this bidder.",A11&" is screened as "&AB11&" on financial capacity. The Committee should record the statement year, line items used, and any limitation or clarification required."))
A12: =IF(LEN('BIDDER REGISTER'!B12)=0,"",'BIDDER REGISTER'!B12) | Q12: =IF(OR(LEN(A12)=0,D12="",E12=""),"",IFERROR(E12/D12,"")) | R12: =IF(OR(LEN(A12)=0,D12="",F12=""),"",IFERROR(F12/D12,"")) | S12: =IF(OR(LEN(A12)=0,G12="",I12=""),"",IFERROR(G12/I12,"")) | T12: =IF(OR(LEN(A12)=0,G12="",I12=""),"",IFERROR((G12-IF(H12="",0,H12))/I12,"")) | U12: =IF(OR(LEN(A12)=0,K12="",L12="",L12<=0),"",IFERROR(K12/L12,"")) | V12: =IF(OR(LEN(A12)=0,F12="",J12=""),"",IFERROR(F12/J12,"")) | W12: =IF(OR(LEN(A12)=0,F12="",L12="",L12<=0),"",IFERROR(F12/L12,"")) | X12: =IF(OR(LEN(A12)=0,D12="",M12=""),"",IF(N12<>"",IFERROR(D12/AVERAGE(M12,N12),""),IFERROR(D12/M12,""))) | Y12: =IF(OR(LEN(A12)=0,D12="",J12=""),"",IFERROR(D12/J12,"")) | Z12: =IF(OR(LEN(A12)=0,G12="",I12=""),"",G12-I12) | AA12: =IF(OR(LEN(A12)=0,O12="",P12="",P12<=0),"",IFERROR(O12/P12,"")) | AB12: =IF(LEN(A12)=0,"",IF(AND(ISNUMBER(L12),L12<=0),"High Risk",IF(COUNT(D12:L12)=0,"No Data",IF(COUNTBLANK(D12:L12)>0,"Incomplete",CHOOSE(1+IF(AND(ISNUMBER(S12),S12>=1.2),1,0)+IF(AND(ISNUMBER(T12),T12>=0.8),1,0)+IF(AND(ISNUMBER(U12),U12>0,U12<=1.5),1,0)+IF(AND(ISNUMBER(R12),R12>=0),1,0)+IF(AND(ISNUMBER(Z12),Z12>0),1,0),"High Risk","High Risk","Stretched","Adequate with Caution","Adequate","Strong"))))) | AC12: =IF(LEN(A12)=0,"",IF(AB12="Strong",'CRITERIA BUILDER'!$C$14,IF(AB12="Adequate",'CRITERIA BUILDER'!$C$14*0.8,IF(AB12="Adequate with Caution",'CRITERIA BUILDER'!$C$14*0.6,IF(AB12="Stretched",'CRITERIA BUILDER'!$C$14*0.3,0))))) | AD12: =IF(LEN(A12)=0,"",IF(AND(ISNUMBER(L12),L12<=0),A12&" shows negative equity. Screened as High Risk. The Committee should request clarification on accumulated losses, capital position, and any restructuring or capital injection before relying on this bidder.",A12&" is screened as "&AB12&" on financial capacity. The Committee should record the statement year, line items used, and any limitation or clarification required."))
A13: =IF(LEN('BIDDER REGISTER'!B13)=0,"",'BIDDER REGISTER'!B13) | Q13: =IF(OR(LEN(A13)=0,D13="",E13=""),"",IFERROR(E13/D13,"")) | R13: =IF(OR(LEN(A13)=0,D13="",F13=""),"",IFERROR(F13/D13,"")) | S13: =IF(OR(LEN(A13)=0,G13="",I13=""),"",IFERROR(G13/I13,"")) | T13: =IF(OR(LEN(A13)=0,G13="",I13=""),"",IFERROR((G13-IF(H13="",0,H13))/I13,"")) | U13: =IF(OR(LEN(A13)=0,K13="",L13="",L13<=0),"",IFERROR(K13/L13,"")) | V13: =IF(OR(LEN(A13)=0,F13="",J13=""),"",IFERROR(F13/J13,"")) | W13: =IF(OR(LEN(A13)=0,F13="",L13="",L13<=0),"",IFERROR(F13/L13,"")) | X13: =IF(OR(LEN(A13)=0,D13="",M13=""),"",IF(N13<>"",IFERROR(D13/AVERAGE(M13,N13),""),IFERROR(D13/M13,""))) | Y13: =IF(OR(LEN(A13)=0,D13="",J13=""),"",IFERROR(D13/J13,"")) | Z13: =IF(OR(LEN(A13)=0,G13="",I13=""),"",G13-I13) | AA13: =IF(OR(LEN(A13)=0,O13="",P13="",P13<=0),"",IFERROR(O13/P13,"")) | AB13: =IF(LEN(A13)=0,"",IF(AND(ISNUMBER(L13),L13<=0),"High Risk",IF(COUNT(D13:L13)=0,"No Data",IF(COUNTBLANK(D13:L13)>0,"Incomplete",CHOOSE(1+IF(AND(ISNUMBER(S13),S13>=1.2),1,0)+IF(AND(ISNUMBER(T13),T13>=0.8),1,0)+IF(AND(ISNUMBER(U13),U13>0,U13<=1.5),1,0)+IF(AND(ISNUMBER(R13),R13>=0),1,0)+IF(AND(ISNUMBER(Z13),Z13>0),1,0),"High Risk","High Risk","Stretched","Adequate with Caution","Adequate","Strong"))))) | AC13: =IF(LEN(A13)=0,"",IF(AB13="Strong",'CRITERIA BUILDER'!$C$14,IF(AB13="Adequate",'CRITERIA BUILDER'!$C$14*0.8,IF(AB13="Adequate with Caution",'CRITERIA BUILDER'!$C$14*0.6,IF(AB13="Stretched",'CRITERIA BUILDER'!$C$14*0.3,0))))) | AD13: =IF(LEN(A13)=0,"",IF(AND(ISNUMBER(L13),L13<=0),A13&" shows negative equity. Screened as High Risk. The Committee should request clarification on accumulated losses, capital position, and any restructuring or capital injection before relying on this bidder.",A13&" is screened as "&AB13&" on financial capacity. The Committee should record the statement year, line items used, and any limitation or clarification required."))
A14: =IF(LEN('BIDDER REGISTER'!B14)=0,"",'BIDDER REGISTER'!B14) | Q14: =IF(OR(LEN(A14)=0,D14="",E14=""),"",IFERROR(E14/D14,"")) | R14: =IF(OR(LEN(A14)=0,D14="",F14=""),"",IFERROR(F14/D14,"")) | S14: =IF(OR(LEN(A14)=0,G14="",I14=""),"",IFERROR(G14/I14,"")) | T14: =IF(OR(LEN(A14)=0,G14="",I14=""),"",IFERROR((G14-IF(H14="",0,H14))/I14,"")) | U14: =IF(OR(LEN(A14)=0,K14="",L14="",L14<=0),"",IFERROR(K14/L14,"")) | V14: =IF(OR(LEN(A14)=0,F14="",J14=""),"",IFERROR(F14/J14,"")) | W14: =IF(OR(LEN(A14)=0,F14="",L14="",L14<=0),"",IFERROR(F14/L14,"")) | X14: =IF(OR(LEN(A14)=0,D14="",M14=""),"",IF(N14<>"",IFERROR(D14/AVERAGE(M14,N14),""),IFERROR(D14/M14,""))) | Y14: =IF(OR(LEN(A14)=0,D14="",J14=""),"",IFERROR(D14/J14,"")) | Z14: =IF(OR(LEN(A14)=0,G14="",I14=""),"",G14-I14) | AA14: =IF(OR(LEN(A14)=0,O14="",P14="",P14<=0),"",IFERROR(O14/P14,"")) | AB14: =IF(LEN(A14)=0,"",IF(AND(ISNUMBER(L14),L14<=0),"High Risk",IF(COUNT(D14:L14)=0,"No Data",IF(COUNTBLANK(D14:L14)>0,"Incomplete",CHOOSE(1+IF(AND(ISNUMBER(S14),S14>=1.2),1,0)+IF(AND(ISNUMBER(T14),T14>=0.8),1,0)+IF(AND(ISNUMBER(U14),U14>0,U14<=1.5),1,0)+IF(AND(ISNUMBER(R14),R14>=0),1,0)+IF(AND(ISNUMBER(Z14),Z14>0),1,0),"High Risk","High Risk","Stretched","Adequate with Caution","Adequate","Strong"))))) | AC14: =IF(LEN(A14)=0,"",IF(AB14="Strong",'CRITERIA BUILDER'!$C$14,IF(AB14="Adequate",'CRITERIA BUILDER'!$C$14*0.8,IF(AB14="Adequate with Caution",'CRITERIA BUILDER'!$C$14*0.6,IF(AB14="Stretched",'CRITERIA BUILDER'!$C$14*0.3,0))))) | AD14: =IF(LEN(A14)=0,"",IF(AND(ISNUMBER(L14),L14<=0),A14&" shows negative equity. Screened as High Risk. The Committee should request clarification on accumulated losses, capital position, and any restructuring or capital injection before relying on this bidder.",A14&" is screened as "&AB14&" on financial capacity. The Committee should record the statement year, line items used, and any limitation or clarification required."))
A15: =IF(LEN('BIDDER REGISTER'!B15)=0,"",'BIDDER REGISTER'!B15) | Q15: =IF(OR(LEN(A15)=0,D15="",E15=""),"",IFERROR(E15/D15,"")) | R15: =IF(OR(LEN(A15)=0,D15="",F15=""),"",IFERROR(F15/D15,"")) | S15: =IF(OR(LEN(A15)=0,G15="",I15=""),"",IFERROR(G15/I15,"")) | T15: =IF(OR(LEN(A15)=0,G15="",I15=""),"",IFERROR((G15-IF(H15="",0,H15))/I15,"")) | U15: =IF(OR(LEN(A15)=0,K15="",L15="",L15<=0),"",IFERROR(K15/L15,"")) | V15: =IF(OR(LEN(A15)=0,F15="",J15=""),"",IFERROR(F15/J15,"")) | W15: =IF(OR(LEN(A15)=0,F15="",L15="",L15<=0),"",IFERROR(F15/L15,"")) | X15: =IF(OR(LEN(A15)=0,D15="",M15=""),"",IF(N15<>"",IFERROR(D15/AVERAGE(M15,N15),""),IFERROR(D15/M15,""))) | Y15: =IF(OR(LEN(A15)=0,D15="",J15=""),"",IFERROR(D15/J15,"")) | Z15: =IF(OR(LEN(A15)=0,G15="",I15=""),"",G15-I15) | AA15: =IF(OR(LEN(A15)=0,O15="",P15="",P15<=0),"",IFERROR(O15/P15,"")) | AB15: =IF(LEN(A15)=0,"",IF(AND(ISNUMBER(L15),L15<=0),"High Risk",IF(COUNT(D15:L15)=0,"No Data",IF(COUNTBLANK(D15:L15)>0,"Incomplete",CHOOSE(1+IF(AND(ISNUMBER(S15),S15>=1.2),1,0)+IF(AND(ISNUMBER(T15),T15>=0.8),1,0)+IF(AND(ISNUMBER(U15),U15>0,U15<=1.5),1,0)+IF(AND(ISNUMBER(R15),R15>=0),1,0)+IF(AND(ISNUMBER(Z15),Z15>0),1,0),"High Risk","High Risk","Stretched","Adequate with Caution","Adequate","Strong"))))) | AC15: =IF(LEN(A15)=0,"",IF(AB15="Strong",'CRITERIA BUILDER'!$C$14,IF(AB15="Adequate",'CRITERIA BUILDER'!$C$14*0.8,IF(AB15="Adequate with Caution",'CRITERIA BUILDER'!$C$14*0.6,IF(AB15="Stretched",'CRITERIA BUILDER'!$C$14*0.3,0))))) | AD15: =IF(LEN(A15)=0,"",IF(AND(ISNUMBER(L15),L15<=0),A15&" shows negative equity. Screened as High Risk. The Committee should request clarification on accumulated losses, capital position, and any restructuring or capital injection before relying on this bidder.",A15&" is screened as "&AB15&" on financial capacity. The Committee should record the statement year, line items used, and any limitation or clarification required."))
A16: =IF(LEN('BIDDER REGISTER'!B16)=0,"",'BIDDER REGISTER'!B16) | Q16: =IF(OR(LEN(A16)=0,D16="",E16=""),"",IFERROR(E16/D16,"")) | R16: =IF(OR(LEN(A16)=0,D16="",F16=""),"",IFERROR(F16/D16,"")) | S16: =IF(OR(LEN(A16)=0,G16="",I16=""),"",IFERROR(G16/I16,"")) | T16: =IF(OR(LEN(A16)=0,G16="",I16=""),"",IFERROR((G16-IF(H16="",0,H16))/I16,"")) | U16: =IF(OR(LEN(A16)=0,K16="",L16="",L16<=0),"",IFERROR(K16/L16,"")) | V16: =IF(OR(LEN(A16)=0,F16="",J16=""),"",IFERROR(F16/J16,"")) | W16: =IF(OR(LEN(A16)=0,F16="",L16="",L16<=0),"",IFERROR(F16/L16,"")) | X16: =IF(OR(LEN(A16)=0,D16="",M16=""),"",IF(N16<>"",IFERROR(D16/AVERAGE(M16,N16),""),IFERROR(D16/M16,""))) | Y16: =IF(OR(LEN(A16)=0,D16="",J16=""),"",IFERROR(D16/J16,"")) | Z16: =IF(OR(LEN(A16)=0,G16="",I16=""),"",G16-I16) | AA16: =IF(OR(LEN(A16)=0,O16="",P16="",P16<=0),"",IFERROR(O16/P16,"")) | AB16: =IF(LEN(A16)=0,"",IF(AND(ISNUMBER(L16),L16<=0),"High Risk",IF(COUNT(D16:L16)=0,"No Data",IF(COUNTBLANK(D16:L16)>0,"Incomplete",CHOOSE(1+IF(AND(ISNUMBER(S16),S16>=1.2),1,0)+IF(AND(ISNUMBER(T16),T16>=0.8),1,0)+IF(AND(ISNUMBER(U16),U16>0,U16<=1.5),1,0)+IF(AND(ISNUMBER(R16),R16>=0),1,0)+IF(AND(ISNUMBER(Z16),Z16>0),1,0),"High Risk","High Risk","Stretched","Adequate with Caution","Adequate","Strong"))))) | AC16: =IF(LEN(A16)=0,"",IF(AB16="Strong",'CRITERIA BUILDER'!$C$14,IF(AB16="Adequate",'CRITERIA BUILDER'!$C$14*0.8,IF(AB16="Adequate with Caution",'CRITERIA BUILDER'!$C$14*0.6,IF(AB16="Stretched",'CRITERIA BUILDER'!$C$14*0.3,0))))) | AD16: =IF(LEN(A16)=0,"",IF(AND(ISNUMBER(L16),L16<=0),A16&" shows negative equity. Screened as High Risk. The Committee should request clarification on accumulated losses, capital position, and any restructuring or capital injection before relying on this bidder.",A16&" is screened as "&AB16&" on financial capacity. The Committee should record the statement year, line items used, and any limitation or clarification required."))
A17: =IF(LEN('BIDDER REGISTER'!B17)=0,"",'BIDDER REGISTER'!B17) | Q17: =IF(OR(LEN(A17)=0,D17="",E17=""),"",IFERROR(E17/D17,"")) | R17: =IF(OR(LEN(A17)=0,D17="",F17=""),"",IFERROR(F17/D17,"")) | S17: =IF(OR(LEN(A17)=0,G17="",I17=""),"",IFERROR(G17/I17,"")) | T17: =IF(OR(LEN(A17)=0,G17="",I17=""),"",IFERROR((G17-IF(H17="",0,H17))/I17,"")) | U17: =IF(OR(LEN(A17)=0,K17="",L17="",L17<=0),"",IFERROR(K17/L17,"")) | V17: =IF(OR(LEN(A17)=0,F17="",J17=""),"",IFERROR(F17/J17,"")) | W17: =IF(OR(LEN(A17)=0,F17="",L17="",L17<=0),"",IFERROR(F17/L17,"")) | X17: =IF(OR(LEN(A17)=0,D17="",M17=""),"",IF(N17<>"",IFERROR(D17/AVERAGE(M17,N17),""),IFERROR(D17/M17,""))) | Y17: =IF(OR(LEN(A17)=0,D17="",J17=""),"",IFERROR(D17/J17,"")) | Z17: =IF(OR(LEN(A17)=0,G17="",I17=""),"",G17-I17) | AA17: =IF(OR(LEN(A17)=0,O17="",P17="",P17<=0),"",IFERROR(O17/P17,"")) | AB17: =IF(LEN(A17)=0,"",IF(AND(ISNUMBER(L17),L17<=0),"High Risk",IF(COUNT(D17:L17)=0,"No Data",IF(COUNTBLANK(D17:L17)>0,"Incomplete",CHOOSE(1+IF(AND(ISNUMBER(S17),S17>=1.2),1,0)+IF(AND(ISNUMBER(T17),T17>=0.8),1,0)+IF(AND(ISNUMBER(U17),U17>0,U17<=1.5),1,0)+IF(AND(ISNUMBER(R17),R17>=0),1,0)+IF(AND(ISNUMBER(Z17),Z17>0),1,0),"High Risk","High Risk","Stretched","Adequate with Caution","Adequate","Strong"))))) | AC17: =IF(LEN(A17)=0,"",IF(AB17="Strong",'CRITERIA BUILDER'!$C$14,IF(AB17="Adequate",'CRITERIA BUILDER'!$C$14*0.8,IF(AB17="Adequate with Caution",'CRITERIA BUILDER'!$C$14*0.6,IF(AB17="Stretched",'CRITERIA BUILDER'!$C$14*0.3,0))))) | AD17: =IF(LEN(A17)=0,"",IF(AND(ISNUMBER(L17),L17<=0),A17&" shows negative equity. Screened as High Risk. The Committee should request clarification on accumulated losses, capital position, and any restructuring or capital injection before relying on this bidder.",A17&" is screened as "&AB17&" on financial capacity. The Committee should record the statement year, line items used, and any limitation or clarification required."))
A18: =IF(LEN('BIDDER REGISTER'!B18)=0,"",'BIDDER REGISTER'!B18) | Q18: =IF(OR(LEN(A18)=0,D18="",E18=""),"",IFERROR(E18/D18,"")) | R18: =IF(OR(LEN(A18)=0,D18="",F18=""),"",IFERROR(F18/D18,"")) | S18: =IF(OR(LEN(A18)=0,G18="",I18=""),"",IFERROR(G18/I18,"")) | T18: =IF(OR(LEN(A18)=0,G18="",I18=""),"",IFERROR((G18-IF(H18="",0,H18))/I18,"")) | U18: =IF(OR(LEN(A18)=0,K18="",L18="",L18<=0),"",IFERROR(K18/L18,"")) | V18: =IF(OR(LEN(A18)=0,F18="",J18=""),"",IFERROR(F18/J18,"")) | W18: =IF(OR(LEN(A18)=0,F18="",L18="",L18<=0),"",IFERROR(F18/L18,"")) | X18: =IF(OR(LEN(A18)=0,D18="",M18=""),"",IF(N18<>"",IFERROR(D18/AVERAGE(M18,N18),""),IFERROR(D18/M18,""))) | Y18: =IF(OR(LEN(A18)=0,D18="",J18=""),"",IFERROR(D18/J18,"")) | Z18: =IF(OR(LEN(A18)=0,G18="",I18=""),"",G18-I18) | AA18: =IF(OR(LEN(A18)=0,O18="",P18="",P18<=0),"",IFERROR(O18/P18,"")) | AB18: =IF(LEN(A18)=0,"",IF(AND(ISNUMBER(L18),L18<=0),"High Risk",IF(COUNT(D18:L18)=0,"No Data",IF(COUNTBLANK(D18:L18)>0,"Incomplete",CHOOSE(1+IF(AND(ISNUMBER(S18),S18>=1.2),1,0)+IF(AND(ISNUMBER(T18),T18>=0.8),1,0)+IF(AND(ISNUMBER(U18),U18>0,U18<=1.5),1,0)+IF(AND(ISNUMBER(R18),R18>=0),1,0)+IF(AND(ISNUMBER(Z18),Z18>0),1,0),"High Risk","High Risk","Stretched","Adequate with Caution","Adequate","Strong"))))) | AC18: =IF(LEN(A18)=0,"",IF(AB18="Strong",'CRITERIA BUILDER'!$C$14,IF(AB18="Adequate",'CRITERIA BUILDER'!$C$14*0.8,IF(AB18="Adequate with Caution",'CRITERIA BUILDER'!$C$14*0.6,IF(AB18="Stretched",'CRITERIA BUILDER'!$C$14*0.3,0))))) | AD18: =IF(LEN(A18)=0,"",IF(AND(ISNUMBER(L18),L18<=0),A18&" shows negative equity. Screened as High Risk. The Committee should request clarification on accumulated losses, capital position, and any restructuring or capital injection before relying on this bidder.",A18&" is screened as "&AB18&" on financial capacity. The Committee should record the statement year, line items used, and any limitation or clarification required."))
... A26: =IF(LEN('BIDDER REGISTER'!B26)=0,"",'BIDDER REGISTER'!B26) | Q26: =IF(OR(LEN(A26)=0,D26="",E26=""),"",IFERROR(E26/D26,"")) | R26: =IF(OR(LEN(A26)=0,D26="",F26=""),"",IFERROR(F26/D26,"")) | S26: =IF(OR(LEN(A26)=0,G26="",I26=""),"",IFERROR(G26/I26,"")) | T26: =IF(OR(LEN(A26)=0,G26="",I26=""),"",IFERROR((G26-IF(H26="",0,H26))/I26,"")) | U26: =IF(OR(LEN(A26)=0,K26="",L26="",L26<=0),"",IFERROR(K26/L26,"")) | V26: =IF(OR(LEN(A26)=0,F26="",J26=""),"",IFERROR(F26/J26,"")) | W26: =IF(OR(LEN(A26)=0,F26="",L26="",L26<=0),"",IFERROR(F26/L26,"")) | X26: =IF(OR(LEN(A26)=0,D26="",M26=""),"",IF(N26<>"",IFERROR(D26/AVERAGE(M26,N26),""),IFERROR(D26/M26,""))) | Y26: =IF(OR(LEN(A26)=0,D26="",J26=""),"",IFERROR(D26/J26,"")) | Z26: =IF(OR(LEN(A26)=0,G26="",I26=""),"",G26-I26) | AA26: =IF(OR(LEN(A26)=0,O26="",P26="",P26<=0),"",IFERROR(O26/P26,"")) | AB26: =IF(LEN(A26)=0,"",IF(AND(ISNUMBER(L26),L26<=0),"High Risk",IF(COUNT(D26:L26)=0,"No Data",IF(COUNTBLANK(D26:L26)>0,"Incomplete",CHOOSE(1+IF(AND(ISNUMBER(S26),S26>=1.2),1,0)+IF(AND(ISNUMBER(T26),T26>=0.8),1,0)+IF(AND(ISNUMBER(U26),U26>0,U26<=1.5),1,0)+IF(AND(ISNUMBER(R26),R26>=0),1,0)+IF(AND(ISNUMBER(Z26),Z26>0),1,0),"High Risk","High Risk","Stretched","Adequate with Caution","Adequate","Strong"))))) | AC26: =IF(LEN(A26)=0,"",IF(AB26="Strong",'CRITERIA BUILDER'!$C$14,IF(AB26="Adequate",'CRITERIA BUILDER'!$C$14*0.8,IF(AB26="Adequate with Caution",'CRITERIA BUILDER'!$C$14*0.6,IF(AB26="Stretched",'CRITERIA BUILDER'!$C$14*0.3,0))))) | AD26: =IF(LEN(A26)=0,"",IF(AND(ISNUMBER(L26),L26<=0),A26&" shows negative equity. Screened as High Risk. The Committee should request clarification on accumulated losses, capital position, and any restructuring or capital injection before relying on this bidder.",A26&" is screened as "&AB26&" on financial capacity. The Committee should record the statement year, line items used, and any limitation or clarification required."))

Sheet COMMERCIAL EVAL
A1: COMMERCIAL EVALUATION
A2: Enter evaluated prices. Price score is calculated only for bidders that are responsive and meet the minimum technical threshold.
A6: Bidder | B6: Responsive? | C6: Tech Pass? | D6: Evaluated Price Ex VAT | E6: VAT | F6: Evaluated Price Incl VAT | G6: Eligible for Price Scoring? | H6: Price Score | I6: Commercial Note | J6: Eligible Price Helper
A7: =IF(LEN('BIDDER REGISTER'!B7)=0,"",'BIDDER REGISTER'!B7) | B7: =IF(LEN(A7)=0,"",RESPONSIVENESS!J7) | C7: =IF(LEN(A7)=0,"",'TECHNICAL SCORING'!J7) | F7: =IF(LEN(A7)=0,"",IFERROR(D7+E7,"")) | G7: =IF(LEN(A7)=0,"",IF(AND(B7="Responsive",C7="Yes",F7>0),"Yes","No")) | H7: =IF(LEN(A7)=0,"",IF(G7<>"Yes",0,IFERROR(MIN($J$7:$J$26)/F7*'CRITERIA BUILDER'!$C$15,0))) | I7: =IF(LEN(A7)=0,"",IF(G7="Yes","Price scored against lowest evaluated responsive price.","Not eligible for price scoring at this stage.")) | J7: =IF(G7="Yes",F7,"")
A8: =IF(LEN('BIDDER REGISTER'!B8)=0,"",'BIDDER REGISTER'!B8) | B8: =IF(LEN(A8)=0,"",RESPONSIVENESS!J8) | C8: =IF(LEN(A8)=0,"",'TECHNICAL SCORING'!J8) | F8: =IF(LEN(A8)=0,"",IFERROR(D8+E8,"")) | G8: =IF(LEN(A8)=0,"",IF(AND(B8="Responsive",C8="Yes",F8>0),"Yes","No")) | H8: =IF(LEN(A8)=0,"",IF(G8<>"Yes",0,IFERROR(MIN($J$7:$J$26)/F8*'CRITERIA BUILDER'!$C$15,0))) | I8: =IF(LEN(A8)=0,"",IF(G8="Yes","Price scored against lowest evaluated responsive price.","Not eligible for price scoring at this stage.")) | J8: =IF(G8="Yes",F8,"")
A9: =IF(LEN('BIDDER REGISTER'!B9)=0,"",'BIDDER REGISTER'!B9) | B9: =IF(LEN(A9)=0,"",RESPONSIVENESS!J9) | C9: =IF(LEN(A9)=0,"",'TECHNICAL SCORING'!J9) | F9: =IF(LEN(A9)=0,"",IFERROR(D9+E9,"")) | G9: =IF(LEN(A9)=0,"",IF(AND(B9="Responsive",C9="Yes",F9>0),"Yes","No")) | H9: =IF(LEN(A9)=0,"",IF(G9<>"Yes",0,IFERROR(MIN($J$7:$J$26)/F9*'CRITERIA BUILDER'!$C$15,0))) | I9: =IF(LEN(A9)=0,"",IF(G9="Yes","Price scored against lowest evaluated responsive price.","Not eligible for price scoring at this stage.")) | J9: =IF(G9="Yes",F9,"")
A10: =IF(LEN('BIDDER REGISTER'!B10)=0,"",'BIDDER REGISTER'!B10) | B10: =IF(LEN(A10)=0,"",RESPONSIVENESS!J10) | C10: =IF(LEN(A10)=0,"",'TECHNICAL SCORING'!J10) | F10: =IF(LEN(A10)=0,"",IFERROR(D10+E10,"")) | G10: =IF(LEN(A10)=0,"",IF(AND(B10="Responsive",C10="Yes",F10>0),"Yes","No")) | H10: =IF(LEN(A10)=0,"",IF(G10<>"Yes",0,IFERROR(MIN($J$7:$J$26)/F10*'CRITERIA BUILDER'!$C$15,0))) | I10: =IF(LEN(A10)=0,"",IF(G10="Yes","Price scored against lowest evaluated responsive price.","Not eligible for price scoring at this stage.")) | J10: =IF(G10="Yes",F10,"")
A11: =IF(LEN('BIDDER REGISTER'!B11)=0,"",'BIDDER REGISTER'!B11) | B11: =IF(LEN(A11)=0,"",RESPONSIVENESS!J11) | C11: =IF(LEN(A11)=0,"",'TECHNICAL SCORING'!J11) | F11: =IF(LEN(A11)=0,"",IFERROR(D11+E11,"")) | G11: =IF(LEN(A11)=0,"",IF(AND(B11="Responsive",C11="Yes",F11>0),"Yes","No")) | H11: =IF(LEN(A11)=0,"",IF(G11<>"Yes",0,IFERROR(MIN($J$7:$J$26)/F11*'CRITERIA BUILDER'!$C$15,0))) | I11: =IF(LEN(A11)=0,"",IF(G11="Yes","Price scored against lowest evaluated responsive price.","Not eligible for price scoring at this stage.")) | J11: =IF(G11="Yes",F11,"")
A12: =IF(LEN('BIDDER REGISTER'!B12)=0,"",'BIDDER REGISTER'!B12) | B12: =IF(LEN(A12)=0,"",RESPONSIVENESS!J12) | C12: =IF(LEN(A12)=0,"",'TECHNICAL SCORING'!J12) | F12: =IF(LEN(A12)=0,"",IFERROR(D12+E12,"")) | G12: =IF(LEN(A12)=0,"",IF(AND(B12="Responsive",C12="Yes",F12>0),"Yes","No")) | H12: =IF(LEN(A12)=0,"",IF(G12<>"Yes",0,IFERROR(MIN($J$7:$J$26)/F12*'CRITERIA BUILDER'!$C$15,0))) | I12: =IF(LEN(A12)=0,"",IF(G12="Yes","Price scored against lowest evaluated responsive price.","Not eligible for price scoring at this stage.")) | J12: =IF(G12="Yes",F12,"")
A13: =IF(LEN('BIDDER REGISTER'!B13)=0,"",'BIDDER REGISTER'!B13) | B13: =IF(LEN(A13)=0,"",RESPONSIVENESS!J13) | C13: =IF(LEN(A13)=0,"",'TECHNICAL SCORING'!J13) | F13: =IF(LEN(A13)=0,"",IFERROR(D13+E13,"")) | G13: =IF(LEN(A13)=0,"",IF(AND(B13="Responsive",C13="Yes",F13>0),"Yes","No")) | H13: =IF(LEN(A13)=0,"",IF(G13<>"Yes",0,IFERROR(MIN($J$7:$J$26)/F13*'CRITERIA BUILDER'!$C$15,0))) | I13: =IF(LEN(A13)=0,"",IF(G13="Yes","Price scored against lowest evaluated responsive price.","Not eligible for price scoring at this stage.")) | J13: =IF(G13="Yes",F13,"")
A14: =IF(LEN('BIDDER REGISTER'!B14)=0,"",'BIDDER REGISTER'!B14) | B14: =IF(LEN(A14)=0,"",RESPONSIVENESS!J14) | C14: =IF(LEN(A14)=0,"",'TECHNICAL SCORING'!J14) | F14: =IF(LEN(A14)=0,"",IFERROR(D14+E14,"")) | G14: =IF(LEN(A14)=0,"",IF(AND(B14="Responsive",C14="Yes",F14>0),"Yes","No")) | H14: =IF(LEN(A14)=0,"",IF(G14<>"Yes",0,IFERROR(MIN($J$7:$J$26)/F14*'CRITERIA BUILDER'!$C$15,0))) | I14: =IF(LEN(A14)=0,"",IF(G14="Yes","Price scored against lowest evaluated responsive price.","Not eligible for price scoring at this stage.")) | J14: =IF(G14="Yes",F14,"")
A15: =IF(LEN('BIDDER REGISTER'!B15)=0,"",'BIDDER REGISTER'!B15) | B15: =IF(LEN(A15)=0,"",RESPONSIVENESS!J15) | C15: =IF(LEN(A15)=0,"",'TECHNICAL SCORING'!J15) | F15: =IF(LEN(A15)=0,"",IFERROR(D15+E15,"")) | G15: =IF(LEN(A15)=0,"",IF(AND(B15="Responsive",C15="Yes",F15>0),"Yes","No")) | H15: =IF(LEN(A15)=0,"",IF(G15<>"Yes",0,IFERROR(MIN($J$7:$J$26)/F15*'CRITERIA BUILDER'!$C$15,0))) | I15: =IF(LEN(A15)=0,"",IF(G15="Yes","Price scored against lowest evaluated responsive price.","Not eligible for price scoring at this stage.")) | J15: =IF(G15="Yes",F15,"")
A16: =IF(LEN('BIDDER REGISTER'!B16)=0,"",'BIDDER REGISTER'!B16) | B16: =IF(LEN(A16)=0,"",RESPONSIVENESS!J16) | C16: =IF(LEN(A16)=0,"",'TECHNICAL SCORING'!J16) | F16: =IF(LEN(A16)=0,"",IFERROR(D16+E16,"")) | G16: =IF(LEN(A16)=0,"",IF(AND(B16="Responsive",C16="Yes",F16>0),"Yes","No")) | H16: =IF(LEN(A16)=0,"",IF(G16<>"Yes",0,IFERROR(MIN($J$7:$J$26)/F16*'CRITERIA BUILDER'!$C$15,0))) | I16: =IF(LEN(A16)=0,"",IF(G16="Yes","Price scored against lowest evaluated responsive price.","Not eligible for price scoring at this stage.")) | J16: =IF(G16="Yes",F16,"")
A17: =IF(LEN('BIDDER REGISTER'!B17)=0,"",'BIDDER REGISTER'!B17) | B17: =IF(LEN(A17)=0,"",RESPONSIVENESS!J17) | C17: =IF(LEN(A17)=0,"",'TECHNICAL SCORING'!J17) | F17: =IF(LEN(A17)=0,"",IFERROR(D17+E17,"")) | G17: =IF(LEN(A17)=0,"",IF(AND(B17="Responsive",C17="Yes",F17>0),"Yes","No")) | H17: =IF(LEN(A17)=0,"",IF(G17<>"Yes",0,IFERROR(MIN($J$7:$J$26)/F17*'CRITERIA BUILDER'!$C$15,0))) | I17: =IF(LEN(A17)=0,"",IF(G17="Yes","Price scored against lowest evaluated responsive price.","Not eligible for price scoring at this stage.")) | J17: =IF(G17="Yes",F17,"")
A18: =IF(LEN('BIDDER REGISTER'!B18)=0,"",'BIDDER REGISTER'!B18) | B18: =IF(LEN(A18)=0,"",RESPONSIVENESS!J18) | C18: =IF(LEN(A18)=0,"",'TECHNICAL SCORING'!J18) | F18: =IF(LEN(A18)=0,"",IFERROR(D18+E18,"")) | G18: =IF(LEN(A18)=0,"",IF(AND(B18="Responsive",C18="Yes",F18>0),"Yes","No")) | H18: =IF(LEN(A18)=0,"",IF(G18<>"Yes",0,IFERROR(MIN($J$7:$J$26)/F18*'CRITERIA BUILDER'!$C$15,0))) | I18: =IF(LEN(A18)=0,"",IF(G18="Yes","Price scored against lowest evaluated responsive price.","Not eligible for price scoring at this stage.")) | J18: =IF(G18="Yes",F18,"")
... A26: =IF(LEN('BIDDER REGISTER'!B26)=0,"",'BIDDER REGISTER'!B26) | B26: =IF(LEN(A26)=0,"",RESPONSIVENESS!J26) | C26: =IF(LEN(A26)=0,"",'TECHNICAL SCORING'!J26) | F26: =IF(LEN(A26)=0,"",IFERROR(D26+E26,"")) | G26: =IF(LEN(A26)=0,"",IF(AND(B26="Responsive",C26="Yes",F26>0),"Yes","No")) | H26: =IF(LEN(A26)=0,"",IF(G26<>"Yes",0,IFERROR(MIN($J$7:$J$26)/F26*'CRITERIA BUILDER'!$C$15,0))) | I26: =IF(LEN(A26)=0,"",IF(G26="Yes","Price scored against lowest evaluated responsive price.","Not eligible for price scoring at this stage.")) | J26: =IF(G26="Yes",F26,"")

Sheet CLARIFICATIONS
A1: CLARIFICATION LOG
A2: Record all clarification questions and responses. Keep substance separate from correction of minor arithmetic or missing proof.
A6: No. | B6: Bidder | C6: Date Asked | D6: Question / Clarification Requested | E6: Date Response Received | F6: Response Summary | G6: Changed Score? | H6: Committee Note
A7: 1
A8: 2
A9: 3
A10: 4
A11: 5
A12: 6
A13: 7
A14: 8
A15: 9
A16: 10
A17: 11
A18: 12
... A36: 30

Sheet DASHBOARD
A1: EVALUATION DASHBOARD
A2: Quick view of bidder status, scores, ranking and recommended next action.
A4: Tender | B4: ='TENDER SETUP'!B7 -> 0 | D4: Dashboard is a review screen only. The final evaluation report must still record methodology, criteria, reasons, limitations, clarification history and recommendation.
A5: Total Bidders | B5: =COUNTIF('BIDDER REGISTER'!B7:B26,"?*") -> 0
A6: Responsive Bidders | B6: =COUNTIF(RESPONSIVENESS!J7:J26,"Responsive") -> 0
A7: Price-Eligible Bidders | B7: =COUNTIF('COMMERCIAL EVAL'!G7:G26,"Yes") -> 0
A10: Rank | B10: Bidder | C10: Responsive | D10: Tech Score | E10: Financial Rating | F10: Financial Score | G10: Price Score | H10: Total Score | I10: Status | J10: Recommended Action
A11: =IF(LEN(B11)=0,"",IF(C11<>"Responsive","",IFERROR(1+COUNTIF($H$11:$H$30,">"&H11),""))) | B11: =IF(LEN('BIDDER REGISTER'!B7)=0,"",'BIDDER REGISTER'!B7) | C11: =IF(LEN(B11)=0,"",RESPONSIVENESS!J7) | D11: =IF(LEN(B11)=0,"",'TECHNICAL SCORING'!I7) | E11: =IF(LEN(B11)=0,"",'FINANCIAL CAPACITY'!AB7) | F11: =IF(LEN(B11)=0,"",'FINANCIAL CAPACITY'!AC7) | G11: =IF(LEN(B11)=0,"",'COMMERCIAL EVAL'!H7) | H11: =IF(LEN(B11)=0,"",IF(C11<>"Responsive",0,D11+F11+G11)) | I11: =IF(LEN(B11)=0,"",IF(C11<>"Responsive","Excluded - responsiveness",IF('TECHNICAL SCORING'!J7<>"Yes","Not technically qualified",IF(H11<'TENDER SETUP'!$B$15,"Below overall pass mark","Evaluated")))) | J11: =IF(LEN(B11)=0,"",IF(I11="Below overall pass mark","Do not recommend award under current scoring; below the stated overall pass mark.",IF(I11<>"Evaluated","Do not proceed unless rules allow correction/clarification.",IF(A11=1,IF(OR(E11="High Risk",E11="Stretched",E11="No Data",E11="Incomplete"),"Highest ranked, but financial capacity is "&E11&" — clarify or seek further evidence before recommending award.","Recommended for award/negotiation subject to approvals."),"Evaluated - not highest ranked."))))
A12: =IF(LEN(B12)=0,"",IF(C12<>"Responsive","",IFERROR(1+COUNTIF($H$11:$H$30,">"&H12),""))) | B12: =IF(LEN('BIDDER REGISTER'!B8)=0,"",'BIDDER REGISTER'!B8) | C12: =IF(LEN(B12)=0,"",RESPONSIVENESS!J8) | D12: =IF(LEN(B12)=0,"",'TECHNICAL SCORING'!I8) | E12: =IF(LEN(B12)=0,"",'FINANCIAL CAPACITY'!AB8) | F12: =IF(LEN(B12)=0,"",'FINANCIAL CAPACITY'!AC8) | G12: =IF(LEN(B12)=0,"",'COMMERCIAL EVAL'!H8) | H12: =IF(LEN(B12)=0,"",IF(C12<>"Responsive",0,D12+F12+G12)) | I12: =IF(LEN(B12)=0,"",IF(C12<>"Responsive","Excluded - responsiveness",IF('TECHNICAL SCORING'!J8<>"Yes","Not technically qualified",IF(H12<'TENDER SETUP'!$B$15,"Below overall pass mark","Evaluated")))) | J12: =IF(LEN(B12)=0,"",IF(I12="Below overall pass mark","Do not recommend award under current scoring; below the stated overall pass mark.",IF(I12<>"Evaluated","Do not proceed unless rules allow correction/clarification.",IF(A12=1,IF(OR(E12="High Risk",E12="Stretched",E12="No Data",E12="Incomplete"),"Highest ranked, but financial capacity is "&E12&" — clarify or seek further evidence before recommending award.","Recommended for award/negotiation subject to approvals."),"Evaluated - not highest ranked."))))
A13: =IF(LEN(B13)=0,"",IF(C13<>"Responsive","",IFERROR(1+COUNTIF($H$11:$H$30,">"&H13),""))) | B13: =IF(LEN('BIDDER REGISTER'!B9)=0,"",'BIDDER REGISTER'!B9) | C13: =IF(LEN(B13)=0,"",RESPONSIVENESS!J9) | D13: =IF(LEN(B13)=0,"",'TECHNICAL SCORING'!I9) | E13: =IF(LEN(B13)=0,"",'FINANCIAL CAPACITY'!AB9) | F13: =IF(LEN(B13)=0,"",'FINANCIAL CAPACITY'!AC9) | G13: =IF(LEN(B13)=0,"",'COMMERCIAL EVAL'!H9) | H13: =IF(LEN(B13)=0,"",IF(C13<>"Responsive",0,D13+F13+G13)) | I13: =IF(LEN(B13)=0,"",IF(C13<>"Responsive","Excluded - responsiveness",IF('TECHNICAL SCORING'!J9<>"Yes","Not technically qualified",IF(H13<'TENDER SETUP'!$B$15,"Below overall pass mark","Evaluated")))) | J13: =IF(LEN(B13)=0,"",IF(I13="Below overall pass mark","Do not recommend award under current scoring; below the stated overall pass mark.",IF(I13<>"Evaluated","Do not proceed unless rules allow correction/clarification.",IF(A13=1,IF(OR(E13="High Risk",E13="Stretched",E13="No Data",E13="Incomplete"),"Highest ranked, but financial capacity is "&E13&" — clarify or seek further evidence before recommending award.","Recommended for award/negotiation subject to approvals."),"Evaluated - not highest ranked."))))
A14: =IF(LEN(B14)=0,"",IF(C14<>"Responsive","",IFERROR(1+COUNTIF($H$11:$H$30,">"&H14),""))) | B14: =IF(LEN('BIDDER REGISTER'!B10)=0,"",'BIDDER REGISTER'!B10) | C14: =IF(LEN(B14)=0,"",RESPONSIVENESS!J10) | D14: =IF(LEN(B14)=0,"",'TECHNICAL SCORING'!I10) | E14: =IF(LEN(B14)=0,"",'FINANCIAL CAPACITY'!AB10) | F14: =IF(LEN(B14)=0,"",'FINANCIAL CAPACITY'!AC10) | G14: =IF(LEN(B14)=0,"",'COMMERCIAL EVAL'!H10) | H14: =IF(LEN(B14)=0,"",IF(C14<>"Responsive",0,D14+F14+G14)) | I14: =IF(LEN(B14)=0,"",IF(C14<>"Responsive","Excluded - responsiveness",IF('TECHNICAL SCORING'!J10<>"Yes","Not technically qualified",IF(H14<'TENDER SETUP'!$B$15,"Below overall pass mark","Evaluated")))) | J14: =IF(LEN(B14)=0,"",IF(I14="Below overall pass mark","Do not recommend award under current scoring; below the stated overall pass mark.",IF(I14<>"Evaluated","Do not proceed unless rules allow correction/clarification.",IF(A14=1,IF(OR(E14="High Risk",E14="Stretched",E14="No Data",E14="Incomplete"),"Highest ranked, but financial capacity is "&E14&" — clarify or seek further evidence before recommending award.","Recommended for award/negotiation subject to approvals."),"Evaluated - not highest ranked."))))
A15: =IF(LEN(B15)=0,"",IF(C15<>"Responsive","",IFERROR(1+COUNTIF($H$11:$H$30,">"&H15),""))) | B15: =IF(LEN('BIDDER REGISTER'!B11)=0,"",'BIDDER REGISTER'!B11) | C15: =IF(LEN(B15)=0,"",RESPONSIVENESS!J11) | D15: =IF(LEN(B15)=0,"",'TECHNICAL SCORING'!I11) | E15: =IF(LEN(B15)=0,"",'FINANCIAL CAPACITY'!AB11) | F15: =IF(LEN(B15)=0,"",'FINANCIAL CAPACITY'!AC11) | G15: =IF(LEN(B15)=0,"",'COMMERCIAL EVAL'!H11) | H15: =IF(LEN(B15)=0,"",IF(C15<>"Responsive",0,D15+F15+G15)) | I15: =IF(LEN(B15)=0,"",IF(C15<>"Responsive","Excluded - responsiveness",IF('TECHNICAL SCORING'!J11<>"Yes","Not technically qualified",IF(H15<'TENDER SETUP'!$B$15,"Below overall pass mark","Evaluated")))) | J15: =IF(LEN(B15)=0,"",IF(I15="Below overall pass mark","Do not recommend award under current scoring; below the stated overall pass mark.",IF(I15<>"Evaluated","Do not proceed unless rules allow correction/clarification.",IF(A15=1,IF(OR(E15="High Risk",E15="Stretched",E15="No Data",E15="Incomplete"),"Highest ranked, but financial capacity is "&E15&" — clarify or seek further evidence before recommending award.","Recommended for award/negotiation subject to approvals."),"Evaluated - not highest ranked."))))
A16: =IF(LEN(B16)=0,"",IF(C16<>"Responsive","",IFERROR(1+COUNTIF($H$11:$H$30,">"&H16),""))) | B16: =IF(LEN('BIDDER REGISTER'!B12)=0,"",'BIDDER REGISTER'!B12) | C16: =IF(LEN(B16)=0,"",RESPONSIVENESS!J12) | D16: =IF(LEN(B16)=0,"",'TECHNICAL SCORING'!I12) | E16: =IF(LEN(B16)=0,"",'FINANCIAL CAPACITY'!AB12) | F16: =IF(LEN(B16)=0,"",'FINANCIAL CAPACITY'!AC12) | G16: =IF(LEN(B16)=0,"",'COMMERCIAL EVAL'!H12) | H16: =IF(LEN(B16)=0,"",IF(C16<>"Responsive",0,D16+F16+G16)) | I16: =IF(LEN(B16)=0,"",IF(C16<>"Responsive","Excluded - responsiveness",IF('TECHNICAL SCORING'!J12<>"Yes","Not technically qualified",IF(H16<'TENDER SETUP'!$B$15,"Below overall pass mark","Evaluated")))) | J16: =IF(LEN(B16)=0,"",IF(I16="Below overall pass mark","Do not recommend award under current scoring; below the stated overall pass mark.",IF(I16<>"Evaluated","Do not proceed unless rules allow correction/clarification.",IF(A16=1,IF(OR(E16="High Risk",E16="Stretched",E16="No Data",E16="Incomplete"),"Highest ranked, but financial capacity is "&E16&" — clarify or seek further evidence before recommending award.","Recommended for award/negotiation subject to approvals."),"Evaluated - not highest ranked."))))
A17: =IF(LEN(B17)=0,"",IF(C17<>"Responsive","",IFERROR(1+COUNTIF($H$11:$H$30,">"&H17),""))) | B17: =IF(LEN('BIDDER REGISTER'!B13)=0,"",'BIDDER REGISTER'!B13) | C17: =IF(LEN(B17)=0,"",RESPONSIVENESS!J13) | D17: =IF(LEN(B17)=0,"",'TECHNICAL SCORING'!I13) | E17: =IF(LEN(B17)=0,"",'FINANCIAL CAPACITY'!AB13) | F17: =IF(LEN(B17)=0,"",'FINANCIAL CAPACITY'!AC13) | G17: =IF(LEN(B17)=0,"",'COMMERCIAL EVAL'!H13) | H17: =IF(LEN(B17)=0,"",IF(C17<>"Responsive",0,D17+F17+G17)) | I17: =IF(LEN(B17)=0,"",IF(C17<>"Responsive","Excluded - responsiveness",IF('TECHNICAL SCORING'!J13<>"Yes","Not technically qualified",IF(H17<'TENDER SETUP'!$B$15,"Below overall pass mark","Evaluated")))) | J17: =IF(LEN(B17)=0,"",IF(I17="Below overall pass mark","Do not recommend award under current scoring; below the stated overall pass mark.",IF(I17<>"Evaluated","Do not proceed unless rules allow correction/clarification.",IF(A17=1,IF(OR(E17="High Risk",E17="Stretched",E17="No Data",E17="Incomplete"),"Highest ranked, but financial capacity is "&E17&" — clarify or seek further evidence before recommending award.","Recommended for award/negotiation subject to approvals."),"Evaluated - not highest ranked."))))
A18: =IF(LEN(B18)=0,"",IF(C18<>"Responsive","",IFERROR(1+COUNTIF($H$11:$H$30,">"&H18),""))) | B18: =IF(LEN('BIDDER REGISTER'!B14)=0,"",'BIDDER REGISTER'!B14) | C18: =IF(LEN(B18)=0,"",RESPONSIVENESS!J14) | D18: =IF(LEN(B18)=0,"",'TECHNICAL SCORING'!I14) | E18: =IF(LEN(B18)=0,"",'FINANCIAL CAPACITY'!AB14) | F18: =IF(LEN(B18)=0,"",'FINANCIAL CAPACITY'!AC14) | G18: =IF(LEN(B18)=0,"",'COMMERCIAL EVAL'!H14) | H18: =IF(LEN(B18)=0,"",IF(C18<>"Responsive",0,D18+F18+G18)) | I18: =IF(LEN(B18)=0,"",IF(C18<>"Responsive","Excluded - responsiveness",IF('TECHNICAL SCORING'!J14<>"Yes","Not technically qualified",IF(H18<'TENDER SETUP'!$B$15,"Below overall pass mark","Evaluated")))) | J18: =IF(LEN(B18)=0,"",IF(I18="Below overall pass mark","Do not recommend award under current scoring; below the stated overall pass mark.",IF(I18<>"Evaluated","Do not proceed unless rules allow correction/clarification.",IF(A18=1,IF(OR(E18="High Risk",E18="Stretched",E18="No Data",E18="Incomplete"),"Highest ranked, but financial capacity is "&E18&" — clarify or seek further evidence before recommending award.","Recommended for award/negotiation subject to approvals."),"Evaluated - not highest ranked."))))
A19: =IF(LEN(B19)=0,"",IF(C19<>"Responsive","",IFERROR(1+COUNTIF($H$11:$H$30,">"&H19),""))) | B19: =IF(LEN('BIDDER REGISTER'!B15)=0,"",'BIDDER REGISTER'!B15) | C19: =IF(LEN(B19)=0,"",RESPONSIVENESS!J15) | D19: =IF(LEN(B19)=0,"",'TECHNICAL SCORING'!I15) | E19: =IF(LEN(B19)=0,"",'FINANCIAL CAPACITY'!AB15) | F19: =IF(LEN(B19)=0,"",'FINANCIAL CAPACITY'!AC15) | G19: =IF(LEN(B19)=0,"",'COMMERCIAL EVAL'!H15) | H19: =IF(LEN(B19)=0,"",IF(C19<>"Responsive",0,D19+F19+G19)) | I19: =IF(LEN(B19)=0,"",IF(C19<>"Responsive","Excluded - responsiveness",IF('TECHNICAL SCORING'!J15<>"Yes","Not technically qualified",IF(H19<'TENDER SETUP'!$B$15,"Below overall pass mark","Evaluated")))) | J19: =IF(LEN(B19)=0,"",IF(I19="Below overall pass mark","Do not recommend award under current scoring; below the stated overall pass mark.",IF(I19<>"Evaluated","Do not proceed unless rules allow correction/clarification.",IF(A19=1,IF(OR(E19="High Risk",E19="Stretched",E19="No Data",E19="Incomplete"),"Highest ranked, but financial capacity is "&E19&" — clarify or seek further evidence before recommending award.","Recommended for award/negotiation subject to approvals."),"Evaluated - not highest ranked."))))
A20: =IF(LEN(B20)=0,"",IF(C20<>"Responsive","",IFERROR(1+COUNTIF($H$11:$H$30,">"&H20),""))) | B20: =IF(LEN('BIDDER REGISTER'!B16)=0,"",'BIDDER REGISTER'!B16) | C20: =IF(LEN(B20)=0,"",RESPONSIVENESS!J16) | D20: =IF(LEN(B20)=0,"",'TECHNICAL SCORING'!I16) | E20: =IF(LEN(B20)=0,"",'FINANCIAL CAPACITY'!AB16) | F20: =IF(LEN(B20)=0,"",'FINANCIAL CAPACITY'!AC16) | G20: =IF(LEN(B20)=0,"",'COMMERCIAL EVAL'!H16) | H20: =IF(LEN(B20)=0,"",IF(C20<>"Responsive",0,D20+F20+G20)) | I20: =IF(LEN(B20)=0,"",IF(C20<>"Responsive","Excluded - responsiveness",IF('TECHNICAL SCORING'!J16<>"Yes","Not technically qualified",IF(H20<'TENDER SETUP'!$B$15,"Below overall pass mark","Evaluated")))) | J20: =IF(LEN(B20)=0,"",IF(I20="Below overall pass mark","Do not recommend award under current scoring; below the stated overall pass mark.",IF(I20<>"Evaluated","Do not proceed unless rules allow correction/clarification.",IF(A20=1,IF(OR(E20="High Risk",E20="Stretched",E20="No Data",E20="Incomplete"),"Highest ranked, but financial capacity is "&E20&" — clarify or seek further evidence before recommending award.","Recommended for award/negotiation subject to approvals."),"Evaluated - not highest ranked."))))
A21: =IF(LEN(B21)=0,"",IF(C21<>"Responsive","",IFERROR(1+COUNTIF($H$11:$H$30,">"&H21),""))) | B21: =IF(LEN('BIDDER REGISTER'!B17)=0,"",'BIDDER REGISTER'!B17) | C21: =IF(LEN(B21)=0,"",RESPONSIVENESS!J17) | D21: =IF(LEN(B21)=0,"",'TECHNICAL SCORING'!I17) | E21: =IF(LEN(B21)=0,"",'FINANCIAL CAPACITY'!AB17) | F21: =IF(LEN(B21)=0,"",'FINANCIAL CAPACITY'!AC17) | G21: =IF(LEN(B21)=0,"",'COMMERCIAL EVAL'!H17) | H21: =IF(LEN(B21)=0,"",IF(C21<>"Responsive",0,D21+F21+G21)) | I21: =IF(LEN(B21)=0,"",IF(C21<>"Responsive","Excluded - responsiveness",IF('TECHNICAL SCORING'!J17<>"Yes","Not technically qualified",IF(H21<'TENDER SETUP'!$B$15,"Below overall pass mark","Evaluated")))) | J21: =IF(LEN(B21)=0,"",IF(I21="Below overall pass mark","Do not recommend award under current scoring; below the stated overall pass mark.",IF(I21<>"Evaluated","Do not proceed unless rules allow correction/clarification.",IF(A21=1,IF(OR(E21="High Risk",E21="Stretched",E21="No Data",E21="Incomplete"),"Highest ranked, but financial capacity is "&E21&" — clarify or seek further evidence before recommending award.","Recommended for award/negotiation subject to approvals."),"Evaluated - not highest ranked."))))
A22: =IF(LEN(B22)=0,"",IF(C22<>"Responsive","",IFERROR(1+COUNTIF($H$11:$H$30,">"&H22),""))) | B22: =IF(LEN('BIDDER REGISTER'!B18)=0,"",'BIDDER REGISTER'!B18) | C22: =IF(LEN(B22)=0,"",RESPONSIVENESS!J18) | D22: =IF(LEN(B22)=0,"",'TECHNICAL SCORING'!I18) | E22: =IF(LEN(B22)=0,"",'FINANCIAL CAPACITY'!AB18) | F22: =IF(LEN(B22)=0,"",'FINANCIAL CAPACITY'!AC18) | G22: =IF(LEN(B22)=0,"",'COMMERCIAL EVAL'!H18) | H22: =IF(LEN(B22)=0,"",IF(C22<>"Responsive",0,D22+F22+G22)) | I22: =IF(LEN(B22)=0,"",IF(C22<>"Responsive","Excluded - responsiveness",IF('TECHNICAL SCORING'!J18<>"Yes","Not technically qualified",IF(H22<'TENDER SETUP'!$B$15,"Below overall pass mark","Evaluated")))) | J22: =IF(LEN(B22)=0,"",IF(I22="Below overall pass mark","Do not recommend award under current scoring; below the stated overall pass mark.",IF(I22<>"Evaluated","Do not proceed unless rules allow correction/clarification.",IF(A22=1,IF(OR(E22="High Risk",E22="Stretched",E22="No Data",E22="Incomplete"),"Highest ranked, but financial capacity is "&E22&" — clarify or seek further evidence before recommending award.","Recommended for award/negotiation subject to approvals."),"Evaluated - not highest ranked."))))
... A30: =IF(LEN(B30)=0,"",IF(C30<>"Responsive","",IFERROR(1+COUNTIF($H$11:$H$30,">"&H30),""))) | B30: =IF(LEN('BIDDER REGISTER'!B26)=0,"",'BIDDER REGISTER'!B26) | C30: =IF(LEN(B30)=0,"",RESPONSIVENESS!J26) | D30: =IF(LEN(B30)=0,"",'TECHNICAL SCORING'!I26) | E30: =IF(LEN(B30)=0,"",'FINANCIAL CAPACITY'!AB26) | F30: =IF(LEN(B30)=0,"",'FINANCIAL CAPACITY'!AC26) | G30: =IF(LEN(B30)=0,"",'COMMERCIAL EVAL'!H26) | H30: =IF(LEN(B30)=0,"",IF(C30<>"Responsive",0,D30+F30+G30)) | I30: =IF(LEN(B30)=0,"",IF(C30<>"Responsive","Excluded - responsiveness",IF('TECHNICAL SCORING'!J26<>"Yes","Not technically qualified",IF(H30<'TENDER SETUP'!$B$15,"Below overall pass mark","Evaluated")))) | J30: =IF(LEN(B30)=0,"",IF(I30="Below overall pass mark","Do not recommend award under current scoring; below the stated overall pass mark.",IF(I30<>"Evaluated","Do not proceed unless rules allow correction/clarification.",IF(A30=1,IF(OR(E30="High Risk",E30="Stretched",E30="No Data",E30="Incomplete"),"Highest ranked, but financial capacity is "&E30&" — clarify or seek further evidence before recommending award.","Recommended for award/negotiation subject to approvals."),"Evaluated - not highest ranked."))))

Sheet REPORT BUILDER
A1: EVALUATION REPORT BUILDER
A2: This sheet drafts the report framework. Review and edit for final submission.
A4: ='TENDER SETUP'!B7 -> 0
A6: 1. INTRODUCTION
A7: ="This report documents the evaluation process for the tender titled "&'TENDER SETUP'!B7&" (procurement reference "&'TENDER SETUP'!B8&"), issued by "&'TENDER SETUP'!B5&IF('TENDER SETUP'!B6=""," "," (division/unit: "&'TENDER SETUP'!B6&") ")&"The evaluation was conducted in accordance with the criteria stated in the tender documents, the Public Procurement and Disposal of Public Property Act, 2015 (as amended), and Office of Procurement Regulation guidance." -> This report documents the evaluation process for the tender titled (procurement reference ), issued by Ministry of Defence The evaluation was conducted in accordance with the criteria stated in the tender documents, the Public Procurement and Disposal of Public Property Act, 2015 (as amended), and Office of Procurement Regulation guidance.
A9: 2. PROCUREMENT DETAILS
A10: ="Procurement method: "&'TENDER SETUP'!B9&". Tender type: "&'TENDER SETUP'!B10&IF('TENDER SETUP'!B11=""," ",". Line of business: "&'TENDER SETUP'!B11)&IF('TENDER SETUP'!B12="","",". Estimated value: TTD "&TEXT('TENDER SETUP'!B12,"#,##0"))&IF('TENDER SETUP'!B13="","",". Closing date: "&TEXT('TENDER SETUP'!B13,"dd mmm yyyy"))&". Overall pass mark: "&'TENDER SETUP'!B15&" out of 100. Minimum technical score: "&'TENDER SETUP'!B16&"." -> Procurement method: Open Tender. Tender type: Works / Refurbishment / Construction . Overall pass mark: 70 out of 100. Minimum technical score: 42.
A12: 3. EVALUATION METHODOLOGY
A13: The Committee applied the criteria fixed in the CRITERIA BUILDER before tender opening. Mandatory responsiveness was tested first on a pass/fail basis. Only responsive bidders proceeded to scored evaluation. Technical scoring was applied against the criteria and maximum points stated in the tender. Financial capacity was assessed using submitted financial statements and screened against sector-neutral bands. Commercial evaluation applied the stated price formula. Total scores were computed and ranked on the Dashboard.
A15: 4. MANDATORY RESPONSIVENESS
A16: ="Of "&COUNTIF('BIDDER REGISTER'!B7:B26,"?*")&" bidder(s) registered, the Committee recorded "&COUNTIF(RESPONSIVENESS!J7:J26,"Responsive")&" responsive, "&COUNTIF(RESPONSIVENESS!J7:J26,"Non-responsive")&" non-responsive, and "&COUNTIF(RESPONSIVENESS!J7:J26,"Incomplete")&" incomplete submission(s). Non-responsive and incomplete bidders were excluded from scored evaluation. Reasons are recorded on the RESPONSIVENESS tab and summarised at Section 9 below." -> Of 0 bidder(s) registered, the Committee recorded 0 responsive, 0 non-responsive, and 0 incomplete submission(s). Non-responsive and incomplete bidders were excluded from scored evaluation. Reasons are recorded on the RESPONSIVENESS tab and summarised at Section 9 below.
A18: 5. TECHNICAL EVALUATION SUMMARY
A19: =IF(COUNTIF('TECHNICAL SCORING'!B7:B26,"Responsive")=0,"No responsive bidders were available for technical scoring.","The Committee scored "&COUNTIF('TECHNICAL SCORING'!B7:B26,"Responsive")&" responsive bidder(s) across the stated technical criteria. Scored technical points available: "&('CRITERIA BUILDER'!C9+'CRITERIA BUILDER'!C10+'CRITERIA BUILDER'!C11+'CRITERIA BUILDER'!C12+'CRITERIA BUILDER'!C13+'CRITERIA BUILDER'!C16)&". Minimum technical threshold: "&'TENDER SETUP'!B16&". Bidders meeting the threshold: "&COUNTIF('TECHNICAL SCORING'!J7:J26,"Yes")&". Bidders below the threshold: "&COUNTIF('TECHNICAL SCORING'!J7:J26,"No")&". Bidders below the threshold cannot proceed to award.") -> No responsive bidders were available for technical scoring.
A21: 6. FINANCIAL CAPACITY SUMMARY
A22: =IF(COUNTIF('BIDDER REGISTER'!B7:B26,"?*")=0,"No financial capacity records were entered.","Financial capacity was screened for "&COUNTIF('BIDDER REGISTER'!B7:B26,"?*")&" bidder(s). Outcomes: Strong "&COUNTIF('FINANCIAL CAPACITY'!AB7:AB26,"Strong")&"; Adequate "&COUNTIF('FINANCIAL CAPACITY'!AB7:AB26,"Adequate")&"; Adequate with Caution "&COUNTIF('FINANCIAL CAPACITY'!AB7:AB26,"Adequate with Caution")&"; Stretched "&COUNTIF('FINANCIAL CAPACITY'!AB7:AB26,"Stretched")&"; High Risk "&COUNTIF('FINANCIAL CAPACITY'!AB7:AB26,"High Risk")&"; No Data or Incomplete "&(COUNTIF('FINANCIAL CAPACITY'!AB7:AB26,"No Data")+COUNTIF('FINANCIAL CAPACITY'!AB7:AB26,"Incomplete"))&". Bidders rated Stretched, High Risk, No Data or Incomplete require Committee clarification before award. Full ratios and per-bidder notes appear on the FINANCIAL CAPACITY tab.") -> No financial capacity records were entered.
A24: 7. COMMERCIAL EVALUATION SUMMARY
A25: =IF(COUNTIF('COMMERCIAL EVAL'!G7:G26,"Yes")=0,"No bidders were eligible for price scoring. Price scoring applies only to bidders that pass responsiveness and meet the minimum technical threshold.","Price scoring was applied to "&COUNTIF('COMMERCIAL EVAL'!G7:G26,"Yes")&" eligible bidder(s). Lowest evaluated responsive price (incl VAT): TTD "&TEXT(MIN('COMMERCIAL EVAL'!J7:J26),"#,##0")&". Highest evaluated responsive price: TTD "&TEXT(MAX('COMMERCIAL EVAL'!J7:J26),"#,##0")&". Price formula applied: "&'TENDER SETUP'!B17&". Individual price scores appear on the COMMERCIAL EVAL tab.") -> No bidders were eligible for price scoring. Price scoring applies only to bidders that pass responsiveness and meet the minimum technical threshold.
A27: 8. FINDINGS BY BIDDER
A28: Each bidder is summarised below with data drawn from the earlier tabs. The Committee should review each paragraph, add specific supporting evidence for manual technical scores, and edit as needed for the final report.
A29: =IF(LEN('BIDDER REGISTER'!B7)=0,"","• "&'BIDDER REGISTER'!B7&" — "&IF(RESPONSIVENESS!J7="Non-responsive","Non-responsive to mandatory requirements. Excluded from scored evaluation.",IF(RESPONSIVENESS!J7="Incomplete","Responsiveness assessment incomplete. Not evaluated for scoring until mandatory checks are completed.",IF(RESPONSIVENESS!J7="Responsive","Responsive to mandatory requirements. "&"Technical score: "&IF(ISNUMBER('TECHNICAL SCORING'!I7),'TECHNICAL SCORING'!I7,0)&" of "&('CRITERIA BUILDER'!C9+'CRITERIA BUILDER'!C10+'CRITERIA BUILDER'!C11+'CRITERIA BUILDER'!C12+'CRITERIA BUILDER'!C13+'CRITERIA BUILDER'!C16)&IF('TECHNICAL SCORING'!J7="Yes"," (meets minimum threshold). ",IF('TECHNICAL SCORING'!J7="No"," (below minimum threshold — cannot proceed to award). ",". "))&"Financial capacity screened as "&'FINANCIAL CAPACITY'!AB7&IF('FINANCIAL CAPACITY'!AB7="High Risk",". Committee should request clarification on the bidder's financial position, including any negative equity, accumulated losses, or debt service concerns, before proceeding. ",IF('FINANCIAL CAPACITY'!AB7="Stretched",". Financial position is tight; Committee should record specific concerns. ",IF('FINANCIAL CAPACITY'!AB7="No Data",". No financial statements or figures were entered. Committee should request evidence of financial capacity before proceeding. ",IF('FINANCIAL CAPACITY'!AB7="Incomplete",". Financial submission is incomplete. Committee should request the missing figures. ",". "))))&IF(AND(ISNUMBER('COMMERCIAL EVAL'!F7),'COMMERCIAL EVAL'!F7>0),"Evaluated price (incl VAT): TTD "&TEXT('COMMERCIAL EVAL'!F7,"#,##0")&". Price score: "&TEXT(IF(ISNUMBER('COMMERCIAL EVAL'!H7),'COMMERCIAL EVAL'!H7,0),"0.00")&" of "&'CRITERIA BUILDER'!C15&". ","Price not evaluated. ")&"Total: "&TEXT(IF(ISNUMBER(DASHBOARD!H11),DASHBOARD!H11,0),"0.00")&" of 100. "&IF(ISNUMBER(DASHBOARD!A11),"Rank: "&DASHBOARD!A11&". ","")&"Status: "&DASHBOARD!I11&"."&IF('TECHNICAL SCORING'!K7=""," [Committee to record specific evidence for manual technical scores.]"," Evaluator note: "&'TECHNICAL SCORING'!K7),"Responsiveness not yet recorded."))))
A30: =IF(LEN('BIDDER REGISTER'!B8)=0,"","• "&'BIDDER REGISTER'!B8&" — "&IF(RESPONSIVENESS!J8="Non-responsive","Non-responsive to mandatory requirements. Excluded from scored evaluation.",IF(RESPONSIVENESS!J8="Incomplete","Responsiveness assessment incomplete. Not evaluated for scoring until mandatory checks are completed.",IF(RESPONSIVENESS!J8="Responsive","Responsive to mandatory requirements. "&"Technical score: "&IF(ISNUMBER('TECHNICAL SCORING'!I8),'TECHNICAL SCORING'!I8,0)&" of "&('CRITERIA BUILDER'!C9+'CRITERIA BUILDER'!C10+'CRITERIA BUILDER'!C11+'CRITERIA BUILDER'!C12+'CRITERIA BUILDER'!C13+'CRITERIA BUILDER'!C16)&IF('TECHNICAL SCORING'!J8="Yes"," (meets minimum threshold). ",IF('TECHNICAL SCORING'!J8="No"," (below minimum threshold — cannot proceed to award). ",". "))&"Financial capacity screened as "&'FINANCIAL CAPACITY'!AB8&IF('FINANCIAL CAPACITY'!AB8="High Risk",". Committee should request clarification on the bidder's financial position, including any negative equity, accumulated losses, or debt service concerns, before proceeding. ",IF('FINANCIAL CAPACITY'!AB8="Stretched",". Financial position is tight; Committee should record specific concerns. ",IF('FINANCIAL CAPACITY'!AB8="No Data",". No financial statements or figures were entered. Committee should request evidence of financial capacity before proceeding. ",IF('FINANCIAL CAPACITY'!AB8="Incomplete",". Financial submission is incomplete. Committee should request the missing figures. ",". "))))&IF(AND(ISNUMBER('COMMERCIAL EVAL'!F8),'COMMERCIAL EVAL'!F8>0),"Evaluated price (incl VAT): TTD "&TEXT('COMMERCIAL EVAL'!F8,"#,##0")&". Price score: "&TEXT(IF(ISNUMBER('COMMERCIAL EVAL'!H8),'COMMERCIAL EVAL'!H8,0),"0.00")&" of "&'CRITERIA BUILDER'!C15&". ","Price not evaluated. ")&"Total: "&TEXT(IF(ISNUMBER(DASHBOARD!H12),DASHBOARD!H12,0),"0.00")&" of 100. "&IF(ISNUMBER(DASHBOARD!A12),"Rank: "&DASHBOARD!A12&". ","")&"Status: "&DASHBOARD!I12&"."&IF('TECHNICAL SCORING'!K8=""," [Committee to record specific evidence for manual technical scores.]"," Evaluator note: "&'TECHNICAL SCORING'!K8),"Responsiveness not yet recorded."))))
A31: =IF(LEN('BIDDER REGISTER'!B9)=0,"","• "&'BIDDER REGISTER'!B9&" — "&IF(RESPONSIVENESS!J9="Non-responsive","Non-responsive to mandatory requirements. Excluded from scored evaluation.",IF(RESPONSIVENESS!J9="Incomplete","Responsiveness assessment incomplete. Not evaluated for scoring until mandatory checks are completed.",IF(RESPONSIVENESS!J9="Responsive","Responsive to mandatory requirements. "&"Technical score: "&IF(ISNUMBER('TECHNICAL SCORING'!I9),'TECHNICAL SCORING'!I9,0)&" of "&('CRITERIA BUILDER'!C9+'CRITERIA BUILDER'!C10+'CRITERIA BUILDER'!C11+'CRITERIA BUILDER'!C12+'CRITERIA BUILDER'!C13+'CRITERIA BUILDER'!C16)&IF('TECHNICAL SCORING'!J9="Yes"," (meets minimum threshold). ",IF('TECHNICAL SCORING'!J9="No"," (below minimum threshold — cannot proceed to award). ",". "))&"Financial capacity screened as "&'FINANCIAL CAPACITY'!AB9&IF('FINANCIAL CAPACITY'!AB9="High Risk",". Committee should request clarification on the bidder's financial position, including any negative equity, accumulated losses, or debt service concerns, before proceeding. ",IF('FINANCIAL CAPACITY'!AB9="Stretched",". Financial position is tight; Committee should record specific concerns. ",IF('FINANCIAL CAPACITY'!AB9="No Data",". No financial statements or figures were entered. Committee should request evidence of financial capacity before proceeding. ",IF('FINANCIAL CAPACITY'!AB9="Incomplete",". Financial submission is incomplete. Committee should request the missing figures. ",". "))))&IF(AND(ISNUMBER('COMMERCIAL EVAL'!F9),'COMMERCIAL EVAL'!F9>0),"Evaluated price (incl VAT): TTD "&TEXT('COMMERCIAL EVAL'!F9,"#,##0")&". Price score: "&TEXT(IF(ISNUMBER('COMMERCIAL EVAL'!H9),'COMMERCIAL EVAL'!H9,0),"0.00")&" of "&'CRITERIA BUILDER'!C15&". ","Price not evaluated. ")&"Total: "&TEXT(IF(ISNUMBER(DASHBOARD!H13),DASHBOARD!H13,0),"0.00")&" of 100. "&IF(ISNUMBER(DASHBOARD!A13),"Rank: "&DASHBOARD!A13&". ","")&"Status: "&DASHBOARD!I13&"."&IF('TECHNICAL SCORING'!K9=""," [Committee to record specific evidence for manual technical scores.]"," Evaluator note: "&'TECHNICAL SCORING'!K9),"Responsiveness not yet recorded."))))
A32: =IF(LEN('BIDDER REGISTER'!B10)=0,"","• "&'BIDDER REGISTER'!B10&" — "&IF(RESPONSIVENESS!J10="Non-responsive","Non-responsive to mandatory requirements. Excluded from scored evaluation.",IF(RESPONSIVENESS!J10="Incomplete","Responsiveness assessment incomplete. Not evaluated for scoring until mandatory checks are completed.",IF(RESPONSIVENESS!J10="Responsive","Responsive to mandatory requirements. "&"Technical score: "&IF(ISNUMBER('TECHNICAL SCORING'!I10),'TECHNICAL SCORING'!I10,0)&" of "&('CRITERIA BUILDER'!C9+'CRITERIA BUILDER'!C10+'CRITERIA BUILDER'!C11+'CRITERIA BUILDER'!C12+'CRITERIA BUILDER'!C13+'CRITERIA BUILDER'!C16)&IF('TECHNICAL SCORING'!J10="Yes"," (meets minimum threshold). ",IF('TECHNICAL SCORING'!J10="No"," (below minimum threshold — cannot proceed to award). ",". "))&"Financial capacity screened as "&'FINANCIAL CAPACITY'!AB10&IF('FINANCIAL CAPACITY'!AB10="High Risk",". Committee should request clarification on the bidder's financial position, including any negative equity, accumulated losses, or debt service concerns, before proceeding. ",IF('FINANCIAL CAPACITY'!AB10="Stretched",". Financial position is tight; Committee should record specific concerns. ",IF('FINANCIAL CAPACITY'!AB10="No Data",". No financial statements or figures were entered. Committee should request evidence of financial capacity before proceeding. ",IF('FINANCIAL CAPACITY'!AB10="Incomplete",". Financial submission is incomplete. Committee should request the missing figures. ",". "))))&IF(AND(ISNUMBER('COMMERCIAL EVAL'!F10),'COMMERCIAL EVAL'!F10>0),"Evaluated price (incl VAT): TTD "&TEXT('COMMERCIAL EVAL'!F10,"#,##0")&". Price score: "&TEXT(IF(ISNUMBER('COMMERCIAL EVAL'!H10),'COMMERCIAL EVAL'!H10,0),"0.00")&" of "&'CRITERIA BUILDER'!C15&". ","Price not evaluated. ")&"Total: "&TEXT(IF(ISNUMBER(DASHBOARD!H14),DASHBOARD!H14,0),"0.00")&" of 100. "&IF(ISNUMBER(DASHBOARD!A14),"Rank: "&DASHBOARD!A14&". ","")&"Status: "&DASHBOARD!I14&"."&IF('TECHNICAL SCORING'!K10=""," [Committee to record specific evidence for manual technical scores.]"," Evaluator note: "&'TECHNICAL SCORING'!K10),"Responsiveness not yet recorded."))))
A33: =IF(LEN('BIDDER REGISTER'!B11)=0,"","• "&'BIDDER REGISTER'!B11&" — "&IF(RESPONSIVENESS!J11="Non-responsive","Non-responsive to mandatory requirements. Excluded from scored evaluation.",IF(RESPONSIVENESS!J11="Incomplete","Responsiveness assessment incomplete. Not evaluated for scoring until mandatory checks are completed.",IF(RESPONSIVENESS!J11="Responsive","Responsive to mandatory requirements. "&"Technical score: "&IF(ISNUMBER('TECHNICAL SCORING'!I11),'TECHNICAL SCORING'!I11,0)&" of "&('CRITERIA BUILDER'!C9+'CRITERIA BUILDER'!C10+'CRITERIA BUILDER'!C11+'CRITERIA BUILDER'!C12+'CRITERIA BUILDER'!C13+'CRITERIA BUILDER'!C16)&IF('TECHNICAL SCORING'!J11="Yes"," (meets minimum threshold). ",IF('TECHNICAL SCORING'!J11="No"," (below minimum threshold — cannot proceed to award). ",". "))&"Financial capacity screened as "&'FINANCIAL CAPACITY'!AB11&IF('FINANCIAL CAPACITY'!AB11="High Risk",". Committee should request clarification on the bidder's financial position, including any negative equity, accumulated losses, or debt service concerns, before proceeding. ",IF('FINANCIAL CAPACITY'!AB11="Stretched",". Financial position is tight; Committee should record specific concerns. ",IF('FINANCIAL CAPACITY'!AB11="No Data",". No financial statements or figures were entered. Committee should request evidence of financial capacity before proceeding. ",IF('FINANCIAL CAPACITY'!AB11="Incomplete",". Financial submission is incomplete. Committee should request the missing figures. ",". "))))&IF(AND(ISNUMBER('COMMERCIAL EVAL'!F11),'COMMERCIAL EVAL'!F11>0),"Evaluated price (incl VAT): TTD "&TEXT('COMMERCIAL EVAL'!F11,"#,##0")&". Price score: "&TEXT(IF(ISNUMBER('COMMERCIAL EVAL'!H11),'COMMERCIAL EVAL'!H11,0),"0.00")&" of "&'CRITERIA BUILDER'!C15&". ","Price not evaluated. ")&"Total: "&TEXT(IF(ISNUMBER(DASHBOARD!H15),DASHBOARD!H15,0),"0.00")&" of 100. "&IF(ISNUMBER(DASHBOARD!A15),"Rank: "&DASHBOARD!A15&". ","")&"Status: "&DASHBOARD!I15&"."&IF('TECHNICAL SCORING'!K11=""," [Committee to record specific evidence for manual technical scores.]"," Evaluator note: "&'TECHNICAL SCORING'!K11),"Responsiveness not yet recorded."))))
A34: =IF(LEN('BIDDER REGISTER'!B12)=0,"","• "&'BIDDER REGISTER'!B12&" — "&IF(RESPONSIVENESS!J12="Non-responsive","Non-responsive to mandatory requirements. Excluded from scored evaluation.",IF(RESPONSIVENESS!J12="Incomplete","Responsiveness assessment incomplete. Not evaluated for scoring until mandatory checks are completed.",IF(RESPONSIVENESS!J12="Responsive","Responsive to mandatory requirements. "&"Technical score: "&IF(ISNUMBER('TECHNICAL SCORING'!I12),'TECHNICAL SCORING'!I12,0)&" of "&('CRITERIA BUILDER'!C9+'CRITERIA BUILDER'!C10+'CRITERIA BUILDER'!C11+'CRITERIA BUILDER'!C12+'CRITERIA BUILDER'!C13+'CRITERIA BUILDER'!C16)&IF('TECHNICAL SCORING'!J12="Yes"," (meets minimum threshold). ",IF('TECHNICAL SCORING'!J12="No"," (below minimum threshold — cannot proceed to award). ",". "))&"Financial capacity screened as "&'FINANCIAL CAPACITY'!AB12&IF('FINANCIAL CAPACITY'!AB12="High Risk",". Committee should request clarification on the bidder's financial position, including any negative equity, accumulated losses, or debt service concerns, before proceeding. ",IF('FINANCIAL CAPACITY'!AB12="Stretched",". Financial position is tight; Committee should record specific concerns. ",IF('FINANCIAL CAPACITY'!AB12="No Data",". No financial statements or figures were entered. Committee should request evidence of financial capacity before proceeding. ",IF('FINANCIAL CAPACITY'!AB12="Incomplete",". Financial submission is incomplete. Committee should request the missing figures. ",". "))))&IF(AND(ISNUMBER('COMMERCIAL EVAL'!F12),'COMMERCIAL EVAL'!F12>0),"Evaluated price (incl VAT): TTD "&TEXT('COMMERCIAL EVAL'!F12,"#,##0")&". Price score: "&TEXT(IF(ISNUMBER('COMMERCIAL EVAL'!H12),'COMMERCIAL EVAL'!H12,0),"0.00")&" of "&'CRITERIA BUILDER'!C15&". ","Price not evaluated. ")&"Total: "&TEXT(IF(ISNUMBER(DASHBOARD!H16),DASHBOARD!H16,0),"0.00")&" of 100. "&IF(ISNUMBER(DASHBOARD!A16),"Rank: "&DASHBOARD!A16&". ","")&"Status: "&DASHBOARD!I16&"."&IF('TECHNICAL SCORING'!K12=""," [Committee to record specific evidence for manual technical scores.]"," Evaluator note: "&'TECHNICAL SCORING'!K12),"Responsiveness not yet recorded."))))
A35: =IF(LEN('BIDDER REGISTER'!B13)=0,"","• "&'BIDDER REGISTER'!B13&" — "&IF(RESPONSIVENESS!J13="Non-responsive","Non-responsive to mandatory requirements. Excluded from scored evaluation.",IF(RESPONSIVENESS!J13="Incomplete","Responsiveness assessment incomplete. Not evaluated for scoring until mandatory checks are completed.",IF(RESPONSIVENESS!J13="Responsive","Responsive to mandatory requirements. "&"Technical score: "&IF(ISNUMBER('TECHNICAL SCORING'!I13),'TECHNICAL SCORING'!I13,0)&" of "&('CRITERIA BUILDER'!C9+'CRITERIA BUILDER'!C10+'CRITERIA BUILDER'!C11+'CRITERIA BUILDER'!C12+'CRITERIA BUILDER'!C13+'CRITERIA BUILDER'!C16)&IF('TECHNICAL SCORING'!J13="Yes"," (meets minimum threshold). ",IF('TECHNICAL SCORING'!J13="No"," (below minimum threshold — cannot proceed to award). ",". "))&"Financial capacity screened as "&'FINANCIAL CAPACITY'!AB13&IF('FINANCIAL CAPACITY'!AB13="High Risk",". Committee should request clarification on the bidder's financial position, including any negative equity, accumulated losses, or debt service concerns, before proceeding. ",IF('FINANCIAL CAPACITY'!AB13="Stretched",". Financial position is tight; Committee should record specific concerns. ",IF('FINANCIAL CAPACITY'!AB13="No Data",". No financial statements or figures were entered. Committee should request evidence of financial capacity before proceeding. ",IF('FINANCIAL CAPACITY'!AB13="Incomplete",". Financial submission is incomplete. Committee should request the missing figures. ",". "))))&IF(AND(ISNUMBER('COMMERCIAL EVAL'!F13),'COMMERCIAL EVAL'!F13>0),"Evaluated price (incl VAT): TTD "&TEXT('COMMERCIAL EVAL'!F13,"#,##0")&". Price score: "&TEXT(IF(ISNUMBER('COMMERCIAL EVAL'!H13),'COMMERCIAL EVAL'!H13,0),"0.00")&" of "&'CRITERIA BUILDER'!C15&". ","Price not evaluated. ")&"Total: "&TEXT(IF(ISNUMBER(DASHBOARD!H17),DASHBOARD!H17,0),"0.00")&" of 100. "&IF(ISNUMBER(DASHBOARD!A17),"Rank: "&DASHBOARD!A17&". ","")&"Status: "&DASHBOARD!I17&"."&IF('TECHNICAL SCORING'!K13=""," [Committee to record specific evidence for manual technical scores.]"," Evaluator note: "&'TECHNICAL SCORING'!K13),"Responsiveness not yet recorded."))))
A36: =IF(LEN('BIDDER REGISTER'!B14)=0,"","• "&'BIDDER REGISTER'!B14&" — "&IF(RESPONSIVENESS!J14="Non-responsive","Non-responsive to mandatory requirements. Excluded from scored evaluation.",IF(RESPONSIVENESS!J14="Incomplete","Responsiveness assessment incomplete. Not evaluated for scoring until mandatory checks are completed.",IF(RESPONSIVENESS!J14="Responsive","Responsive to mandatory requirements. "&"Technical score: "&IF(ISNUMBER('TECHNICAL SCORING'!I14),'TECHNICAL SCORING'!I14,0)&" of "&('CRITERIA BUILDER'!C9+'CRITERIA BUILDER'!C10+'CRITERIA BUILDER'!C11+'CRITERIA BUILDER'!C12+'CRITERIA BUILDER'!C13+'CRITERIA BUILDER'!C16)&IF('TECHNICAL SCORING'!J14="Yes"," (meets minimum threshold). ",IF('TECHNICAL SCORING'!J14="No"," (below minimum threshold — cannot proceed to award). ",". "))&"Financial capacity screened as "&'FINANCIAL CAPACITY'!AB14&IF('FINANCIAL CAPACITY'!AB14="High Risk",". Committee should request clarification on the bidder's financial position, including any negative equity, accumulated losses, or debt service concerns, before proceeding. ",IF('FINANCIAL CAPACITY'!AB14="Stretched",". Financial position is tight; Committee should record specific concerns. ",IF('FINANCIAL CAPACITY'!AB14="No Data",". No financial statements or figures were entered. Committee should request evidence of financial capacity before proceeding. ",IF('FINANCIAL CAPACITY'!AB14="Incomplete",". Financial submission is incomplete. Committee should request the missing figures. ",". "))))&IF(AND(ISNUMBER('COMMERCIAL EVAL'!F14),'COMMERCIAL EVAL'!F14>0),"Evaluated price (incl VAT): TTD "&TEXT('COMMERCIAL EVAL'!F14,"#,##0")&". Price score: "&TEXT(IF(ISNUMBER('COMMERCIAL EVAL'!H14),'COMMERCIAL EVAL'!H14,0),"0.00")&" of "&'CRITERIA BUILDER'!C15&". ","Price not evaluated. ")&"Total: "&TEXT(IF(ISNUMBER(DASHBOARD!H18),DASHBOARD!H18,0),"0.00")&" of 100. "&IF(ISNUMBER(DASHBOARD!A18),"Rank: "&DASHBOARD!A18&". ","")&"Status: "&DASHBOARD!I18&"."&IF('TECHNICAL SCORING'!K14=""," [Committee to record specific evidence for manual technical scores.]"," Evaluator note: "&'TECHNICAL SCORING'!K14),"Responsiveness not yet recorded."))))
A37: =IF(LEN('BIDDER REGISTER'!B15)=0,"","• "&'BIDDER REGISTER'!B15&" — "&IF(RESPONSIVENESS!J15="Non-responsive","Non-responsive to mandatory requirements. Excluded from scored evaluation.",IF(RESPONSIVENESS!J15="Incomplete","Responsiveness assessment incomplete. Not evaluated for scoring until mandatory checks are completed.",IF(RESPONSIVENESS!J15="Responsive","Responsive to mandatory requirements. "&"Technical score: "&IF(ISNUMBER('TECHNICAL SCORING'!I15),'TECHNICAL SCORING'!I15,0)&" of "&('CRITERIA BUILDER'!C9+'CRITERIA BUILDER'!C10+'CRITERIA BUILDER'!C11+'CRITERIA BUILDER'!C12+'CRITERIA BUILDER'!C13+'CRITERIA BUILDER'!C16)&IF('TECHNICAL SCORING'!J15="Yes"," (meets minimum threshold). ",IF('TECHNICAL SCORING'!J15="No"," (below minimum threshold — cannot proceed to award). ",". "))&"Financial capacity screened as "&'FINANCIAL CAPACITY'!AB15&IF('FINANCIAL CAPACITY'!AB15="High Risk",". Committee should request clarification on the bidder's financial position, including any negative equity, accumulated losses, or debt service concerns, before proceeding. ",IF('FINANCIAL CAPACITY'!AB15="Stretched",". Financial position is tight; Committee should record specific concerns. ",IF('FINANCIAL CAPACITY'!AB15="No Data",". No financial statements or figures were entered. Committee should request evidence of financial capacity before proceeding. ",IF('FINANCIAL CAPACITY'!AB15="Incomplete",". Financial submission is incomplete. Committee should request the missing figures. ",". "))))&IF(AND(ISNUMBER('COMMERCIAL EVAL'!F15),'COMMERCIAL EVAL'!F15>0),"Evaluated price (incl VAT): TTD "&TEXT('COMMERCIAL EVAL'!F15,"#,##0")&". Price score: "&TEXT(IF(ISNUMBER('COMMERCIAL EVAL'!H15),'COMMERCIAL EVAL'!H15,0),"0.00")&" of "&'CRITERIA BUILDER'!C15&". ","Price not evaluated. ")&"Total: "&TEXT(IF(ISNUMBER(DASHBOARD!H19),DASHBOARD!H19,0),"0.00")&" of 100. "&IF(ISNUMBER(DASHBOARD!A19),"Rank: "&DASHBOARD!A19&". ","")&"Status: "&DASHBOARD!I19&"."&IF('TECHNICAL SCORING'!K15=""," [Committee to record specific evidence for manual technical scores.]"," Evaluator note: "&'TECHNICAL SCORING'!K15),"Responsiveness not yet recorded."))))
A38: =IF(LEN('BIDDER REGISTER'!B16)=0,"","• "&'BIDDER REGISTER'!B16&" — "&IF(RESPONSIVENESS!J16="Non-responsive","Non-responsive to mandatory requirements. Excluded from scored evaluation.",IF(RESPONSIVENESS!J16="Incomplete","Responsiveness assessment incomplete. Not evaluated for scoring until mandatory checks are completed.",IF(RESPONSIVENESS!J16="Responsive","Responsive to mandatory requirements. "&"Technical score: "&IF(ISNUMBER('TECHNICAL SCORING'!I16),'TECHNICAL SCORING'!I16,0)&" of "&('CRITERIA BUILDER'!C9+'CRITERIA BUILDER'!C10+'CRITERIA BUILDER'!C11+'CRITERIA BUILDER'!C12+'CRITERIA BUILDER'!C13+'CRITERIA BUILDER'!C16)&IF('TECHNICAL SCORING'!J16="Yes"," (meets minimum threshold). ",IF('TECHNICAL SCORING'!J16="No"," (below minimum threshold — cannot proceed to award). ",". "))&"Financial capacity screened as "&'FINANCIAL CAPACITY'!AB16&IF('FINANCIAL CAPACITY'!AB16="High Risk",". Committee should request clarification on the bidder's financial position, including any negative equity, accumulated losses, or debt service concerns, before proceeding. ",IF('FINANCIAL CAPACITY'!AB16="Stretched",". Financial position is tight; Committee should record specific concerns. ",IF('FINANCIAL CAPACITY'!AB16="No Data",". No financial statements or figures were entered. Committee should request evidence of financial capacity before proceeding. ",IF('FINANCIAL CAPACITY'!AB16="Incomplete",". Financial submission is incomplete. Committee should request the missing figures. ",". "))))&IF(AND(ISNUMBER('COMMERCIAL EVAL'!F16),'COMMERCIAL EVAL'!F16>0),"Evaluated price (incl VAT): TTD "&TEXT('COMMERCIAL EVAL'!F16,"#,##0")&". Price score: "&TEXT(IF(ISNUMBER('COMMERCIAL EVAL'!H16),'COMMERCIAL EVAL'!H16,0),"0.00")&" of "&'CRITERIA BUILDER'!C15&". ","Price not evaluated. ")&"Total: "&TEXT(IF(ISNUMBER(DASHBOARD!H20),DASHBOARD!H20,0),"0.00")&" of 100. "&IF(ISNUMBER(DASHBOARD!A20),"Rank: "&DASHBOARD!A20&". ","")&"Status: "&DASHBOARD!I20&"."&IF('TECHNICAL SCORING'!K16=""," [Committee to record specific evidence for manual technical scores.]"," Evaluator note: "&'TECHNICAL SCORING'!K16),"Responsiveness not yet recorded."))))
A39: =IF(LEN('BIDDER REGISTER'!B17)=0,"","• "&'BIDDER REGISTER'!B17&" — "&IF(RESPONSIVENESS!J17="Non-responsive","Non-responsive to mandatory requirements. Excluded from scored evaluation.",IF(RESPONSIVENESS!J17="Incomplete","Responsiveness assessment incomplete. Not evaluated for scoring until mandatory checks are completed.",IF(RESPONSIVENESS!J17="Responsive","Responsive to mandatory requirements. "&"Technical score: "&IF(ISNUMBER('TECHNICAL SCORING'!I17),'TECHNICAL SCORING'!I17,0)&" of "&('CRITERIA BUILDER'!C9+'CRITERIA BUILDER'!C10+'CRITERIA BUILDER'!C11+'CRITERIA BUILDER'!C12+'CRITERIA BUILDER'!C13+'CRITERIA BUILDER'!C16)&IF('TECHNICAL SCORING'!J17="Yes"," (meets minimum threshold). ",IF('TECHNICAL SCORING'!J17="No"," (below minimum threshold — cannot proceed to award). ",". "))&"Financial capacity screened as "&'FINANCIAL CAPACITY'!AB17&IF('FINANCIAL CAPACITY'!AB17="High Risk",". Committee should request clarification on the bidder's financial position, including any negative equity, accumulated losses, or debt service concerns, before proceeding. ",IF('FINANCIAL CAPACITY'!AB17="Stretched",". Financial position is tight; Committee should record specific concerns. ",IF('FINANCIAL CAPACITY'!AB17="No Data",". No financial statements or figures were entered. Committee should request evidence of financial capacity before proceeding. ",IF('FINANCIAL CAPACITY'!AB17="Incomplete",". Financial submission is incomplete. Committee should request the missing figures. ",". "))))&IF(AND(ISNUMBER('COMMERCIAL EVAL'!F17),'COMMERCIAL EVAL'!F17>0),"Evaluated price (incl VAT): TTD "&TEXT('COMMERCIAL EVAL'!F17,"#,##0")&". Price score: "&TEXT(IF(ISNUMBER('COMMERCIAL EVAL'!H17),'COMMERCIAL EVAL'!H17,0),"0.00")&" of "&'CRITERIA BUILDER'!C15&". ","Price not evaluated. ")&"Total: "&TEXT(IF(ISNUMBER(DASHBOARD!H21),DASHBOARD!H21,0),"0.00")&" of 100. "&IF(ISNUMBER(DASHBOARD!A21),"Rank: "&DASHBOARD!A21&". ","")&"Status: "&DASHBOARD!I21&"."&IF('TECHNICAL SCORING'!K17=""," [Committee to record specific evidence for manual technical scores.]"," Evaluator note: "&'TECHNICAL SCORING'!K17),"Responsiveness not yet recorded."))))
A40: =IF(LEN('BIDDER REGISTER'!B18)=0,"","• "&'BIDDER REGISTER'!B18&" — "&IF(RESPONSIVENESS!J18="Non-responsive","Non-responsive to mandatory requirements. Excluded from scored evaluation.",IF(RESPONSIVENESS!J18="Incomplete","Responsiveness assessment incomplete. Not evaluated for scoring until mandatory checks are completed.",IF(RESPONSIVENESS!J18="Responsive","Responsive to mandatory requirements. "&"Technical score: "&IF(ISNUMBER('TECHNICAL SCORING'!I18),'TECHNICAL SCORING'!I18,0)&" of "&('CRITERIA BUILDER'!C9+'CRITERIA BUILDER'!C10+'CRITERIA BUILDER'!C11+'CRITERIA BUILDER'!C12+'CRITERIA BUILDER'!C13+'CRITERIA BUILDER'!C16)&IF('TECHNICAL SCORING'!J18="Yes"," (meets minimum threshold). ",IF('TECHNICAL SCORING'!J18="No"," (below minimum threshold — cannot proceed to award). ",". "))&"Financial capacity screened as "&'FINANCIAL CAPACITY'!AB18&IF('FINANCIAL CAPACITY'!AB18="High Risk",". Committee should request clarification on the bidder's financial position, including any negative equity, accumulated losses, or debt service concerns, before proceeding. ",IF('FINANCIAL CAPACITY'!AB18="Stretched",". Financial position is tight; Committee should record specific concerns. ",IF('FINANCIAL CAPACITY'!AB18="No Data",". No financial statements or figures were entered. Committee should request evidence of financial capacity before proceeding. ",IF('FINANCIAL CAPACITY'!AB18="Incomplete",". Financial submission is incomplete. Committee should request the missing figures. ",". "))))&IF(AND(ISNUMBER('COMMERCIAL EVAL'!F18),'COMMERCIAL EVAL'!F18>0),"Evaluated price (incl VAT): TTD "&TEXT('COMMERCIAL EVAL'!F18,"#,##0")&". Price score: "&TEXT(IF(ISNUMBER('COMMERCIAL EVAL'!H18),'COMMERCIAL EVAL'!H18,0),"0.00")&" of "&'CRITERIA BUILDER'!C15&". ","Price not evaluated. ")&"Total: "&TEXT(IF(ISNUMBER(DASHBOARD!H22),DASHBOARD!H22,0),"0.00")&" of 100. "&IF(ISNUMBER(DASHBOARD!A22),"Rank: "&DASHBOARD!A22&". ","")&"Status: "&DASHBOARD!I22&"."&IF('TECHNICAL SCORING'!K18=""," [Committee to record specific evidence for manual technical scores.]"," Evaluator note: "&'TECHNICAL SCORING'!K18),"Responsiveness not yet recorded."))))
A41: =IF(LEN('BIDDER REGISTER'!B19)=0,"","• "&'BIDDER REGISTER'!B19&" — "&IF(RESPONSIVENESS!J19="Non-responsive","Non-responsive to mandatory requirements. Excluded from scored evaluation.",IF(RESPONSIVENESS!J19="Incomplete","Responsiveness assessment incomplete. Not evaluated for scoring until mandatory checks are completed.",IF(RESPONSIVENESS!J19="Responsive","Responsive to mandatory requirements. "&"Technical score: "&IF(ISNUMBER('TECHNICAL SCORING'!I19),'TECHNICAL SCORING'!I19,0)&" of "&('CRITERIA BUILDER'!C9+'CRITERIA BUILDER'!C10+'CRITERIA BUILDER'!C11+'CRITERIA BUILDER'!C12+'CRITERIA BUILDER'!C13+'CRITERIA BUILDER'!C16)&IF('TECHNICAL SCORING'!J19="Yes"," (meets minimum threshold). ",IF('TECHNICAL SCORING'!J19="No"," (below minimum threshold — cannot proceed to award). ",". "))&"Financial capacity screened as "&'FINANCIAL CAPACITY'!AB19&IF('FINANCIAL CAPACITY'!AB19="High Risk",". Committee should request clarification on the bidder's financial position, including any negative equity, accumulated losses, or debt service concerns, before proceeding. ",IF('FINANCIAL CAPACITY'!AB19="Stretched",". Financial position is tight; Committee should record specific concerns. ",IF('FINANCIAL CAPACITY'!AB19="No Data",". No financial statements or figures were entered. Committee should request evidence of financial capacity before proceeding. ",IF('FINANCIAL CAPACITY'!AB19="Incomplete",". Financial submission is incomplete. Committee should request the missing figures. ",". "))))&IF(AND(ISNUMBER('COMMERCIAL EVAL'!F19),'COMMERCIAL EVAL'!F19>0),"Evaluated price (incl VAT): TTD "&TEXT('COMMERCIAL EVAL'!F19,"#,##0")&". Price score: "&TEXT(IF(ISNUMBER('COMMERCIAL EVAL'!H19),'COMMERCIAL EVAL'!H19,0),"0.00")&" of "&'CRITERIA BUILDER'!C15&". ","Price not evaluated. ")&"Total: "&TEXT(IF(ISNUMBER(DASHBOARD!H23),DASHBOARD!H23,0),"0.00")&" of 100. "&IF(ISNUMBER(DASHBOARD!A23),"Rank: "&DASHBOARD!A23&". ","")&"Status: "&DASHBOARD!I23&"."&IF('TECHNICAL SCORING'!K19=""," [Committee to record specific evidence for manual technical scores.]"," Evaluator note: "&'TECHNICAL SCORING'!K19),"Responsiveness not yet recorded."))))
A42: =IF(LEN('BIDDER REGISTER'!B20)=0,"","• "&'BIDDER REGISTER'!B20&" — "&IF(RESPONSIVENESS!J20="Non-responsive","Non-responsive to mandatory requirements. Excluded from scored evaluation.",IF(RESPONSIVENESS!J20="Incomplete","Responsiveness assessment incomplete. Not evaluated for scoring until mandatory checks are completed.",IF(RESPONSIVENESS!J20="Responsive","Responsive to mandatory requirements. "&"Technical score: "&IF(ISNUMBER('TECHNICAL SCORING'!I20),'TECHNICAL SCORING'!I20,0)&" of "&('CRITERIA BUILDER'!C9+'CRITERIA BUILDER'!C10+'CRITERIA BUILDER'!C11+'CRITERIA BUILDER'!C12+'CRITERIA BUILDER'!C13+'CRITERIA BUILDER'!C16)&IF('TECHNICAL SCORING'!J20="Yes"," (meets minimum threshold). ",IF('TECHNICAL SCORING'!J20="No"," (below minimum threshold — cannot proceed to award). ",". "))&"Financial capacity screened as "&'FINANCIAL CAPACITY'!AB20&IF('FINANCIAL CAPACITY'!AB20="High Risk",". Committee should request clarification on the bidder's financial position, including any negative equity, accumulated losses, or debt service concerns, before proceeding. ",IF('FINANCIAL CAPACITY'!AB20="Stretched",". Financial position is tight; Committee should record specific concerns. ",IF('FINANCIAL CAPACITY'!AB20="No Data",". No financial statements or figures were entered. Committee should request evidence of financial capacity before proceeding. ",IF('FINANCIAL CAPACITY'!AB20="Incomplete",". Financial submission is incomplete. Committee should request the missing figures. ",". "))))&IF(AND(ISNUMBER('COMMERCIAL EVAL'!F20),'COMMERCIAL EVAL'!F20>0),"Evaluated price (incl VAT): TTD "&TEXT('COMMERCIAL EVAL'!F20,"#,##0")&". Price score: "&TEXT(IF(ISNUMBER('COMMERCIAL EVAL'!H20),'COMMERCIAL EVAL'!H20,0),"0.00")&" of "&'CRITERIA BUILDER'!C15&". ","Price not evaluated. ")&"Total: "&TEXT(IF(ISNUMBER(DASHBOARD!H24),DASHBOARD!H24,0),"0.00")&" of 100. "&IF(ISNUMBER(DASHBOARD!A24),"Rank: "&DASHBOARD!A24&". ","")&"Status: "&DASHBOARD!I24&"."&IF('TECHNICAL SCORING'!K20=""," [Committee to record specific evidence for manual technical scores.]"," Evaluator note: "&'TECHNICAL SCORING'!K20),"Responsiveness not yet recorded."))))
A43: =IF(LEN('BIDDER REGISTER'!B21)=0,"","• "&'BIDDER REGISTER'!B21&" — "&IF(RESPONSIVENESS!J21="Non-responsive","Non-responsive to mandatory requirements. Excluded from scored evaluation.",IF(RESPONSIVENESS!J21="Incomplete","Responsiveness assessment incomplete. Not evaluated for scoring until mandatory checks are completed.",IF(RESPONSIVENESS!J21="Responsive","Responsive to mandatory requirements. "&"Technical score: "&IF(ISNUMBER('TECHNICAL SCORING'!I21),'TECHNICAL SCORING'!I21,0)&" of "&('CRITERIA BUILDER'!C9+'CRITERIA BUILDER'!C10+'CRITERIA BUILDER'!C11+'CRITERIA BUILDER'!C12+'CRITERIA BUILDER'!C13+'CRITERIA BUILDER'!C16)&IF('TECHNICAL SCORING'!J21="Yes"," (meets minimum threshold). ",IF('TECHNICAL SCORING'!J21="No"," (below minimum threshold — cannot proceed to award). ",". "))&"Financial capacity screened as "&'FINANCIAL CAPACITY'!AB21&IF('FINANCIAL CAPACITY'!AB21="High Risk",". Committee should request clarification on the bidder's financial position, including any negative equity, accumulated losses, or debt service concerns, before proceeding. ",IF('FINANCIAL CAPACITY'!AB21="Stretched",". Financial position is tight; Committee should record specific concerns. ",IF('FINANCIAL CAPACITY'!AB21="No Data",". No financial statements or figures were entered. Committee should request evidence of financial capacity before proceeding. ",IF('FINANCIAL CAPACITY'!AB21="Incomplete",". Financial submission is incomplete. Committee should request the missing figures. ",". "))))&IF(AND(ISNUMBER('COMMERCIAL EVAL'!F21),'COMMERCIAL EVAL'!F21>0),"Evaluated price (incl VAT): TTD "&TEXT('COMMERCIAL EVAL'!F21,"#,##0")&". Price score: "&TEXT(IF(ISNUMBER('COMMERCIAL EVAL'!H21),'COMMERCIAL EVAL'!H21,0),"0.00")&" of "&'CRITERIA BUILDER'!C15&". ","Price not evaluated. ")&"Total: "&TEXT(IF(ISNUMBER(DASHBOARD!H25),DASHBOARD!H25,0),"0.00")&" of 100. "&IF(ISNUMBER(DASHBOARD!A25),"Rank: "&DASHBOARD!A25&". ","")&"Status: "&DASHBOARD!I25&"."&IF('TECHNICAL SCORING'!K21=""," [Committee to record specific evidence for manual technical scores.]"," Evaluator note: "&'TECHNICAL SCORING'!K21),"Responsiveness not yet recorded."))))
A44: =IF(LEN('BIDDER REGISTER'!B22)=0,"","• "&'BIDDER REGISTER'!B22&" — "&IF(RESPONSIVENESS!J22="Non-responsive","Non-responsive to mandatory requirements. Excluded from scored evaluation.",IF(RESPONSIVENESS!J22="Incomplete","Responsiveness assessment incomplete. Not evaluated for scoring until mandatory checks are completed.",IF(RESPONSIVENESS!J22="Responsive","Responsive to mandatory requirements. "&"Technical score: "&IF(ISNUMBER('TECHNICAL SCORING'!I22),'TECHNICAL SCORING'!I22,0)&" of "&('CRITERIA BUILDER'!C9+'CRITERIA BUILDER'!C10+'CRITERIA BUILDER'!C11+'CRITERIA BUILDER'!C12+'CRITERIA BUILDER'!C13+'CRITERIA BUILDER'!C16)&IF('TECHNICAL SCORING'!J22="Yes"," (meets minimum threshold). ",IF('TECHNICAL SCORING'!J22="No"," (below minimum threshold — cannot proceed to award). ",". "))&"Financial capacity screened as "&'FINANCIAL CAPACITY'!AB22&IF('FINANCIAL CAPACITY'!AB22="High Risk",". Committee should request clarification on the bidder's financial position, including any negative equity, accumulated losses, or debt service concerns, before proceeding. ",IF('FINANCIAL CAPACITY'!AB22="Stretched",". Financial position is tight; Committee should record specific concerns. ",IF('FINANCIAL CAPACITY'!AB22="No Data",". No financial statements or figures were entered. Committee should request evidence of financial capacity before proceeding. ",IF('FINANCIAL CAPACITY'!AB22="Incomplete",". Financial submission is incomplete. Committee should request the missing figures. ",". "))))&IF(AND(ISNUMBER('COMMERCIAL EVAL'!F22),'COMMERCIAL EVAL'!F22>0),"Evaluated price (incl VAT): TTD "&TEXT('COMMERCIAL EVAL'!F22,"#,##0")&". Price score: "&TEXT(IF(ISNUMBER('COMMERCIAL EVAL'!H22),'COMMERCIAL EVAL'!H22,0),"0.00")&" of "&'CRITERIA BUILDER'!C15&". ","Price not evaluated. ")&"Total: "&TEXT(IF(ISNUMBER(DASHBOARD!H26),DASHBOARD!H26,0),"0.00")&" of 100. "&IF(ISNUMBER(DASHBOARD!A26),"Rank: "&DASHBOARD!A26&". ","")&"Status: "&DASHBOARD!I26&"."&IF('TECHNICAL SCORING'!K22=""," [Committee to record specific evidence for manual technical scores.]"," Evaluator note: "&'TECHNICAL SCORING'!K22),"Responsiveness not yet recorded."))))
A45: =IF(LEN('BIDDER REGISTER'!B23)=0,"","• "&'BIDDER REGISTER'!B23&" — "&IF(RESPONSIVENESS!J23="Non-responsive","Non-responsive to mandatory requirements. Excluded from scored evaluation.",IF(RESPONSIVENESS!J23="Incomplete","Responsiveness assessment incomplete. Not evaluated for scoring until mandatory checks are completed.",IF(RESPONSIVENESS!J23="Responsive","Responsive to mandatory requirements. "&"Technical score: "&IF(ISNUMBER('TECHNICAL SCORING'!I23),'TECHNICAL SCORING'!I23,0)&" of "&('CRITERIA BUILDER'!C9+'CRITERIA BUILDER'!C10+'CRITERIA BUILDER'!C11+'CRITERIA BUILDER'!C12+'CRITERIA BUILDER'!C13+'CRITERIA BUILDER'!C16)&IF('TECHNICAL SCORING'!J23="Yes"," (meets minimum threshold). ",IF('TECHNICAL SCORING'!J23="No"," (below minimum threshold — cannot proceed to award). ",". "))&"Financial capacity screened as "&'FINANCIAL CAPACITY'!AB23&IF('FINANCIAL CAPACITY'!AB23="High Risk",". Committee should request clarification on the bidder's financial position, including any negative equity, accumulated losses, or debt service concerns, before proceeding. ",IF('FINANCIAL CAPACITY'!AB23="Stretched",". Financial position is tight; Committee should record specific concerns. ",IF('FINANCIAL CAPACITY'!AB23="No Data",". No financial statements or figures were entered. Committee should request evidence of financial capacity before proceeding. ",IF('FINANCIAL CAPACITY'!AB23="Incomplete",". Financial submission is incomplete. Committee should request the missing figures. ",". "))))&IF(AND(ISNUMBER('COMMERCIAL EVAL'!F23),'COMMERCIAL EVAL'!F23>0),"Evaluated price (incl VAT): TTD "&TEXT('COMMERCIAL EVAL'!F23,"#,##0")&". Price score: "&TEXT(IF(ISNUMBER('COMMERCIAL EVAL'!H23),'COMMERCIAL EVAL'!H23,0),"0.00")&" of "&'CRITERIA BUILDER'!C15&". ","Price not evaluated. ")&"Total: "&TEXT(IF(ISNUMBER(DASHBOARD!H27),DASHBOARD!H27,0),"0.00")&" of 100. "&IF(ISNUMBER(DASHBOARD!A27),"Rank: "&DASHBOARD!A27&". ","")&"Status: "&DASHBOARD!I27&"."&IF('TECHNICAL SCORING'!K23=""," [Committee to record specific evidence for manual technical scores.]"," Evaluator note: "&'TECHNICAL SCORING'!K23),"Responsiveness not yet recorded."))))
A46: =IF(LEN('BIDDER REGISTER'!B24)=0,"","• "&'BIDDER REGISTER'!B24&" — "&IF(RESPONSIVENESS!J24="Non-responsive","Non-responsive to mandatory requirements. Excluded from scored evaluation.",IF(RESPONSIVENESS!J24="Incomplete","Responsiveness assessment incomplete. Not evaluated for scoring until mandatory checks are completed.",IF(RESPONSIVENESS!J24="Responsive","Responsive to mandatory requirements. "&"Technical score: "&IF(ISNUMBER('TECHNICAL SCORING'!I24),'TECHNICAL SCORING'!I24,0)&" of "&('CRITERIA BUILDER'!C9+'CRITERIA BUILDER'!C10+'CRITERIA BUILDER'!C11+'CRITERIA BUILDER'!C12+'CRITERIA BUILDER'!C13+'CRITERIA BUILDER'!C16)&IF('TECHNICAL SCORING'!J24="Yes"," (meets minimum threshold). ",IF('TECHNICAL SCORING'!J24="No"," (below minimum threshold — cannot proceed to award). ",". "))&"Financial capacity screened as "&'FINANCIAL CAPACITY'!AB24&IF('FINANCIAL CAPACITY'!AB24="High Risk",". Committee should request clarification on the bidder's financial position, including any negative equity, accumulated losses, or debt service concerns, before proceeding. ",IF('FINANCIAL CAPACITY'!AB24="Stretched",". Financial position is tight; Committee should record specific concerns. ",IF('FINANCIAL CAPACITY'!AB24="No Data",". No financial statements or figures were entered. Committee should request evidence of financial capacity before proceeding. ",IF('FINANCIAL CAPACITY'!AB24="Incomplete",". Financial submission is incomplete. Committee should request the missing figures. ",". "))))&IF(AND(ISNUMBER('COMMERCIAL EVAL'!F24),'COMMERCIAL EVAL'!F24>0),"Evaluated price (incl VAT): TTD "&TEXT('COMMERCIAL EVAL'!F24,"#,##0")&". Price score: "&TEXT(IF(ISNUMBER('COMMERCIAL EVAL'!H24),'COMMERCIAL EVAL'!H24,0),"0.00")&" of "&'CRITERIA BUILDER'!C15&". ","Price not evaluated. ")&"Total: "&TEXT(IF(ISNUMBER(DASHBOARD!H28),DASHBOARD!H28,0),"0.00")&" of 100. "&IF(ISNUMBER(DASHBOARD!A28),"Rank: "&DASHBOARD!A28&". ","")&"Status: "&DASHBOARD!I28&"."&IF('TECHNICAL SCORING'!K24=""," [Committee to record specific evidence for manual technical scores.]"," Evaluator note: "&'TECHNICAL SCORING'!K24),"Responsiveness not yet recorded."))))
A47: =IF(LEN('BIDDER REGISTER'!B25)=0,"","• "&'BIDDER REGISTER'!B25&" — "&IF(RESPONSIVENESS!J25="Non-responsive","Non-responsive to mandatory requirements. Excluded from scored evaluation.",IF(RESPONSIVENESS!J25="Incomplete","Responsiveness assessment incomplete. Not evaluated for scoring until mandatory checks are completed.",IF(RESPONSIVENESS!J25="Responsive","Responsive to mandatory requirements. "&"Technical score: "&IF(ISNUMBER('TECHNICAL SCORING'!I25),'TECHNICAL SCORING'!I25,0)&" of "&('CRITERIA BUILDER'!C9+'CRITERIA BUILDER'!C10+'CRITERIA BUILDER'!C11+'CRITERIA BUILDER'!C12+'CRITERIA BUILDER'!C13+'CRITERIA BUILDER'!C16)&IF('TECHNICAL SCORING'!J25="Yes"," (meets minimum threshold). ",IF('TECHNICAL SCORING'!J25="No"," (below minimum threshold — cannot proceed to award). ",". "))&"Financial capacity screened as "&'FINANCIAL CAPACITY'!AB25&IF('FINANCIAL CAPACITY'!AB25="High Risk",". Committee should request clarification on the bidder's financial position, including any negative equity, accumulated losses, or debt service concerns, before proceeding. ",IF('FINANCIAL CAPACITY'!AB25="Stretched",". Financial position is tight; Committee should record specific concerns. ",IF('FINANCIAL CAPACITY'!AB25="No Data",". No financial statements or figures were entered. Committee should request evidence of financial capacity before proceeding. ",IF('FINANCIAL CAPACITY'!AB25="Incomplete",". Financial submission is incomplete. Committee should request the missing figures. ",". "))))&IF(AND(ISNUMBER('COMMERCIAL EVAL'!F25),'COMMERCIAL EVAL'!F25>0),"Evaluated price (incl VAT): TTD "&TEXT('COMMERCIAL EVAL'!F25,"#,##0")&". Price score: "&TEXT(IF(ISNUMBER('COMMERCIAL EVAL'!H25),'COMMERCIAL EVAL'!H25,0),"0.00")&" of "&'CRITERIA BUILDER'!C15&". ","Price not evaluated. ")&"Total: "&TEXT(IF(ISNUMBER(DASHBOARD!H29),DASHBOARD!H29,0),"0.00")&" of 100. "&IF(ISNUMBER(DASHBOARD!A29),"Rank: "&DASHBOARD!A29&". ","")&"Status: "&DASHBOARD!I29&"."&IF('TECHNICAL SCORING'!K25=""," [Committee to record specific evidence for manual technical scores.]"," Evaluator note: "&'TECHNICAL SCORING'!K25),"Responsiveness not yet recorded."))))
A48: =IF(LEN('BIDDER REGISTER'!B26)=0,"","• "&'BIDDER REGISTER'!B26&" — "&IF(RESPONSIVENESS!J26="Non-responsive","Non-responsive to mandatory requirements. Excluded from scored evaluation.",IF(RESPONSIVENESS!J26="Incomplete","Responsiveness assessment incomplete. Not evaluated for scoring until mandatory checks are completed.",IF(RESPONSIVENESS!J26="Responsive","Responsive to mandatory requirements. "&"Technical score: "&IF(ISNUMBER('TECHNICAL SCORING'!I26),'TECHNICAL SCORING'!I26,0)&" of "&('CRITERIA BUILDER'!C9+'CRITERIA BUILDER'!C10+'CRITERIA BUILDER'!C11+'CRITERIA BUILDER'!C12+'CRITERIA BUILDER'!C13+'CRITERIA BUILDER'!C16)&IF('TECHNICAL SCORING'!J26="Yes"," (meets minimum threshold). ",IF('TECHNICAL SCORING'!J26="No"," (below minimum threshold — cannot proceed to award). ",". "))&"Financial capacity screened as "&'FINANCIAL CAPACITY'!AB26&IF('FINANCIAL CAPACITY'!AB26="High Risk",". Committee should request clarification on the bidder's financial position, including any negative equity, accumulated losses, or debt service concerns, before proceeding. ",IF('FINANCIAL CAPACITY'!AB26="Stretched",". Financial position is tight; Committee should record specific concerns. ",IF('FINANCIAL CAPACITY'!AB26="No Data",". No financial statements or figures were entered. Committee should request evidence of financial capacity before proceeding. ",IF('FINANCIAL CAPACITY'!AB26="Incomplete",". Financial submission is incomplete. Committee should request the missing figures. ",". "))))&IF(AND(ISNUMBER('COMMERCIAL EVAL'!F26),'COMMERCIAL EVAL'!F26>0),"Evaluated price (incl VAT): TTD "&TEXT('COMMERCIAL EVAL'!F26,"#,##0")&". Price score: "&TEXT(IF(ISNUMBER('COMMERCIAL EVAL'!H26),'COMMERCIAL EVAL'!H26,0),"0.00")&" of "&'CRITERIA BUILDER'!C15&". ","Price not evaluated. ")&"Total: "&TEXT(IF(ISNUMBER(DASHBOARD!H30),DASHBOARD!H30,0),"0.00")&" of 100. "&IF(ISNUMBER(DASHBOARD!A30),"Rank: "&DASHBOARD!A30&". ","")&"Status: "&DASHBOARD!I30&"."&IF('TECHNICAL SCORING'!K26=""," [Committee to record specific evidence for manual technical scores.]"," Evaluator note: "&'TECHNICAL SCORING'!K26),"Responsiveness not yet recorded."))))
A50: 9. NON-RESPONSIVE AND INCOMPLETE BIDDERS
A51: =IF(COUNTIF(RESPONSIVENESS!J7:J26,"Non-responsive")+COUNTIF(RESPONSIVENESS!J7:J26,"Incomplete")=0,"No non-responsive or incomplete submissions were recorded.","The following bidder(s) were not evaluated for scoring. Reasons must be recorded on the RESPONSIVENESS tab: "&IF(RESPONSIVENESS!J7="Non-responsive",RESPONSIVENESS!A7&" (Non-responsive)"&IF(RESPONSIVENESS!K7<>""," — "&RESPONSIVENESS!K7,"")&"; ","")&IF(RESPONSIVENESS!J8="Non-responsive",RESPONSIVENESS!A8&" (Non-responsive)"&IF(RESPONSIVENESS!K8<>""," — "&RESPONSIVENESS!K8,"")&"; ","")&IF(RESPONSIVENESS!J9="Non-responsive",RESPONSIVENESS!A9&" (Non-responsive)"&IF(RESPONSIVENESS!K9<>""," — "&RESPONSIVENESS!K9,"")&"; ","")&IF(RESPONSIVENESS!J10="Non-responsive",RESPONSIVENESS!A10&" (Non-responsive)"&IF(RESPONSIVENESS!K10<>""," — "&RESPONSIVENESS!K10,"")&"; ","")&IF(RESPONSIVENESS!J11="Non-responsive",RESPONSIVENESS!A11&" (Non-responsive)"&IF(RESPONSIVENESS!K11<>""," — "&RESPONSIVENESS!K11,"")&"; ","")&IF(RESPONSIVENESS!J12="Non-responsive",RESPONSIVENESS!A12&" (Non-responsive)"&IF(RESPONSIVENESS!K12<>""," — "&RESPONSIVENESS!K12,"")&"; ","")&IF(RESPONSIVENESS!J13="Non-responsive",RESPONSIVENESS!A13&" (Non-responsive)"&IF(RESPONSIVENESS!K13<>""," — "&RESPONSIVENESS!K13,"")&"; ","")&IF(RESPONSIVENESS!J14="Non-responsive",RESPONSIVENESS!A14&" (Non-responsive)"&IF(RESPONSIVENESS!K14<>""," — "&RESPONSIVENESS!K14,"")&"; ","")&IF(RESPONSIVENESS!J15="Non-responsive",RESPONSIVENESS!A15&" (Non-responsive)"&IF(RESPONSIVENESS!K15<>""," — "&RESPONSIVENESS!K15,"")&"; ","")&IF(RESPONSIVENESS!J16="Non-responsive",RESPONSIVENESS!A16&" (Non-responsive)"&IF(RESPONSIVENESS!K16<>""," — "&RESPONSIVENESS!K16,"")&"; ","")&IF(RESPONSIVENESS!J17="Non-responsive",RESPONSIVENESS!A17&" (Non-responsive)"&IF(RESPONSIVENESS!K17<>""," — "&RESPONSIVENESS!K17,"")&"; ","")&IF(RESPONSIVENESS!J18="Non-responsive",RESPONSIVENESS!A18&" (Non-responsive)"&IF(RESPONSIVENESS!K18<>""," — "&RESPONSIVENESS!K18,"")&"; ","")&IF(RESPONSIVENESS!J19="Non-responsive",RESPONSIVENESS!A19&" (Non-responsive)"&IF(RESPONSIVENESS!K19<>""," — "&RESPONSIVENESS!K19,"")&"; ","")&IF(RESPONSIVENESS!J20="Non-responsive",RESPONSIVENESS!A20&" (Non-responsive)"&IF(RESPONSIVENESS!K20<>""," — "&RESPONSIVENESS!K20,"")&"; ","")&IF(RESPONSIVENESS!J21="Non-responsive",RESPONSIVENESS!A21&" (Non-responsive)"&IF(RESPONSIVENESS!K21<>""," — "&RESPONSIVENESS!K21,"")&"; ","")&IF(RESPONSIVENESS!J22="Non-responsive",RESPONSIVENESS!A22&" (Non-responsive)"&IF(RESPONSIVENESS!K22<>""," — "&RESPONSIVENESS!K22,"")&"; ","")&IF(RESPONSIVENESS!J23="Non-responsive",RESPONSIVENESS!A23&" (Non-responsive)"&IF(RESPONSIVENESS!K23<>""," — "&RESPONSIVENESS!K23,"")&"; ","")&IF(RESPONSIVENESS!J24="Non-responsive",RESPONSIVENESS!A24&" (Non-responsive)"&IF(RESPONSIVENESS!K24<>""," — "&RESPONSIVENESS!K24,"")&"; ","")&IF(RESPONSIVENESS!J25="Non-responsive",RESPONSIVENESS!A25&" (Non-responsive)"&IF(RESPONSIVENESS!K25<>""," — "&RESPONSIVENESS!K25,"")&"; ","")&IF(RESPONSIVENESS!J26="Non-responsive",RESPONSIVENESS!A26&" (Non-responsive)"&IF(RESPONSIVENESS!K26<>""," — "&RESPONSIVENESS!K26,"")&"; ","")&IF(RESPONSIVENESS!J7="Incomplete",RESPONSIVENESS!A7&" (Incomplete)"&IF(RESPONSIVENESS!K7<>""," — "&RESPONSIVENESS!K7,"")&"; ","")&IF(RESPONSIVENESS!J8="Incomplete",RESPONSIVENESS!A8&" (Incomplete)"&IF(RESPONSIVENESS!K8<>""," — "&RESPONSIVENESS!K8,"")&"; ","")&IF(RESPONSIVENESS!J9="Incomplete",RESPONSIVENESS!A9&" (Incomplete)"&IF(RESPONSIVENESS!K9<>""," — "&RESPONSIVENESS!K9,"")&"; ","")&IF(RESPONSIVENESS!J10="Incomplete",RESPONSIVENESS!A10&" (Incomplete)"&IF(RESPONSIVENESS!K10<>""," — "&RESPONSIVENESS!K10,"")&"; ","")&IF(RESPONSIVENESS!J11="Incomplete",RESPONSIVENESS!A11&" (Incomplete)"&IF(RESPONSIVENESS!K11<>""," — "&RESPONSIVENESS!K11,"")&"; ","")&IF(RESPONSIVENESS!J12="Incomplete",RESPONSIVENESS!A12&" (Incomplete)"&IF(RESPONSIVENESS!K12<>""," — "&RESPONSIVENESS!K12,"")&"; ","")&IF(RESPONSIVENESS!J13="Incomplete",RESPONSIVENESS!A13&" (Incomplete)"&IF(RESPONSIVENESS!K13<>""," — "&RESPONSIVENESS!K13,"")&"; ","")&IF(RESPONSIVENESS!J14="Incomplete",RESPONSIVENESS!A14&" (Incomplete)"&IF(RESPONSIVENESS!K14<>""," — "&RESPONSIVENESS!K14,"")&"; ","")&IF(RESPONSIVENESS!J15="Incomplete",RESPONSIVENESS!A15&" (Incomplete)"&IF(RESPONSIVENESS!K15<>""," — "&RESPONSIVENESS!K15,"")&"; ","")&IF(RESPONSIVENESS!J16="Incomplete",RESPONSIVENESS!A16&" (Incomplete)"&IF(RESPONSIVENESS!K16<>""," — "&RESPONSIVENESS!K16,"")&"; ","")&IF(RESPONSIVENESS!J17="Incomplete",RESPONSIVENESS!A17&" (Incomplete)"&IF(RESPONSIVENESS!K17<>""," — "&RESPONSIVENESS!K17,"")&"; ","")&IF(RESPONSIVENESS!J18="Incomplete",RESPONSIVENESS!A18&" (Incomplete)"&IF(RESPONSIVENESS!K18<>""," — "&RESPONSIVENESS!K18,"")&"; ","")&IF(RESPONSIVENESS!J19="Incomplete",RESPONSIVENESS!A19&" (Incomplete)"&IF(RESPONSIVENESS!K19<>""," — "&RESPONSIVENESS!K19,"")&"; ","")&IF(RESPONSIVENESS!J20="Incomplete",RESPONSIVENESS!A20&" (Incomplete)"&IF(RESPONSIVENESS!K20<>""," — "&RESPONSIVENESS!K20,"")&"; ","")&IF(RESPONSIVENESS!J21="Incomplete",RESPONSIVENESS!A21&" (Incomplete)"&IF(RESPONSIVENESS!K21<>""," — "&RESPONSIVENESS!K21,"")&"; ","")&IF(RESPONSIVENESS!J22="Incomplete",RESPONSIVENESS!A22&" (Incomplete)"&IF(RESPONSIVENESS!K22<>""," — "&RESPONSIVENESS!K22,"")&"; ","")&IF(RESPONSIVENESS!J23="Incomplete",RESPONSIVENESS!A23&" (Incomplete)"&IF(RESPONSIVENESS!K23<>""," — "&RESPONSIVENESS!K23,"")&"; ","")&IF(RESPONSIVENESS!J24="Incomplete",RESPONSIVENESS!A24&" (Incomplete)"&IF(RESPONSIVENESS!K24<>""," — "&RESPONSIVENESS!K24,"")&"; ","")&IF(RESPONSIVENESS!J25="Incomplete",RESPONSIVENESS!A25&" (Incomplete)"&IF(RESPONSIVENESS!K25<>""," — "&RESPONSIVENESS!K25,"")&"; ","")&IF(RESPONSIVENESS!J26="Incomplete",RESPONSIVENESS!A26&" (Incomplete)"&IF(RESPONSIVENESS!K26<>""," — "&RESPONSIVENESS!K26,"")&"; ","")) -> No non-responsive or incomplete submissions were recorded.
A53: 10. RECOMMENDATION
A54: =IFERROR("Based on the workbook results, the highest-ranked evaluated bidder is "&INDEX(DASHBOARD!B11:B30,MATCH(1,DASHBOARD!A11:A30,0))&" with a total score of "&TEXT(INDEX(DASHBOARD!H11:H30,MATCH(1,DASHBOARD!A11:A30,0)),"0.00")&" out of 100 points."&IF(OR(INDEX(DASHBOARD!E11:E30,MATCH(1,DASHBOARD!A11:A30,0))="High Risk",INDEX(DASHBOARD!E11:E30,MATCH(1,DASHBOARD!A11:A30,0))="Stretched",INDEX(DASHBOARD!E11:E30,MATCH(1,DASHBOARD!A11:A30,0))="No Data",INDEX(DASHBOARD!E11:E30,MATCH(1,DASHBOARD!A11:A30,0))="Incomplete")," The Committee notes that this bidder's financial capacity is screened as "&INDEX(DASHBOARD!E11:E30,MATCH(1,DASHBOARD!A11:A30,0))&". The Committee must obtain and record specific clarification or additional evidence on financial capacity before recommending award.","")&IFERROR(" The next-ranked bidder is "&INDEX(DASHBOARD!B11:B30,MATCH(2,DASHBOARD!A11:A30,0))&" with "&TEXT(INDEX(DASHBOARD!H11:H30,MATCH(2,DASHBOARD!A11:A30,0)),"0.00")&" points, to be considered if the highest-ranked bidder cannot proceed to award.","")&" This recommendation remains subject to the Committee's review of manual technical evidence, the clarifications log, availability of funds, and all required approvals under the Public Procurement and Disposal of Public Property Act.","No recommendation is generated until at least one eligible bidder has been scored.") -> No recommendation is generated until at least one eligible bidder has been scored.
A56: 11. SUMMARY COMPARISON TABLE
A58: Rank | B58: Bidder | C58: Responsive | D58: Tech Score | E58: Financial Rating | F58: Price Score | G58: Total Score | H58: Status
A59: =DASHBOARD!A11 | B59: =DASHBOARD!B11 | C59: =DASHBOARD!C11 | D59: =DASHBOARD!D11 | E59: =DASHBOARD!E11 | F59: =DASHBOARD!G11 | G59: =DASHBOARD!H11 | H59: =DASHBOARD!I11
A60: =DASHBOARD!A12 | B60: =DASHBOARD!B12 | C60: =DASHBOARD!C12 | D60: =DASHBOARD!D12 | E60: =DASHBOARD!E12 | F60: =DASHBOARD!G12 | G60: =DASHBOARD!H12 | H60: =DASHBOARD!I12
A61: =DASHBOARD!A13 | B61: =DASHBOARD!B13 | C61: =DASHBOARD!C13 | D61: =DASHBOARD!D13 | E61: =DASHBOARD!E13 | F61: =DASHBOARD!G13 | G61: =DASHBOARD!H13 | H61: =DASHBOARD!I13
A62: =DASHBOARD!A14 | B62: =DASHBOARD!B14 | C62: =DASHBOARD!C14 | D62: =DASHBOARD!D14 | E62: =DASHBOARD!E14 | F62: =DASHBOARD!G14 | G62: =DASHBOARD!H14 | H62: =DASHBOARD!I14
A63: =DASHBOARD!A15 | B63: =DASHBOARD!B15 | C63: =DASHBOARD!C15 | D63: =DASHBOARD!D15 | E63: =DASHBOARD!E15 | F63: =DASHBOARD!G15 | G63: =DASHBOARD!H15 | H63: =DASHBOARD!I15
A64: =DASHBOARD!A16 | B64: =DASHBOARD!B16 | C64: =DASHBOARD!C16 | D64: =DASHBOARD!D16 | E64: =DASHBOARD!E16 | F64: =DASHBOARD!G16 | G64: =DASHBOARD!H16 | H64: =DASHBOARD!I16
A65: =DASHBOARD!A17 | B65: =DASHBOARD!B17 | C65: =DASHBOARD!C17 | D65: =DASHBOARD!D17 | E65: =DASHBOARD!E17 | F65: =DASHBOARD!G17 | G65: =DASHBOARD!H17 | H65: =DASHBOARD!I17
A66: =DASHBOARD!A18 | B66: =DASHBOARD!B18 | C66: =DASHBOARD!C18 | D66: =DASHBOARD!D18 | E66: =DASHBOARD!E18 | F66: =DASHBOARD!G18 | G66: =DASHBOARD!H18 | H66: =DASHBOARD!I18
A67: =DASHBOARD!A19 | B67: =DASHBOARD!B19 | C67: =DASHBOARD!C19 | D67: =DASHBOARD!D19 | E67: =DASHBOARD!E19 | F67: =DASHBOARD!G19 | G67: =DASHBOARD!H19 | H67: =DASHBOARD!I19
A68: =DASHBOARD!A20 | B68: =DASHBOARD!B20 | C68: =DASHBOARD!C20 | D68: =DASHBOARD!D20 | E68: =DASHBOARD!E20 | F68: =DASHBOARD!G20 | G68: =DASHBOARD!H20 | H68: =DASHBOARD!I20
A69: =DASHBOARD!A21 | B69: =DASHBOARD!B21 | C69: =DASHBOARD!C21 | D69: =DASHBOARD!D21 | E69: =DASHBOARD!E21 | F69: =DASHBOARD!G21 | G69: =DASHBOARD!H21 | H69: =DASHBOARD!I21
A70: =DASHBOARD!A22 | B70: =DASHBOARD!B22 | C70: =DASHBOARD!C22 | D70: =DASHBOARD!D22 | E70: =DASHBOARD!E22 | F70: =DASHBOARD!G22 | G70: =DASHBOARD!H22 | H70: =DASHBOARD!I22
... A78: =DASHBOARD!A30 | B78: =DASHBOARD!B30 | C78: =DASHBOARD!C30 | D78: =DASHBOARD!D30 | E78: =DASHBOARD!E30 | F78: =DASHBOARD!G30 | G78: =DASHBOARD!H30 | H78: =DASHBOARD!I30
A82: 12. COMMITTEE SIGNATURES
A84: Name | B84: Designation | C84: Signature | D84: Date

Sheet SOURCE REGISTER
A1: SOURCE REGISTER AND CONTROL NOTE
A2: Records the authority, assumptions and limitations used in this workbook.
A4: Source / Control | B4: Use in workbook | C4: Reference / URL / File | D4: Committee note
A5: Public Procurement and Disposal of Public Property Act | B5: Governing statutory framework | C5: Act No. 1 of 2015 (as amended) | D5: Apply the current version of the Act and related regulations.
A6: OPR Pre-Qualification and Pre-Selection Guidelines | B6: Prequalification and evidence-based due diligence | C6: Office of Procurement Regulation (T&T) | D6: Use line of business, value category and evidence-based records.
A7: OPR Ethical Code of Conduct | B7: Ethics, confidentiality, conflict of interest | C7: Office of Procurement Regulation (T&T) | D7: Every committee member signs before evaluation begins.
A8: Approved tender documents (RFP/ITT) | B8: Source of criteria, weights, mandatory items and pass marks | C8: As issued by the public body | D8: Criteria and weights in this workbook must match the issued documents.
A9: Committee Terms of Reference | B9: Appointment, quorum, decision rules | C9: As approved by the Accounting Officer | D9: File the ToR with the evaluation record.
A10: Bidder submissions | B10: Primary source for figures, prices, declarations | C10: As received via the approved tender box or portal | D10: Every figure must be traced to an original submitted document.
A11: Financial Capacity screening approach | B11: Ratio calculation and screening rating logic | C11: Companion internal methodology | D11: Screening aid, not the final decision-maker.
A12: Committee Control Rule | B12: Protects against post-opening changes to criteria | C12: Internal governance rule | D12: Criteria are fixed before tender opening. No changes after.
A13: Limitation Statement | B13: Guards against black-box decisions | C13: Internal governance rule | D13: This workbook supports Committee judgement. It does not replace it.
A14: SCRUTINY RULE: Every finding must be traceable to the tender criteria, a source document, a score or calculation, and a written reason. If the workbook output cannot be defended from the file, do not use it as final wording.

Sheet LISTS
A1: SYSTEM LISTS
A2: Dropdown values and lookup tables. Do not edit unless the chairperson authorises it.
I3: Reference guidance — not a dropdown. Explains which model suits each tender type.
A4: PassFailNA | B4: StatusList | C4: TenderType (editable) | D4: ProcurementMethod (editable) | E4: Rating | F4: Multiplier | G4: Plain Meaning | I4: Tender Type (guidance only) | J4: Suggested Evaluation Model | K4: Notes
A5: Pass | B5: Not Started | C5: Ordinary Goods | D5: Open Tender | E5: Strong | F5: 1 | G5: Core evidence is strong for the sector and contract. | I5: Ordinary Goods | J5: Price can carry higher weight after compliance. | K5: Use where goods are simple and standardized.
A6: Fail | B6: In Progress | C6: Specialist Equipment / Safety | D6: Selective Tender | E6: Adequate | F6: 0.8 | G6: Usable, with no major warning sign. | I6: Specialist Equipment / Safety | J6: Technical and support must dominate. | K6: Use for mission/life safety items.
A7: N/A | B7: Complete | C7: Works / Refurbishment / Construction | D7: Request for Proposals (RFP) | E7: Adequate with Caution | F7: 0.6 | G7: Usable, but the Committee should record the risk. | I7: Works / Refurbishment / Construction | J7: Technical, method, HSE and financial capacity matter. | K7: Use for contractors and works.
B8: Open | C8: Consultancy / Professional Services | D8: Request for Quotations (RFQ) | E8: Stretched | F8: 0.3 | G8: Weak or tight financial position. | I8: Consultancy / Professional Services | J8: Key experts and methodology dominate. | K8: Lowest price should not dominate.
B9: Closed | C9: Events / Logistics / Public Outreach | D9: Limited Tender | E9: High Risk | F9: 0 | G9: Material concern; do not treat as safe without strong clarification. | I9: Events / Logistics / Public Outreach | J9: Logistics and delivery risk are central. | K9: Check staffing, backup and coordination.
B10: Yes | C10: Security Systems / CCTV / ICT | D10: Sole Source / Direct Contracting | E10: No Data | F10: 0 | G10: No usable financial evidence entered. | I10: Security Systems / CCTV / ICT | J10: Technical solution and after-sales support matter. | K10: Check authorization, warranty and SLA.
B11: No | C11: General Services | D11: Framework Agreement | E11: Incomplete | F11: 0 | G11: Required financial figures are missing. | I11: General Services | J11: Use balanced model. | K11: Adjust before tender issue.
B12: Responsive | E12: Specialist Review | F12: 0 | G12: Ordinary ratios may not be the best test.
B13: Non-responsive
B14: Incomplete
B15: Strong
